Workbook

Sheet Dashboard
B1: SALES INTELLIGENCE DASHBOARD
B2: ="Sales transactions | "&TEXT(Analysis!$B$12,"dd mmm yyyy")&" to "&TEXT(Analysis!$B$13,"dd mmm yyyy")&" | "&Analysis!$B$36&" transactions | Last refreshed "&TEXT(NOW(),"dd mmm yyyy hh:mm:ss") -> Sales transactions | 01 Jan 2023 to 01 Jan 2024 | 1000 transactions | Last refreshed 24 Oct 2026 15:53:40
B4: KEY PERFORMANCE INDICATORS
B5: TOTAL SALES | E5: TRANSACTIONS | H5: UNITS SOLD | K5: AVERAGE SALE | N5: AVG DISCOUNT | Q5: NET MARGIN %
B6: =Analysis!$B$35 -> 5019265.2 | E6: =Analysis!$B$36 -> 1000 | H6: =Analysis!$B$37 -> 25355 | K6: =Analysis!$B$38 -> 5019.2652 | N6: =Analysis!$B$40 -> 0.15239 | Q6: =Analysis!$B$46 -> -0.069629528
B7: =IF(H51>=0,"▲ ","▼ ")&TEXT(ABS(H51),"0.0%")&" vs target" -> ▼ 8.7% vs target | E7: =IF(H52>=0,"▲ ","▼ ")&TEXT(ABS(H52),"0.0%")&" vs target" -> ▼ 9.1% vs target | H7: =TEXT(Analysis!$B$37/Analysis!$B$36,"0.0")&" units per sale" -> 25.4 units per sale | K7: =IF(H53>=0,"▲ ","▼ ")&TEXT(ABS(H53),"0.0%")&" vs target" -> ▲ 0.4% vs target | N7: ="Break-even: "&TEXT(Analysis!$B$49,"0.0%") -> Break-even: 9.2% | Q7: =IF(H54>=0,"▲ ","▼ ")&TEXT(ABS(H54)*100,"0.0")&" pts vs target" -> ▼ 12.0 pts vs target
B9: INTERACTIVE FILTERS: choose from the dropdowns, the charts below update instantly
B10: REGION | E10: PRODUCT CATEGORY | H10: SALES REP | K10: SALES CHANNEL | N10: FROM DATE | Q10: TO DATE
B11: All | E11: All | H11: All | K11: All | N11: 44927 | Q11: 45322
B13: SELECTED SALES | E13: TRANSACTIONS | H13: UNITS | K13: AVG DISCOUNT | N13: NET MARGIN % | Q13: VIEW
B14: =Calc!B66 -> 5019265.2 | E14: =Calc!B67 -> 1000 | H14: =Calc!B68 -> 25355 | K14: =Calc!B69 -> 0.15239 | N14: =Calc!B70 -> -0.069629528 | Q14: =Calc!B72 -> Full dataset (no filters)
B16: TRENDS & MIX (respond to the filters above)
B17: Monthly Sales Trend | K17: Sales by Region
B33: Sales by Product Category | H33: Sales by Sales Rep | N33: Net Margin % by Discount Band
B49: PERFORMANCE VS TARGET | TOP 10 REGION-REP COMBINATIONS
B50: KPI | D50: Actual | F50: Target | H50: Variance | I50: Status | K50: Rank | L50: Region-Rep | O50: Sales | Q50: Share of sales
B51: Total Sales | D51: =Analysis!$B$35 -> 5019265.2 | F51: 5500000 | H51: =D51/F51-1 -> -0.087406322 | I51: =IF(H51>=0,"On target",IF(H51>=-0.1,"Watch","Behind")) -> Watch | K51: =Performance!L4 -> 1 | L51: =Performance!M4 -> South-David | O51: =Performance!N4 -> 311416.99 | Q51: =Performance!O4 -> 0.062044338
B52: Transactions | D52: =Analysis!$B$36 -> 1000 | F52: 1100 | H52: =D52/F52-1 -> -0.090909091 | I52: =IF(H52>=0,"On target",IF(H52>=-0.1,"Watch","Behind")) -> Watch | K52: =Performance!L5 -> 2 | L52: =Performance!M5 -> East-Bob | O52: =Performance!N5 -> 309876.11 | Q52: =Performance!O5 -> 0.061737345
B53: Average Sale | D53: =Analysis!$B$38 -> 5019.2652 | F53: 5000 | H53: =D53/F53-1 -> 0.003853046 | I53: =IF(H53>=0,"On target",IF(H53>=-0.1,"Watch","Behind")) -> On target | K53: =Performance!L6 -> 3 | L53: =Performance!M6 -> North-Eve | O53: =Performance!N6 -> 304172.2 | Q53: =Performance!O6 -> 0.060600942
B54: Net Margin % | D54: =Analysis!$B$46 -> -0.069629528 | F54: 0.05 | H54: =D54-F54 -> -0.11962953 | I54: =IF(H54>=0,"On target",IF(H54>=-0.1,"Watch","Behind")) -> Behind | K54: =Performance!L7 -> 4 | L54: =Performance!M7 -> North-Charlie | O54: =Performance!N7 -> 299789.01 | Q54: =Performance!O7 -> 0.059727669
B55: Loss-making share (lower is better) | D55: =Analysis!$B$51 -> 0.604 | F55: 0.25 | H55: =F55-D55 -> -0.354 | I55: =IF(H55>=0,"On target",IF(H55>=-0.1,"Watch","Behind")) -> Behind | K55: =Performance!L8 -> 5 | L55: =Performance!M8 -> West-Bob | O55: =Performance!N8 -> 286449.28 | Q55: =Performance!O8 -> 0.057069963
B56: Yellow targets are placeholder assumptions, not dataset values. | K56: =Performance!L9 -> 6 | L56: =Performance!M9 -> East-David | O56: =Performance!N9 -> 284613.51 | Q56: =Performance!O9 -> 0.056704218
B57: Region-Rep tiers | K57: =Performance!L10 -> 7 | L57: =Performance!M10 -> North-David | O57: =Performance!N10 -> 282539.27 | Q57: =Performance!O10 -> 0.056290962
B58: High-Value | D58: =COUNTIF(Performance!$I$4:$I$23,"High-Value") -> 4 | F58: =SUMIF(Performance!$I$4:$I$23,"High-Value",Performance!$D$4:$D$23) -> 1225254.3 | H58: =F58/Analysis!$B$35 -> 0.24411029 | K58: =Performance!L11 -> 8 | L58: =Performance!M11 -> West-David | O58: =Performance!N11 -> 263167.59 | Q58: =Performance!O11 -> 0.052431497
B59: Mid | D59: =COUNTIF(Performance!$I$4:$I$23,"Mid") -> 6 | F59: =SUMIF(Performance!$I$4:$I$23,"Mid",Performance!$D$4:$D$23) -> 1628759.6 | H59: =F59/Analysis!$B$35 -> 0.32450159 | K59: =Performance!L12 -> 9 | L59: =Performance!M12 -> East-Alice | O59: =Performance!N12 -> 260789.47 | Q59: =Performance!O12 -> 0.051957699
B60: Low | D60: =COUNTIF(Performance!$I$4:$I$23,"Low") -> 10 | F60: =SUMIF(Performance!$I$4:$I$23,"Low",Performance!$D$4:$D$23) -> 2165251.4 | H60: =F60/Analysis!$B$35 -> 0.43138812 | K60: =Performance!L13 -> 10 | L60: =Performance!M13 -> South-Bob | O60: =Performance!N13 -> 251200.43 | Q60: =Performance!O13 -> 0.050047252
B62: PIVOT TABLES, PIVOT CHARTS & SLICERS: the four slicers on the right filter every PivotTable and pivot chart (click an item; Ctrl-click for several; the funnel icon clears). Refresh All after data changes.
B63: Sales by Region | E63: Sales by Category | H63: Sales by Rep | K63: Sales by Month | N63: Sales by Payment
B64: Filter | E64: Filter | H64: Filter | K64: Filter | N64: Filter
B65: Product_Category | C65: - all - | E65: Region | F65: - all - | H65: Region | I65: - all - | K65: Region | L65: - all - | N65: Region | O65: - all -
B66: Sales_Channel | C66: - all - | E66: Sales_Channel | F66: - all - | H66: Product_Category | I66: - all - | K66: Product_Category | L66: - all - | N66: Product_Category | O66: - all -
B68: Region | C68: Sales ($) | E68: Product_Category | F68: Sales ($) | H68: Sales_Rep | I68: Sales ($) | K68: Year_Month | L68: Sales ($) | N68: Payment_Method | O68: Sales ($)
B69: East | C69: 1259792.9 | E69: Clothing | F69: 1313474.4 | H69: Alice | I69: 965541.77 | K69: 2023-01 | L69: 476092.36 | N69: Bank Transfer | O69: 1717363.2
B70: North | C70: 1369612.5 | E70: Electronics | F70: 1243499.6 | H70: Bob | I70: 1080990.6 | K70: 2023-02 | L70: 368919.36 | N70: Cash | O70: 1544338.5
B71: South | C71: 1154250.9 | E71: Food | F71: 1201773.5 | H71: Charlie | I71: 860811.48 | K71: 2023-03 | L71: 402638.77 | N71: Credit Card | O71: 1757563.5
B72: West | C72: 1235608.9 | E72: Furniture | F72: 1260517.7 | H72: David | I72: 1141737.4 | K72: 2023-04 | L72: 438992.61 | N72: Grand Total | O72: 5019265.2
B73: Grand Total | C73: 5019265.2 | E73: Grand Total | F73: 5019265.2 | H73: Eve | I73: 970183.99 | K73: 2023-05 | L73: 389078.76
H74: Grand Total | I74: 5019265.2 | K74: 2023-06 | L74: 418458.34
K75: 2023-07 | L75: 374242.88
K76: 2023-08 | L76: 443171.28
K77: 2023-09 | L77: 367837.6
K78: 2023-10 | L78: 460378.78
K79: 2023-11 | L79: 467482.9
K80: 2023-12 | L80: 392643.58
K81: 2024-01 | L81: 19328.01
K82: Grand Total | L82: 5019265.2
B83: Pivot Chart: Sales by Region (Bar) | H83: Pivot Chart: Monthly Sales (Line) | N83: Pivot Chart: Category Mix (Pie)
B100: Pivot charts are linked to the PivotTable cell ranges above. Slicers (right of the pivot band) and the report filters drive the pivot band; the INTERACTIVE FILTERS band at the top drives the upper charts.

Sheet Report
B1: Final Report: Insights & Storytelling
B2: Every sentence below is a formula, so it updates with the data. Targets and scenario inputs are placeholder assumptions.
B4: 1. The big picture
B5: ="Sales total "&TEXT(Analysis!$B$35,"$#,##0")&" from "&TEXT(Analysis!$B$36,"#,##0")&" transactions ("&TEXT(Analysis!$B$37,"#,##0")&" units) between "&TEXT(Analysis!$B$12,"d mmm yyyy")&" and "&TEXT(Analysis!$B$13,"d mmm yyyy")&". The average sale is "&TEXT(Analysis!$B$38,"$#,##0")&" and the median "&TEXT(Analysis!$B$39,"$#,##0")&"; individual sales range widely (coefficient of variation "&TEXT(Analysis!$B$202,"0%")&"), with "&Analysis!$B$203&" outliers beyond two standard deviations." -> Sales total $50,19,265 from 1,000 transactions (25,355 units) between 1 Jan 2023 and 1 Jan 2024. The average sale is $5,019 and the median $5,019; individual sales range widely (coefficient of variation 57%), with 0 outliers beyond two standard deviations.
B7: 2. Where and what
B8: ="Region: "&Analysis!$B$61&" leads with "&TEXT(MAX(Analysis!$C$56:$C$59),"$#,##0")&" and "&Analysis!$B$62&" trails with "&TEXT(MIN(Analysis!$C$56:$C$59),"$#,##0")&" (a "&TEXT(MAX(Analysis!$C$56:$C$59)/MIN(Analysis!$C$56:$C$59)-1,"0%")&" gap). Category: "&Analysis!$B$71&" leads ("&TEXT(MAX(Analysis!$C$66:$C$69),"$#,##0")&") and "&Analysis!$B$72&" is lowest ("&TEXT(MIN(Analysis!$C$66:$C$69),"$#,##0")&"). Sales are spread fairly evenly, so no single region or category carries the business." -> Region: North leads with $13,69,613 and South trails with $11,54,251 (a 19% gap). Category: Clothing leads ($13,13,474) and Food is lowest ($12,01,774). Sales are spread fairly evenly, so no single region or category carries the business.
B10: 3. People
B11: ="Top sales rep: "&Analysis!$B$82&" ("&TEXT(MAX(Analysis!$C$76:$C$80),"$#,##0")&"); lowest: "&Analysis!$B$83&" ("&TEXT(MIN(Analysis!$C$76:$C$80),"$#,##0")&"). The best Region-Rep combination is "&Performance!M4&" at "&TEXT(Performance!N4,"$#,##0")&"; "&COUNTIF(Performance!$Q$4:$Q$23,"A")&" of 20 combinations produce the first 80% of sales (Pareto class A)." -> Top sales rep: David ($11,41,737); lowest: Charlie ($8,60,811). The best Region-Rep combination is South-David at $3,11,417; 14 of 20 combinations produce the first 80% of sales (Pareto class A).
B13: 4. Channel and customers
B14: ="Retail sells "&TEXT(Analysis!C88,"$#,##0")&" versus Online "&TEXT(Analysis!C87,"$#,##0")&"; returning customers account for "&TEXT(Analysis!D96,"0.0%")&" of sales and new customers "&TEXT(Analysis!D95,"0.0%")&". The differences are small, so channel and customer type are not performance levers on their own. Most-used payment method: "&Analysis!$B$107&"." -> Retail sells $25,60,431 versus Online $24,58,834; returning customers account for 50.1% of sales and new customers 49.9%. The differences are small, so channel and customer type are not performance levers on their own. Most-used payment method: Credit Card.
B16: 5. Time patterns
B17: ="Best full month: "&INDEX(Analysis!B167:B178,MATCH(MAX(Analysis!E167:E178),Analysis!E167:E178,0))&"; weakest: "&INDEX(Analysis!B167:B178,MATCH(MIN(Analysis!E167:E178),Analysis!E167:E178,0))&". Best weekday: "&Analysis!$B$138&"; weakest: "&Analysis!$B$139&". Strongest quarter: "&Analysis!$B$149&". The monthly trend slope is "&TEXT('Regression Output'!$B$21,"$#,##0")&" per month with Significance F "&TEXT('Regression Output'!$F$14,"0.000")&": "&IF('Regression Output'!$F$14<0.05,"a significant trend.","no statistically significant trend, sales are flat with random swings.") -> Best full month: Jan-23; weakest: Sep-23. Best weekday: Thursday; weakest: Saturday. Strongest quarter: 2023-Q4. The monthly trend slope is $474 per month with Significance F 0.894: no statistically significant trend, sales are flat with random swings.
B19: 6. The discount story (key insight)
B20: ="The weighted average discount is "&TEXT(Analysis!$B$48,"0.0%")&" against a break-even level of "&TEXT(Analysis!$B$49,"0.0%")&" (the discount at which net margin on a list-price basis is zero). Net margin is "&TEXT(Analysis!$B$46,"0.0%")&" and "&TEXT(Analysis!$B$51,"0%")&" of sales ("&Analysis!$B$50&") lose money after discount. By band, net margin is "&TEXT(Analysis!H112,"0.0%")&" at 0-9% discount, "&TEXT(Analysis!H113,"0.0%")&" at 10-19% and "&TEXT(Analysis!H114,"0.0%")&" at 20%+. Discount is not buying larger sales: correlation of discount with Sales_Amount is only "&TEXT(Analysis!$B$204,"0.00")&"." -> The weighted average discount is 15.1% against a break-even level of 9.2% (the discount at which net margin on a list-price basis is zero). Net margin is -7.0% and 60% of sales (604) lose money after discount. By band, net margin is 4.5% at 0-9% discount, -5.8% at 10-19% and -20.8% at 20%+. Discount is not buying larger sales: correlation of discount with Sales_Amount is only 0.02.
B22: 7. Regression findings
B23: ='Regression Output'!A90&" "&'Regression Output'!A91&" "&'Regression Output'!A92 -> A) Trend: sales move $474 per month (R² 0.002, Significance F 0.894): NOT significant, so monthly sales are flat apart from random swings. B) Drivers: Quantity, Discount and Unit_Price together explain only 0.2% of Sales_Amount (Significance F 0.483): none of these fields predicts the size of a sale. C) Discount vs margin: every +1 percentage point of discount changes net margin by -1.14% (R² 0.223, p-value 0.0000): statistically significant.
B25: 8. Scenarios and Goal Seek
B26: ="Projected net margin: Base "&TEXT(Analysis!C222,"0.0%")&"; Discount discipline "&TEXT(Analysis!D222,"0.0%")&" (sales "&TEXT(Analysis!D219/Analysis!C219-1,"+0.0%;-0.0%")&"); Growth push "&TEXT(Analysis!E222,"0.0%")&"; Price rise "&TEXT(Analysis!F222,"0.0%")&". Goal Seek: to reach a "&TEXT(Analysis!$B$224,"0%")&" net margin the weighted discount must fall to "&TEXT(Analysis!$B$225,"0.0%")&", a change of "&TEXT(Analysis!$B$226*100,"0.0")&" percentage points." -> Projected net margin: Base -7.0%; Discount discipline -1.0% (sales +2.7%); Growth push -10.9%; Price rise -1.9%. Goal Seek: to reach a 5% net margin the weighted discount must fall to 4.4%, a change of -10.7 percentage points.
B28: 9. Data-quality findings
B29: ="(1) Sales_Amount does not reconcile to Quantity x Unit_Price (correlation "&TEXT(CORREL('Raw Data'!$O$2:$O$1001,'Raw Data'!$E$2:$E$1001),"0.00")&"), so margins use the list-price basis. (2) "&'Product IDs'!$P$12&" of "&COUNT('Product IDs'!A4:A103)&" Product_IDs appear under all four categories and only "&'Product IDs'!$P$9&" under one, so Product_ID is not a reliable product key. (3) There is no customer identifier, so customer-level analysis is not possible. (4) January 2024 contains a single day. (5) Floating-point noise in Unit_Price was rounded to 2 decimals." -> (1) Sales_Amount does not reconcile to Quantity x Unit_Price (correlation -0.03), so margins use the list-price basis. (2) 71 of 100 Product_IDs appear under all four categories and only 0 under one, so Product_ID is not a reliable product key. (3) There is no customer identifier, so customer-level analysis is not possible. (4) January 2024 contains a single day. (5) Floating-point noise in Unit_Price was rounded to 2 decimals.
B31: 10. Recommendations
B32: ="(1) Cap discounts: aim for a weighted discount near "&TEXT(Analysis!$B$225,"0%")&" and review every deal above 20% ("&COUNTIF('Raw Data'!$U$2:$U$1001,"20%+")&" sales). (2) Share the practices of "&Analysis!$B$82&" and coach "&Analysis!$B$83&". (3) Lift "&Analysis!$B$62&" with targeted campaigns. (4) Fix master data: unique product keys, a customer ID and reconciled sales amounts. (5) Track net margin by discount band monthly on the Dashboard." -> (1) Cap discounts: aim for a weighted discount near 4% and review every deal above 20% (380 sales). (2) Share the practices of David and coach Charlie. (3) Lift South with targeted campaigns. (4) Fix master data: unique product keys, a customer ID and reconciled sales amounts. (5) Track net margin by discount band monthly on the Dashboard.

Sheet Raw Data
A1: Product_ID | B1: Sale_Date | C1: Sales_Rep | D1: Region | E1: Sales_Amount | F1: Quantity_Sold | G1: Product_Category | H1: Unit_Cost | I1: Unit_Price | J1: Customer_Type | K1: Discount | L1: Payment_Method | M1: Sales_Channel | N1: Region_and_Sales_Rep | O1: List_Value | P1: Net_List_Value | Q1: COGS | R1: Net_Margin | S1: Net_Margin_Pct | T1: Loss_Flag | U1: Discount_Band | V1: Sales_Size | W1: Year_Month | X1: Month_End | Y1: Year_Quarter | Z1: Weekday | AA1: Weekday_No | AB1: Week_No | AC1: Day_Type | AD1: Days_Since_Sale | AE1: Age_Months | AF1: Rep_Code | AG1: Order_Code | AH1: Filter_Seq | AI1: X1_Quantity | AJ1: X2_Discount | AK1: X3_Unit_Price | AL1: Sales_Rank
A2: 1052 | B2: 44960 | C2: Bob | D2: North | E2: 5053.97 | F2: 18 | G2: Furniture | H2: 152.75 | I2: 267.22 | J2: Returning | K2: 0.09 | L2: Cash | M2: Online | N2: North-Bob | O2: =ROUND(F2*I2,2) -> 4809.96 | P2: =ROUND(F2*I2*(1-K2),2) -> 4377.06 | Q2: =ROUND(F2*H2,2) -> 2749.5 | R2: =P2-Q2 -> 1627.56 | S2: =IF(P2=0,0,R2/P2) -> 0.37183863 | T2: =IF(R2<0,"Loss","OK") -> OK | U2: =IF(K2<0.1,"0-9%",IF(K2<0.2,"10-19%","20%+")) -> 0-9% | V2: =IF(E2>=Analysis!$B$4,"High",IF(E2>=Analysis!$B$5,"Mid","Low")) -> Mid | W2: =TEXT(B2,"yyyy-mm") -> 2023-02 | X2: =EOMONTH(B2,0) -> 44985 | Y2: =YEAR(B2)&"-Q"&ROUNDUP(MONTH(B2)/3,0) -> 2023-Q1 | Z2: =TEXT(B2,"ddd") -> Fri | AA2: =WEEKDAY(B2,2) -> 5 | AB2: =WEEKNUM(B2,2) -> 6 | AC2: =IF(AA2>5,"Weekend","Weekday") -> Weekday | AD2: =TODAY()-B2 -> 1359 | AE2: =DATEDIF(B2,TODAY(),"M") -> 44 | AF2: =UPPER(LEFT(C2,3)) -> BOB | AG2: =UPPER(LEFT(D2,1))&UPPER(LEFT(M2,1))&"-"&TEXT(B2,"yymmdd")&"-"&TEXT(ROW()-1,"0000") -> NO-230203-0001 | AH2: =IF(AND(OR(Filter!$B$4="All",D2=Filter!$B$4),OR(Filter!$B$5="All",M2=Filter!$B$5),E2>=Filter!$B$6),MAX(AH$1:AH1)+1,"") | AI2: =F2 -> 18 | AJ2: =K2 -> 0.09 | AK2: =I2 -> 267.22 | AL2: =RANK(E2,$E$2:$E$1001,0)+COUNTIF($E$2:E2,E2)-1 -> 496
A3: 1093 | B3: 45037 | C3: Bob | D3: West | E3: 4384.02 | F3: 17 | G3: Furniture | H3: 3816.39 | I3: 4209.44 | J3: Returning | K3: 0.11 | L3: Cash | M3: Retail | N3: West-Bob | O3: =ROUND(F3*I3,2) -> 71560.48 | P3: =ROUND(F3*I3*(1-K3),2) -> 63688.83 | Q3: =ROUND(F3*H3,2) -> 64878.63 | R3: =P3-Q3 -> -1189.8 | S3: =IF(P3=0,0,R3/P3) -> -0.018681455 | T3: =IF(R3<0,"Loss","OK") -> Loss | U3: =IF(K3<0.1,"0-9%",IF(K3<0.2,"10-19%","20%+")) -> 10-19% | V3: =IF(E3>=Analysis!$B$4,"High",IF(E3>=Analysis!$B$5,"Mid","Low")) -> Mid | W3: =TEXT(B3,"yyyy-mm") -> 2023-04 | X3: =EOMONTH(B3,0) -> 45046 | Y3: =YEAR(B3)&"-Q"&ROUNDUP(MONTH(B3)/3,0) -> 2023-Q2 | Z3: =TEXT(B3,"ddd") -> Fri | AA3: =WEEKDAY(B3,2) -> 5 | AB3: =WEEKNUM(B3,2) -> 17 | AC3: =IF(AA3>5,"Weekend","Weekday") -> Weekday | AD3: =TODAY()-B3 -> 1282 | AE3: =DATEDIF(B3,TODAY(),"M") -> 42 | AF3: =UPPER(LEFT(C3,3)) -> BOB | AG3: =UPPER(LEFT(D3,1))&UPPER(LEFT(M3,1))&"-"&TEXT(B3,"yymmdd")&"-"&TEXT(ROW()-1,"0000") -> WR-230421-0002 | AH3: =IF(AND(OR(Filter!$B$4="All",D3=Filter!$B$4),OR(Filter!$B$5="All",M3=Filter!$B$5),E3>=Filter!$B$6),MAX(AH$1:AH2)+1,"") | AI3: =F3 -> 17 | AJ3: =K3 -> 0.11 | AK3: =I3 -> 4209.44 | AL3: =RANK(E3,$E$2:$E$1001,0)+COUNTIF($E$2:E3,E3)-1 -> 562
A4: 1015 | B4: 45190 | C4: David | D4: South | E4: 4631.23 | F4: 30 | G4: Food | H4: 261.56 | I4: 371.4 | J4: Returning | K4: 0.2 | L4: Bank Transfer | M4: Retail | N4: South-David | O4: =ROUND(F4*I4,2) -> 11142 | P4: =ROUND(F4*I4*(1-K4),2) -> 8913.6 | Q4: =ROUND(F4*H4,2) -> 7846.8 | R4: =P4-Q4 -> 1066.8 | S4: =IF(P4=0,0,R4/P4) -> 0.11968228 | T4: =IF(R4<0,"Loss","OK") -> OK | U4: =IF(K4<0.1,"0-9%",IF(K4<0.2,"10-19%","20%+")) -> 20%+ | V4: =IF(E4>=Analysis!$B$4,"High",IF(E4>=Analysis!$B$5,"Mid","Low")) -> Mid | W4: =TEXT(B4,"yyyy-mm") -> 2023-09 | X4: =EOMONTH(B4,0) -> 45199 | Y4: =YEAR(B4)&"-Q"&ROUNDUP(MONTH(B4)/3,0) -> 2023-Q3 | Z4: =TEXT(B4,"ddd") -> Thu | AA4: =WEEKDAY(B4,2) -> 4 | AB4: =WEEKNUM(B4,2) -> 39 | AC4: =IF(AA4>5,"Weekend","Weekday") -> Weekday | AD4: =TODAY()-B4 -> 1129 | AE4: =DATEDIF(B4,TODAY(),"M") -> 37 | AF4: =UPPER(LEFT(C4,3)) -> DAV | AG4: =UPPER(LEFT(D4,1))&UPPER(LEFT(M4,1))&"-"&TEXT(B4,"yymmdd")&"-"&TEXT(ROW()-1,"0000") -> SR-230921-0003 | AH4: =IF(AND(OR(Filter!$B$4="All",D4=Filter!$B$4),OR(Filter!$B$5="All",M4=Filter!$B$5),E4>=Filter!$B$6),MAX(AH$1:AH3)+1,"") | AI4: =F4 -> 30 | AJ4: =K4 -> 0.2 | AK4: =I4 -> 371.4 | AL4: =RANK(E4,$E$2:$E$1001,0)+COUNTIF($E$2:E4,E4)-1 -> 539
A5: 1072 | B5: 45162 | C5: Bob | D5: South | E5: 2167.94 | F5: 39 | G5: Clothing | H5: 4330.03 | I5: 4467.75 | J5: New | K5: 0.02 | L5: Credit Card | M5: Retail | N5: South-Bob | O5: =ROUND(F5*I5,2) -> 174242.25 | P5: =ROUND(F5*I5*(1-K5),2) -> 170757.41 | Q5: =ROUND(F5*H5,2) -> 168871.17 | R5: =P5-Q5 -> 1886.24 | S5: =IF(P5=0,0,R5/P5) -> 0.011046314 | T5: =IF(R5<0,"Loss","OK") -> OK | U5: =IF(K5<0.1,"0-9%",IF(K5<0.2,"10-19%","20%+")) -> 0-9% | V5: =IF(E5>=Analysis!$B$4,"High",IF(E5>=Analysis!$B$5,"Mid","Low")) -> Low | W5: =TEXT(B5,"yyyy-mm") -> 2023-08 | X5: =EOMONTH(B5,0) -> 45169 | Y5: =YEAR(B5)&"-Q"&ROUNDUP(MONTH(B5)/3,0) -> 2023-Q3 | Z5: =TEXT(B5,"ddd") -> Thu | AA5: =WEEKDAY(B5,2) -> 4 | AB5: =WEEKNUM(B5,2) -> 35 | AC5: =IF(AA5>5,"Weekend","Weekday") -> Weekday | AD5: =TODAY()-B5 -> 1157 | AE5: =DATEDIF(B5,TODAY(),"M") -> 38 | AF5: =UPPER(LEFT(C5,3)) -> BOB | AG5: =UPPER(LEFT(D5,1))&UPPER(LEFT(M5,1))&"-"&TEXT(B5,"yymmdd")&"-"&TEXT(ROW()-1,"0000") -> SR-230824-0004 | AH5: =IF(AND(OR(Filter!$B$4="All",D5=Filter!$B$4),OR(Filter!$B$5="All",M5=Filter!$B$5),E5>=Filter!$B$6),MAX(AH$1:AH4)+1,"") | AI5: =F5 -> 39 | AJ5: =K5 -> 0.02 | AK5: =I5 -> 4467.75 | AL5: =RANK(E5,$E$2:$E$1001,0)+COUNTIF($E$2:E5,E5)-1 -> 796
A6: 1061 | B6: 45009 | C6: Charlie | D6: East | E6: 3750.2 | F6: 13 | G6: Electronics | H6: 637.37 | I6: 692.71 | J6: New | K6: 0.08 | L6: Credit Card | M6: Online | N6: East-Charlie | O6: =ROUND(F6*I6,2) -> 9005.23 | P6: =ROUND(F6*I6*(1-K6),2) -> 8284.81 | Q6: =ROUND(F6*H6,2) -> 8285.81 | R6: =P6-Q6 -> -1 | S6: =IF(P6=0,0,R6/P6) -> -0.00012070283 | T6: =IF(R6<0,"Loss","OK") -> Loss | U6: =IF(K6<0.1,"0-9%",IF(K6<0.2,"10-19%","20%+")) -> 0-9% | V6: =IF(E6>=Analysis!$B$4,"High",IF(E6>=Analysis!$B$5,"Mid","Low")) -> Mid | W6: =TEXT(B6,"yyyy-mm") -> 2023-03 | X6: =EOMONTH(B6,0) -> 45016 | Y6: =YEAR(B6)&"-Q"&ROUNDUP(MONTH(B6)/3,0) -> 2023-Q1 | Z6: =TEXT(B6,"ddd") -> Fri | AA6: =WEEKDAY(B6,2) -> 5 | AB6: =WEEKNUM(B6,2) -> 13 | AC6: =IF(AA6>5,"Weekend","Weekday") -> Weekday | AD6: =TODAY()-B6 -> 1310 | AE6: =DATEDIF(B6,TODAY(),"M") -> 43 | AF6: =UPPER(LEFT(C6,3)) -> CHA | AG6: =UPPER(LEFT(D6,1))&UPPER(LEFT(M6,1))&"-"&TEXT(B6,"yymmdd")&"-"&TEXT(ROW()-1,"0000") -> EO-230324-0005 | AH6: =IF(AND(OR(Filter!$B$4="All",D6=Filter!$B$4),OR(Filter!$B$5="All",M6=Filter!$B$5),E6>=Filter!$B$6),MAX(AH$1:AH5)+1,"") | AI6: =F6 -> 13 | AJ6: =K6 -> 0.08 | AK6: =I6 -> 692.71 | AL6: =RANK(E6,$E$2:$E$1001,0)+COUNTIF($E$2:E6,E6)-1 -> 625
A7: 1021 | B7: 44968 | C7: Charlie | D7: West | E7: 3761.15 | F7: 32 | G7: Food | H7: 900.79 | I7: 1106.51 | J7: New | K7: 0.21 | L7: Cash | M7: Online | N7: West-Charlie | O7: =ROUND(F7*I7,2) -> 35408.32 | P7: =ROUND(F7*I7*(1-K7),2) -> 27972.57 | Q7: =ROUND(F7*H7,2) -> 28825.28 | R7: =P7-Q7 -> -852.71 | S7: =IF(P7=0,0,R7/P7) -> -0.030483792 | T7: =IF(R7<0,"Loss","OK") -> Loss | U7: =IF(K7<0.1,"0-9%",IF(K7<0.2,"10-19%","20%+")) -> 20%+ | V7: =IF(E7>=Analysis!$B$4,"High",IF(E7>=Analysis!$B$5,"Mid","Low")) -> Mid | W7: =TEXT(B7,"yyyy-mm") -> 2023-02 | X7: =EOMONTH(B7,0) -> 44985 | Y7: =YEAR(B7)&"-Q"&ROUNDUP(MONTH(B7)/3,0) -> 2023-Q1 | Z7: =TEXT(B7,"ddd") -> Sat | AA7: =WEEKDAY(B7,2) -> 6 | AB7: =WEEKNUM(B7,2) -> 7 | AC7: =IF(AA7>5,"Weekend","Weekday") -> Weekend | AD7: =TODAY()-B7 -> 1351 | AE7: =DATEDIF(B7,TODAY(),"M") -> 44 | AF7: =UPPER(LEFT(C7,3)) -> CHA | AG7: =UPPER(LEFT(D7,1))&UPPER(LEFT(M7,1))&"-"&TEXT(B7,"yymmdd")&"-"&TEXT(ROW()-1,"0000") -> WO-230211-0006 | AH7: =IF(AND(OR(Filter!$B$4="All",D7=Filter!$B$4),OR(Filter!$B$5="All",M7=Filter!$B$5),E7>=Filter!$B$6),MAX(AH$1:AH6)+1,"") | AI7: =F7 -> 32 | AJ7: =K7 -> 0.21 | AK7: =I7 -> 1106.51 | AL7: =RANK(E7,$E$2:$E$1001,0)+COUNTIF($E$2:E7,E7)-1 -> 622
A8: 1083 | B8: 45027 | C8: Bob | D8: West | E8: 618.31 | F8: 29 | G8: Furniture | H8: 2408.81 | I8: 2624.09 | J8: Returning | K8: 0.14 | L8: Cash | M8: Online | N8: West-Bob | O8: =ROUND(F8*I8,2) -> 76098.61 | P8: =ROUND(F8*I8*(1-K8),2) -> 65444.8 | Q8: =ROUND(F8*H8,2) -> 69855.49 | R8: =P8-Q8 -> -4410.69 | S8: =IF(P8=0,0,R8/P8) -> -0.067395576 | T8: =IF(R8<0,"Loss","OK") -> Loss | U8: =IF(K8<0.1,"0-9%",IF(K8<0.2,"10-19%","20%+")) -> 10-19% | V8: =IF(E8>=Analysis!$B$4,"High",IF(E8>=Analysis!$B$5,"Mid","Low")) -> Low | W8: =TEXT(B8,"yyyy-mm") -> 2023-04 | X8: =EOMONTH(B8,0) -> 45046 | Y8: =YEAR(B8)&"-Q"&ROUNDUP(MONTH(B8)/3,0) -> 2023-Q2 | Z8: =TEXT(B8,"ddd") -> Tue | AA8: =WEEKDAY(B8,2) -> 2 | AB8: =WEEKNUM(B8,2) -> 16 | AC8: =IF(AA8>5,"Weekend","Weekday") -> Weekday | AD8: =TODAY()-B8 -> 1292 | AE8: =DATEDIF(B8,TODAY(),"M") -> 42 | AF8: =UPPER(LEFT(C8,3)) -> BOB | AG8: =UPPER(LEFT(D8,1))&UPPER(LEFT(M8,1))&"-"&TEXT(B8,"yymmdd")&"-"&TEXT(ROW()-1,"0000") -> WO-230411-0007 | AH8: =IF(AND(OR(Filter!$B$4="All",D8=Filter!$B$4),OR(Filter!$B$5="All",M8=Filter!$B$5),E8>=Filter!$B$6),MAX(AH$1:AH7)+1,"") | AI8: =F8 -> 29 | AJ8: =K8 -> 0.14 | AK8: =I8 -> 2624.09 | AL8: =RANK(E8,$E$2:$E$1001,0)+COUNTIF($E$2:E8,E8)-1 -> 950
A9: 1087 | B9: 44932 | C9: Eve | D9: South | E9: 7698.92 | F9: 46 | G9: Furniture | H9: 3702.51 | I9: 3964.65 | J9: New | K9: 0.12 | L9: Bank Transfer | M9: Online | N9: South-Eve | O9: =ROUND(F9*I9,2) -> 182373.9 | P9: =ROUND(F9*I9*(1-K9),2) -> 160489.03 | Q9: =ROUND(F9*H9,2) -> 170315.46 | R9: =P9-Q9 -> -9826.43 | S9: =IF(P9=0,0,R9/P9) -> -0.061228048 | T9: =IF(R9<0,"Loss","OK") -> Loss | U9: =IF(K9<0.1,"0-9%",IF(K9<0.2,"10-19%","20%+")) -> 10-19% | V9: =IF(E9>=Analysis!$B$4,"High",IF(E9>=Analysis!$B$5,"Mid","Low")) -> High | W9: =TEXT(B9,"yyyy-mm") -> 2023-01 | X9: =EOMONTH(B9,0) -> 44957 | Y9: =YEAR(B9)&"-Q"&ROUNDUP(MONTH(B9)/3,0) -> 2023-Q1 | Z9: =TEXT(B9,"ddd") -> Fri | AA9: =WEEKDAY(B9,2) -> 5 | AB9: =WEEKNUM(B9,2) -> 2 | AC9: =IF(AA9>5,"Weekend","Weekday") -> Weekday | AD9: =TODAY()-B9 -> 1387 | AE9: =DATEDIF(B9,TODAY(),"M") -> 45 | AF9: =UPPER(LEFT(C9,3)) -> EVE | AG9: =UPPER(LEFT(D9,1))&UPPER(LEFT(M9,1))&"-"&TEXT(B9,"yymmdd")&"-"&TEXT(ROW()-1,"0000") -> SO-230106-0008 | AH9: =IF(AND(OR(Filter!$B$4="All",D9=Filter!$B$4),OR(Filter!$B$5="All",M9=Filter!$B$5),E9>=Filter!$B$6),MAX(AH$1:AH8)+1,"") | AI9: =F9 -> 46 | AJ9: =K9 -> 0.12 | AK9: =I9 -> 3964.65 | AL9: =RANK(E9,$E$2:$E$1001,0)+COUNTIF($E$2:E9,E9)-1 -> 227
A10: 1075 | B10: 45106 | C10: David | D10: South | E10: 4223.39 | F10: 30 | G10: Furniture | H10: 738.06 | I10: 1095.45 | J10: New | K10: 0.05 | L10: Bank Transfer | M10: Online | N10: South-David | O10: =ROUND(F10*I10,2) -> 32863.5 | P10: =ROUND(F10*I10*(1-K10),2) -> 31220.33 | Q10: =ROUND(F10*H10,2) -> 22141.8 | R10: =P10-Q10 -> 9078.53 | S10: =IF(P10=0,0,R10/P10) -> 0.29078905 | T10: =IF(R10<0,"Loss","OK") -> OK | U10: =IF(K10<0.1,"0-9%",IF(K10<0.2,"10-19%","20%+")) -> 0-9% | V10: =IF(E10>=Analysis!$B$4,"High",IF(E10>=Analysis!$B$5,"Mid","Low")) -> Mid | W10: =TEXT(B10,"yyyy-mm") -> 2023-06 | X10: =EOMONTH(B10,0) -> 45107 | Y10: =YEAR(B10)&"-Q"&ROUNDUP(MONTH(B10)/3,0) -> 2023-Q2 | Z10: =TEXT(B10,"ddd") -> Thu | AA10: =WEEKDAY(B10,2) -> 4 | AB10: =WEEKNUM(B10,2) -> 27 | AC10: =IF(AA10>5,"Weekend","Weekday") -> Weekday | AD10: =TODAY()-B10 -> 1213 | AE10: =DATEDIF(B10,TODAY(),"M") -> 39 | AF10: =UPPER(LEFT(C10,3)) -> DAV | AG10: =UPPER(LEFT(D10,1))&UPPER(LEFT(M10,1))&"-"&TEXT(B10,"yymmdd")&"-"&TEXT(ROW()-1,"0000") -> SO-230629-0009 | AH10: =IF(AND(OR(Filter!$B$4="All",D10=Filter!$B$4),OR(Filter!$B$5="All",M10=Filter!$B$5),E10>=Filter!$B$6),MAX(AH$1:AH9)+1,"") | AI10: =F10 -> 30 | AJ10: =K10 -> 0.05 | AK10: =I10 -> 1095.45 | AL10: =RANK(E10,$E$2:$E$1001,0)+COUNTIF($E$2:E10,E10)-1 -> 578
A11: 1075 | B11: 45208 | C11: Charlie | D11: West | E11: 8239.58 | F11: 18 | G11: Clothing | H11: 2228.35 | I11: 2682.34 | J11: New | K11: 0.13 | L11: Bank Transfer | M11: Online | N11: West-Charlie | O11: =ROUND(F11*I11,2) -> 48282.12 | P11: =ROUND(F11*I11*(1-K11),2) -> 42005.44 | Q11: =ROUND(F11*H11,2) -> 40110.3 | R11: =P11-Q11 -> 1895.14 | S11: =IF(P11=0,0,R11/P11) -> 0.045116537 | T11: =IF(R11<0,"Loss","OK") -> OK | U11: =IF(K11<0.1,"0-9%",IF(K11<0.2,"10-19%","20%+")) -> 10-19% | V11: =IF(E11>=Analysis!$B$4,"High",IF(E11>=Analysis!$B$5,"Mid","Low")) -> High | W11: =TEXT(B11,"yyyy-mm") -> 2023-10 | X11: =EOMONTH(B11,0) -> 45230 | Y11: =YEAR(B11)&"-Q"&ROUNDUP(MONTH(B11)/3,0) -> 2023-Q4 | Z11: =TEXT(B11,"ddd") -> Mon | AA11: =WEEKDAY(B11,2) -> 1 | AB11: =WEEKNUM(B11,2) -> 42 | AC11: =IF(AA11>5,"Weekend","Weekday") -> Weekday | AD11: =TODAY()-B11 -> 1111 | AE11: =DATEDIF(B11,TODAY(),"M") -> 36 | AF11: =UPPER(LEFT(C11,3)) -> CHA | AG11: =UPPER(LEFT(D11,1))&UPPER(LEFT(M11,1))&"-"&TEXT(B11,"yymmdd")&"-"&TEXT(ROW()-1,"0000") -> WO-231009-0010 | AH11: =IF(AND(OR(Filter!$B$4="All",D11=Filter!$B$4),OR(Filter!$B$5="All",M11=Filter!$B$5),E11>=Filter!$B$6),MAX(AH$1:AH10)+1,"") | AI11: =F11 -> 18 | AJ11: =K11 -> 0.13 | AK11: =I11 -> 2682.34 | AL11: =RANK(E11,$E$2:$E$1001,0)+COUNTIF($E$2:E11,E11)-1 -> 168
A12: 1088 | B12: 45246 | C12: Eve | D12: North | E12: 8518.45 | F12: 13 | G12: Furniture | H12: 2440.11 | I12: 2517.6 | J12: New | K12: 0.23 | L12: Bank Transfer | M12: Retail | N12: North-Eve | O12: =ROUND(F12*I12,2) -> 32728.8 | P12: =ROUND(F12*I12*(1-K12),2) -> 25201.18 | Q12: =ROUND(F12*H12,2) -> 31721.43 | R12: =P12-Q12 -> -6520.25 | S12: =IF(P12=0,0,R12/P12) -> -0.25872796 | T12: =IF(R12<0,"Loss","OK") -> Loss | U12: =IF(K12<0.1,"0-9%",IF(K12<0.2,"10-19%","20%+")) -> 20%+ | V12: =IF(E12>=Analysis!$B$4,"High",IF(E12>=Analysis!$B$5,"Mid","Low")) -> High | W12: =TEXT(B12,"yyyy-mm") -> 2023-11 | X12: =EOMONTH(B12,0) -> 45260 | Y12: =YEAR(B12)&"-Q"&ROUNDUP(MONTH(B12)/3,0) -> 2023-Q4 | Z12: =TEXT(B12,"ddd") -> Thu | AA12: =WEEKDAY(B12,2) -> 4 | AB12: =WEEKNUM(B12,2) -> 47 | AC12: =IF(AA12>5,"Weekend","Weekday") -> Weekday | AD12: =TODAY()-B12 -> 1073 | AE12: =DATEDIF(B12,TODAY(),"M") -> 35 | AF12: =UPPER(LEFT(C12,3)) -> EVE | AG12: =UPPER(LEFT(D12,1))&UPPER(LEFT(M12,1))&"-"&TEXT(B12,"yymmdd")&"-"&TEXT(ROW()-1,"0000") -> NR-231116-0011 | AH12: =IF(AND(OR(Filter!$B$4="All",D12=Filter!$B$4),OR(Filter!$B$5="All",M12=Filter!$B$5),E12>=Filter!$B$6),MAX(AH$1:AH11)+1,"") | AI12: =F12 -> 13 | AJ12: =K12 -> 0.23 | AK12: =I12 -> 2517.6 | AL12: =RANK(E12,$E$2:$E$1001,0)+COUNTIF($E$2:E12,E12)-1 -> 139
A13: 1100 | B13: 45152 | C13: Bob | D13: West | E13: 2198.74 | F13: 43 | G13: Food | H13: 1100.81 | I13: 1137.44 | J13: Returning | K13: 0.08 | L13: Bank Transfer | M13: Online | N13: West-Bob | O13: =ROUND(F13*I13,2) -> 48909.92 | P13: =ROUND(F13*I13*(1-K13),2) -> 44997.13 | Q13: =ROUND(F13*H13,2) -> 47334.83 | R13: =P13-Q13 -> -2337.7 | S13: =IF(P13=0,0,R13/P13) -> -0.051952202 | T13: =IF(R13<0,"Loss","OK") -> Loss | U13: =IF(K13<0.1,"0-9%",IF(K13<0.2,"10-19%","20%+")) -> 0-9% | V13: =IF(E13>=Analysis!$B$4,"High",IF(E13>=Analysis!$B$5,"Mid","Low")) -> Low | W13: =TEXT(B13,"yyyy-mm") -> 2023-08 | X13: =EOMONTH(B13,0) -> 45169 | Y13: =YEAR(B13)&"-Q"&ROUNDUP(MONTH(B13)/3,0) -> 2023-Q3 | Z13: =TEXT(B13,"ddd") -> Mon | AA13: =WEEKDAY(B13,2) -> 1 | AB13: =WEEKNUM(B13,2) -> 34 | AC13: =IF(AA13>5,"Weekend","Weekday") -> Weekday | AD13: =TODAY()-B13 -> 1167 | AE13: =DATEDIF(B13,TODAY(),"M") -> 38 | AF13: =UPPER(LEFT(C13,3)) -> BOB | AG13: =UPPER(LEFT(D13,1))&UPPER(LEFT(M13,1))&"-"&TEXT(B13,"yymmdd")&"-"&TEXT(ROW()-1,"0000") -> WO-230814-0012 | AH13: =IF(AND(OR(Filter!$B$4="All",D13=Filter!$B$4),OR(Filter!$B$5="All",M13=Filter!$B$5),E13>=Filter!$B$6),MAX(AH$1:AH12)+1,"") | AI13: =F13 -> 43 | AJ13: =K13 -> 0.08 | AK13: =I13 -> 1137.44 | AL13: =RANK(E13,$E$2:$E$1001,0)+COUNTIF($E$2:E13,E13)-1 -> 790
... A1001: 1086 | B1001: 45154 | C1001: Alice | D1001: East | E1001: 4923.93 | F1001: 48 | G1001: Food | H1001: 2632.58 | I1001: 2926.68 | J1001: Returning | K1001: 0.14 | L1001: Cash | M1001: Online | N1001: East-Alice | O1001: =ROUND(F1001*I1001,2) -> 140480.64 | P1001: =ROUND(F1001*I1001*(1-K1001),2) -> 120813.35 | Q1001: =ROUND(F1001*H1001,2) -> 126363.84 | R1001: =P1001-Q1001 -> -5550.49 | S1001: =IF(P1001=0,0,R1001/P1001) -> -0.045942688 | T1001: =IF(R1001<0,"Loss","OK") -> Loss | U1001: =IF(K1001<0.1,"0-9%",IF(K1001<0.2,"10-19%","20%+")) -> 10-19% | V1001: =IF(E1001>=Analysis!$B$4,"High",IF(E1001>=Analysis!$B$5,"Mid","Low")) -> Mid | W1001: =TEXT(B1001,"yyyy-mm") -> 2023-08 | X1001: =EOMONTH(B1001,0) -> 45169 | Y1001: =YEAR(B1001)&"-Q"&ROUNDUP(MONTH(B1001)/3,0) -> 2023-Q3 | Z1001: =TEXT(B1001,"ddd") -> Wed | AA1001: =WEEKDAY(B1001,2) -> 3 | AB1001: =WEEKNUM(B1001,2) -> 34 | AC1001: =IF(AA1001>5,"Weekend","Weekday") -> Weekday | AD1001: =TODAY()-B1001 -> 1165 | AE1001: =DATEDIF(B1001,TODAY(),"M") -> 38 | AF1001: =UPPER(LEFT(C1001,3)) -> ALI | AG1001: =UPPER(LEFT(D1001,1))&UPPER(LEFT(M1001,1))&"-"&TEXT(B1001,"yymmdd")&"-"&TEXT(ROW()-1,"0000") -> EO-230816-1000 | AH1001: =IF(AND(OR(Filter!$B$4="All",D1001=Filter!$B$4),OR(Filter!$B$5="All",M1001=Filter!$B$5),E1001>=Filter!$B$6),MAX(AH$1:AH1000)+1,"") | AI1001: =F1001 -> 48 | AJ1001: =K1001 -> 0.14 | AK1001: =I1001 -> 2926.68 | AL1001: =RANK(E1001,$E$2:$E$1001,0)+COUNTIF($E$2:E1001,E1001)-1 -> 509

Sheet Analysis
A1: Analysis
A3: 0. Parameters (drive the Sales_Size column in Raw Data)
A4: Large-sale threshold (75th percentile of Sales_Amount) | B4: =PERCENTILE('Raw Data'!$E$2:$E$1001,0.75) -> 7507.445
A5: Small-sale threshold (25th percentile of Sales_Amount) | B5: =PERCENTILE('Raw Data'!$E$2:$E$1001,0.25) -> 2550.2975
A7: 1. Date & Time Functions (TODAY, NOW, DATEDIF, EOMONTH, EDATE, NETWORKDAYS, WEEKNUM)
A8: Today | B8: =TODAY() -> 46319
A9: Now (date & time) | B9: =NOW() -> 46319.662
A10: End of current month | B10: =EOMONTH(TODAY(),0) -> 46326
A11: Start of current month | B11: =EOMONTH(TODAY(),-1)+1 -> 46296
A12: First sale | B12: =MIN('Raw Data'!$B$2:$B$1001) -> 44927
A13: Last sale | B13: =MAX('Raw Data'!$B$2:$B$1001) -> 45292
A14: Dataset span (months, DATEDIF) | B14: =DATEDIF(B12,B13,"M") -> 12
A15: Dataset span (days) | B15: =B13-B12 -> 365
A16: Working days in span (NETWORKDAYS) | B16: =NETWORKDAYS(B12,B13) -> 261
A17: Distinct selling days | B17: =SUMPRODUCT(1/COUNTIF('Raw Data'!$B$2:$B$1001,'Raw Data'!$B$2:$B$1001)) -> 340
A18: Average sales per selling day | B18: =B35/B17 -> 14762.545
A19: Days since last sale | B19: =TODAY()-B13 -> 1027
A20: Months since last sale (DATEDIF) | B20: =DATEDIF(B13,TODAY(),"M") -> 33
A21: Six months after first sale (EDATE) | B21: =EDATE(B12,6) -> 45108
A22: Weekday of last sale | B22: =TEXT(B13,"dddd") -> Monday
A23: ISO-style week of last sale (WEEKNUM) | B23: =WEEKNUM(B13,2) -> 1
A25: 2. Timestamp with NOW() + Iterative Calculation (circular on purpose; File > Options > Formulas > Enable iterative calculation)
A26: Entry (type here) | B26: Timestamp (freezes once typed) | C26: Elapsed since stamp
A27: Order batch 1 | B27: =IF(A27="","",IF(OR(B27="",B27=0),NOW(),B27)) -> 46319.426 | C27: =IF(B27="","",TEXT(NOW()-B27,"[h]:mm:ss")) -> 0:00:02
A28: Order batch 2 | B28: =IF(A28="","",IF(OR(B28="",B28=0),NOW(),B28)) -> 46319.426 | C28: =IF(B28="","",TEXT(NOW()-B28,"[h]:mm:ss")) -> 0:00:02
A29: Order batch 3 | B29: =IF(A29="","",IF(OR(B29="",B29=0),NOW(),B29)) -> 46319.426 | C29: =IF(B29="","",TEXT(NOW()-B29,"[h]:mm:ss")) -> 0:00:02
B30: =IF(A30="","",IF(OR(B30="",B30=0),NOW(),B30)) | C30: =IF(B30="","",TEXT(NOW()-B30,"[h]:mm:ss"))
B31: =IF(A31="","",IF(OR(B31="",B31=0),NOW(),B31)) | C31: =IF(B31="","",TEXT(NOW()-B31,"[h]:mm:ss"))
A32: Type anything in A30 or A31 and the timestamp appears and stays fixed (column C shows time elapsed since it was stamped).
A34: 3. Headline KPIs
A35: Total Sales | B35: =SUM('Raw Data'!$E$2:$E$1001) -> 5019265.2
A36: Transactions | B36: =COUNTA('Raw Data'!$E$2:$E$1001) -> 1000
A37: Units Sold | B37: =SUM('Raw Data'!$F$2:$F$1001) -> 25355
A38: Average Sale | B38: =AVERAGE('Raw Data'!$E$2:$E$1001) -> 5019.2652
A39: Median Sale | B39: =MEDIAN('Raw Data'!$E$2:$E$1001) -> 5019.3
A40: Average Discount | B40: =AVERAGE('Raw Data'!$K$2:$K$1001) -> 0.15239
A41: List Value (Qty x Unit_Price) | B41: =SUM('Raw Data'!$O$2:$O$1001) -> 70329941
A42: Net List Value (after discount) | B42: =SUM('Raw Data'!$P$2:$P$1001) -> 59686174
A43: Discount Given ($, list basis) | B43: =B41-B42 -> 10643767
A44: Cost of Goods (Qty x Unit_Cost) | B44: =SUM('Raw Data'!$Q$2:$Q$1001) -> 63842094
A45: Net Margin ($, list basis) | B45: =B42-B44 -> -4155920.1
A46: Net Margin % | B46: =IF(B42=0,0,B45/B42) -> -0.069629528
A47: Gross Margin % before discount | B47: =1-B44/B41 -> 0.092248721
A48: Weighted Average Discount | B48: =1-B42/B41 -> 0.15134048
A49: Break-even Discount (net margin = 0) | B49: =1-B44/B41 -> 0.092248721
A50: Loss-making Transactions | B50: =COUNTIF('Raw Data'!$T$2:$T$1001,"Loss") -> 604
A51: Loss-making Share | B51: =B50/B36 -> 0.604
A54: 4. Regional Sales
A55: Region | B55: Transactions | C55: Sales | D55: Share | E55: Avg Sale | F55: Units | G55: Avg Discount | H55: Net Margin % | I55: Rank
A56: East | B56: =COUNTIFS('Raw Data'!$D$2:$D$1001,A56) -> 263 | C56: =SUMIFS('Raw Data'!$E$2:$E$1001,'Raw Data'!$D$2:$D$1001,A56) -> 1259792.9 | D56: =C56/$B$35 -> 0.2509915 | E56: =IF(B56=0,0,C56/B56) -> 4790.0872 | F56: =SUMIFS('Raw Data'!$F$2:$F$1001,'Raw Data'!$D$2:$D$1001,A56) -> 6356 | G56: =IFERROR(AVERAGEIFS('Raw Data'!$K$2:$K$1001,'Raw Data'!$D$2:$D$1001,A56),0) -> 0.16254753 | H56: =IFERROR(SUMIFS('Raw Data'!$R$2:$R$1001,'Raw Data'!$D$2:$D$1001,A56)/SUMIFS('Raw Data'!$P$2:$P$1001,'Raw Data'!$D$2:$D$1001,A56),0) -> -0.080551166 | I56: =RANK(C56,$C$56:$C$59,0) -> 2
A57: North | B57: =COUNTIFS('Raw Data'!$D$2:$D$1001,A57) -> 267 | C57: =SUMIFS('Raw Data'!$E$2:$E$1001,'Raw Data'!$D$2:$D$1001,A57) -> 1369612.5 | D57: =C57/$B$35 -> 0.27287112 | E57: =IF(B57=0,0,C57/B57) -> 5129.6349 | F57: =SUMIFS('Raw Data'!$F$2:$F$1001,'Raw Data'!$D$2:$D$1001,A57) -> 6705 | G57: =IFERROR(AVERAGEIFS('Raw Data'!$K$2:$K$1001,'Raw Data'!$D$2:$D$1001,A57),0) -> 0.14955056 | H57: =IFERROR(SUMIFS('Raw Data'!$R$2:$R$1001,'Raw Data'!$D$2:$D$1001,A57)/SUMIFS('Raw Data'!$P$2:$P$1001,'Raw Data'!$D$2:$D$1001,A57),0) -> -0.062721833 | I57: =RANK(C57,$C$56:$C$59,0) -> 1
A58: South | B58: =COUNTIFS('Raw Data'!$D$2:$D$1001,A58) -> 226 | C58: =SUMIFS('Raw Data'!$E$2:$E$1001,'Raw Data'!$D$2:$D$1001,A58) -> 1154250.9 | D58: =C58/$B$35 -> 0.22996411 | E58: =IF(B58=0,0,C58/B58) -> 5107.3047 | F58: =SUMIFS('Raw Data'!$F$2:$F$1001,'Raw Data'!$D$2:$D$1001,A58) -> 5808 | G58: =IFERROR(AVERAGEIFS('Raw Data'!$K$2:$K$1001,'Raw Data'!$D$2:$D$1001,A58),0) -> 0.14831858 | H58: =IFERROR(SUMIFS('Raw Data'!$R$2:$R$1001,'Raw Data'!$D$2:$D$1001,A58)/SUMIFS('Raw Data'!$P$2:$P$1001,'Raw Data'!$D$2:$D$1001,A58),0) -> -0.062482268 | I58: =RANK(C58,$C$56:$C$59,0) -> 4
A59: West | B59: =COUNTIFS('Raw Data'!$D$2:$D$1001,A59) -> 244 | C59: =SUMIFS('Raw Data'!$E$2:$E$1001,'Raw Data'!$D$2:$D$1001,A59) -> 1235608.9 | D59: =C59/$B$35 -> 0.24617327 | E59: =IF(B59=0,0,C59/B59) -> 5063.971 | F59: =SUMIFS('Raw Data'!$F$2:$F$1001,'Raw Data'!$D$2:$D$1001,A59) -> 6486 | G59: =IFERROR(AVERAGEIFS('Raw Data'!$K$2:$K$1001,'Raw Data'!$D$2:$D$1001,A59),0) -> 0.14831967 | H59: =IFERROR(SUMIFS('Raw Data'!$R$2:$R$1001,'Raw Data'!$D$2:$D$1001,A59)/SUMIFS('Raw Data'!$P$2:$P$1001,'Raw Data'!$D$2:$D$1001,A59),0) -> -0.072348112 | I59: =RANK(C59,$C$56:$C$59,0) -> 3
A60: Total | B60: =SUM(B56:B59) -> 1000 | C60: =SUM(C56:C59) -> 5019265.2 | D60: =SUM(D56:D59) -> 1 | F60: =SUM(F56:F59) -> 25355
A61: Top region (by sales) | B61: =INDEX(A56:A59,MATCH(MAX(C56:C59),C56:C59,0)) -> North
A62: Lowest region (by sales) | B62: =INDEX(A56:A59,MATCH(MIN(C56:C59),C56:C59,0)) -> South
A64: 5. Product Category Sales
A65: Category | B65: Transactions | C65: Sales | D65: Share | E65: Avg Sale | F65: Units | G65: Avg Discount | H65: Net Margin % | I65: Rank
A66: Clothing | B66: =COUNTIFS('Raw Data'!$G$2:$G$1001,A66) -> 268 | C66: =SUMIFS('Raw Data'!$E$2:$E$1001,'Raw Data'!$G$2:$G$1001,A66) -> 1313474.4 | D66: =C66/$B$35 -> 0.26168658 | E66: =IF(B66=0,0,C66/B66) -> 4901.0237 | F66: =SUMIFS('Raw Data'!$F$2:$F$1001,'Raw Data'!$G$2:$G$1001,A66) -> 6922 | G66: =IFERROR(AVERAGEIFS('Raw Data'!$K$2:$K$1001,'Raw Data'!$G$2:$G$1001,A66),0) -> 0.16022388 | H66: =IFERROR(SUMIFS('Raw Data'!$R$2:$R$1001,'Raw Data'!$G$2:$G$1001,A66)/SUMIFS('Raw Data'!$P$2:$P$1001,'Raw Data'!$G$2:$G$1001,A66),0) -> -0.074136239 | I66: =RANK(C66,$C$66:$C$69,0) -> 1
A67: Electronics | B67: =COUNTIFS('Raw Data'!$G$2:$G$1001,A67) -> 246 | C67: =SUMIFS('Raw Data'!$E$2:$E$1001,'Raw Data'!$G$2:$G$1001,A67) -> 1243499.6 | D67: =C67/$B$35 -> 0.24774535 | E67: =IF(B67=0,0,C67/B67) -> 5054.8766 | F67: =SUMIFS('Raw Data'!$F$2:$F$1001,'Raw Data'!$G$2:$G$1001,A67) -> 6096 | G67: =IFERROR(AVERAGEIFS('Raw Data'!$K$2:$K$1001,'Raw Data'!$G$2:$G$1001,A67),0) -> 0.13650407 | H67: =IFERROR(SUMIFS('Raw Data'!$R$2:$R$1001,'Raw Data'!$G$2:$G$1001,A67)/SUMIFS('Raw Data'!$P$2:$P$1001,'Raw Data'!$G$2:$G$1001,A67),0) -> -0.055664397 | I67: =RANK(C67,$C$66:$C$69,0) -> 3
A68: Food | B68: =COUNTIFS('Raw Data'!$G$2:$G$1001,A68) -> 226 | C68: =SUMIFS('Raw Data'!$E$2:$E$1001,'Raw Data'!$G$2:$G$1001,A68) -> 1201773.5 | D68: =C68/$B$35 -> 0.23943216 | E68: =IF(B68=0,0,C68/B68) -> 5317.582 | F68: =SUMIFS('Raw Data'!$F$2:$F$1001,'Raw Data'!$G$2:$G$1001,A68) -> 5608 | G68: =IFERROR(AVERAGEIFS('Raw Data'!$K$2:$K$1001,'Raw Data'!$G$2:$G$1001,A68),0) -> 0.15380531 | H68: =IFERROR(SUMIFS('Raw Data'!$R$2:$R$1001,'Raw Data'!$G$2:$G$1001,A68)/SUMIFS('Raw Data'!$P$2:$P$1001,'Raw Data'!$G$2:$G$1001,A68),0) -> -0.071238919 | I68: =RANK(C68,$C$66:$C$69,0) -> 4
A69: Furniture | B69: =COUNTIFS('Raw Data'!$G$2:$G$1001,A69) -> 260 | C69: =SUMIFS('Raw Data'!$E$2:$E$1001,'Raw Data'!$G$2:$G$1001,A69) -> 1260517.7 | D69: =C69/$B$35 -> 0.2511359 | E69: =IF(B69=0,0,C69/B69) -> 4848.145 | F69: =SUMIFS('Raw Data'!$F$2:$F$1001,'Raw Data'!$G$2:$G$1001,A69) -> 6729 | G69: =IFERROR(AVERAGEIFS('Raw Data'!$K$2:$K$1001,'Raw Data'!$G$2:$G$1001,A69),0) -> 0.15811538 | H69: =IFERROR(SUMIFS('Raw Data'!$R$2:$R$1001,'Raw Data'!$G$2:$G$1001,A69)/SUMIFS('Raw Data'!$P$2:$P$1001,'Raw Data'!$G$2:$G$1001,A69),0) -> -0.07726239 | I69: =RANK(C69,$C$66:$C$69,0) -> 2
A70: Total | B70: =SUM(B66:B69) -> 1000 | C70: =SUM(C66:C69) -> 5019265.2 | D70: =SUM(D66:D69) -> 1 | F70: =SUM(F66:F69) -> 25355
A71: Top category (by sales) | B71: =INDEX(A66:A69,MATCH(MAX(C66:C69),C66:C69,0)) -> Clothing
A72: Lowest category (by sales) | B72: =INDEX(A66:A69,MATCH(MIN(C66:C69),C66:C69,0)) -> Food
A74: 6. Sales Rep Leaderboard
A75: Sales Rep | B75: Transactions | C75: Sales | D75: Share | E75: Avg Sale | F75: Units | G75: Avg Discount | H75: Net Margin % | I75: Rank
A76: Alice | B76: =COUNTIFS('Raw Data'!$C$2:$C$1001,A76) -> 192 | C76: =SUMIFS('Raw Data'!$E$2:$E$1001,'Raw Data'!$C$2:$C$1001,A76) -> 965541.77 | D76: =C76/$B$35 -> 0.19236715 | E76: =IF(B76=0,0,C76/B76) -> 5028.8634 | F76: =SUMIFS('Raw Data'!$F$2:$F$1001,'Raw Data'!$C$2:$C$1001,A76) -> 4832 | G76: =IFERROR(AVERAGEIFS('Raw Data'!$K$2:$K$1001,'Raw Data'!$C$2:$C$1001,A76),0) -> 0.14109375 | H76: =IFERROR(SUMIFS('Raw Data'!$R$2:$R$1001,'Raw Data'!$C$2:$C$1001,A76)/SUMIFS('Raw Data'!$P$2:$P$1001,'Raw Data'!$C$2:$C$1001,A76),0) -> -0.054568425 | I76: =RANK(C76,$C$76:$C$80,0) -> 4
A77: Bob | B77: =COUNTIFS('Raw Data'!$C$2:$C$1001,A77) -> 208 | C77: =SUMIFS('Raw Data'!$E$2:$E$1001,'Raw Data'!$C$2:$C$1001,A77) -> 1080990.6 | D77: =C77/$B$35 -> 0.2153683 | E77: =IF(B77=0,0,C77/B77) -> 5197.0703 | F77: =SUMIFS('Raw Data'!$F$2:$F$1001,'Raw Data'!$C$2:$C$1001,A77) -> 4977 | G77: =IFERROR(AVERAGEIFS('Raw Data'!$K$2:$K$1001,'Raw Data'!$C$2:$C$1001,A77),0) -> 0.14240385 | H77: =IFERROR(SUMIFS('Raw Data'!$R$2:$R$1001,'Raw Data'!$C$2:$C$1001,A77)/SUMIFS('Raw Data'!$P$2:$P$1001,'Raw Data'!$C$2:$C$1001,A77),0) -> -0.065693231 | I77: =RANK(C77,$C$76:$C$80,0) -> 2
A78: Charlie | B78: =COUNTIFS('Raw Data'!$C$2:$C$1001,A78) -> 169 | C78: =SUMIFS('Raw Data'!$E$2:$E$1001,'Raw Data'!$C$2:$C$1001,A78) -> 860811.48 | D78: =C78/$B$35 -> 0.17150149 | E78: =IF(B78=0,0,C78/B78) -> 5093.5591 | F78: =SUMIFS('Raw Data'!$F$2:$F$1001,'Raw Data'!$C$2:$C$1001,A78) -> 4217 | G78: =IFERROR(AVERAGEIFS('Raw Data'!$K$2:$K$1001,'Raw Data'!$C$2:$C$1001,A78),0) -> 0.15514793 | H78: =IFERROR(SUMIFS('Raw Data'!$R$2:$R$1001,'Raw Data'!$C$2:$C$1001,A78)/SUMIFS('Raw Data'!$P$2:$P$1001,'Raw Data'!$C$2:$C$1001,A78),0) -> -0.066461693 | I78: =RANK(C78,$C$76:$C$80,0) -> 5
A79: David | B79: =COUNTIFS('Raw Data'!$C$2:$C$1001,A79) -> 222 | C79: =SUMIFS('Raw Data'!$E$2:$E$1001,'Raw Data'!$C$2:$C$1001,A79) -> 1141737.4 | D79: =C79/$B$35 -> 0.22747102 | E79: =IF(B79=0,0,C79/B79) -> 5142.9611 | F79: =SUMIFS('Raw Data'!$F$2:$F$1001,'Raw Data'!$C$2:$C$1001,A79) -> 6042 | G79: =IFERROR(AVERAGEIFS('Raw Data'!$K$2:$K$1001,'Raw Data'!$C$2:$C$1001,A79),0) -> 0.16459459 | H79: =IFERROR(SUMIFS('Raw Data'!$R$2:$R$1001,'Raw Data'!$C$2:$C$1001,A79)/SUMIFS('Raw Data'!$P$2:$P$1001,'Raw Data'!$C$2:$C$1001,A79),0) -> -0.089175696 | I79: =RANK(C79,$C$76:$C$80,0) -> 1
A80: Eve | B80: =COUNTIFS('Raw Data'!$C$2:$C$1001,A80) -> 209 | C80: =SUMIFS('Raw Data'!$E$2:$E$1001,'Raw Data'!$C$2:$C$1001,A80) -> 970183.99 | D80: =C80/$B$35 -> 0.19329203 | E80: =IF(B80=0,0,C80/B80) -> 4642.0287 | F80: =SUMIFS('Raw Data'!$F$2:$F$1001,'Raw Data'!$C$2:$C$1001,A80) -> 5287 | G80: =IFERROR(AVERAGEIFS('Raw Data'!$K$2:$K$1001,'Raw Data'!$C$2:$C$1001,A80),0) -> 0.15751196 | H80: =IFERROR(SUMIFS('Raw Data'!$R$2:$R$1001,'Raw Data'!$C$2:$C$1001,A80)/SUMIFS('Raw Data'!$P$2:$P$1001,'Raw Data'!$C$2:$C$1001,A80),0) -> -0.068317673 | I80: =RANK(C80,$C$76:$C$80,0) -> 3
A81: Total | B81: =SUM(B76:B80) -> 1000 | C81: =SUM(C76:C80) -> 5019265.2 | D81: =SUM(D76:D80) -> 1 | F81: =SUM(F76:F80) -> 25355
A82: Top sales rep (by sales) | B82: =INDEX(A76:A80,MATCH(MAX(C76:C80),C76:C80,0)) -> David
A83: Lowest sales rep (by sales) | B83: =INDEX(A76:A80,MATCH(MIN(C76:C80),C76:C80,0)) -> Charlie
A85: 7. Sales Channel
A86: Channel | B86: Transactions | C86: Sales | D86: Share | E86: Avg Sale | F86: Units | G86: Avg Discount | H86: Net Margin % | I86: Rank
A87: Online | B87: =COUNTIFS('Raw Data'!$M$2:$M$1001,A87) -> 488 | C87: =SUMIFS('Raw Data'!$E$2:$E$1001,'Raw Data'!$M$2:$M$1001,A87) -> 2458833.9 | D87: =C87/$B$35 -> 0.48987926 | E87: =IF(B87=0,0,C87/B87) -> 5038.5941 | F87: =SUMIFS('Raw Data'!$F$2:$F$1001,'Raw Data'!$M$2:$M$1001,A87) -> 12602 | G87: =IFERROR(AVERAGEIFS('Raw Data'!$K$2:$K$1001,'Raw Data'!$M$2:$M$1001,A87),0) -> 0.15256148 | H87: =IFERROR(SUMIFS('Raw Data'!$R$2:$R$1001,'Raw Data'!$M$2:$M$1001,A87)/SUMIFS('Raw Data'!$P$2:$P$1001,'Raw Data'!$M$2:$M$1001,A87),0) -> -0.07145072 | I87: =RANK(C87,$C$87:$C$88,0) -> 2
A88: Retail | B88: =COUNTIFS('Raw Data'!$M$2:$M$1001,A88) -> 512 | C88: =SUMIFS('Raw Data'!$E$2:$E$1001,'Raw Data'!$M$2:$M$1001,A88) -> 2560431.3 | D88: =C88/$B$35 -> 0.51012074 | E88: =IF(B88=0,0,C88/B88) -> 5000.8424 | F88: =SUMIFS('Raw Data'!$F$2:$F$1001,'Raw Data'!$M$2:$M$1001,A88) -> 12753 | G88: =IFERROR(AVERAGEIFS('Raw Data'!$K$2:$K$1001,'Raw Data'!$M$2:$M$1001,A88),0) -> 0.15222656 | H88: =IFERROR(SUMIFS('Raw Data'!$R$2:$R$1001,'Raw Data'!$M$2:$M$1001,A88)/SUMIFS('Raw Data'!$P$2:$P$1001,'Raw Data'!$M$2:$M$1001,A88),0) -> -0.067752203 | I88: =RANK(C88,$C$87:$C$88,0) -> 1
A89: Total | B89: =SUM(B87:B88) -> 1000 | C89: =SUM(C87:C88) -> 5019265.2 | D89: =SUM(D87:D88) -> 1 | F89: =SUM(F87:F88) -> 25355
A90: Top channel (by sales) | B90: =INDEX(A87:A88,MATCH(MAX(C87:C88),C87:C88,0)) -> Retail
A91: Lowest channel (by sales) | B91: =INDEX(A87:A88,MATCH(MIN(C87:C88),C87:C88,0)) -> Online
A93: 8. Customer Type
A94: Customer Type | B94: Transactions | C94: Sales | D94: Share | E94: Avg Sale | F94: Units | G94: Avg Discount | H94: Net Margin % | I94: Rank
A95: New | B95: =COUNTIFS('Raw Data'!$J$2:$J$1001,A95) -> 504 | C95: =SUMIFS('Raw Data'!$E$2:$E$1001,'Raw Data'!$J$2:$J$1001,A95) -> 2506258.3 | D95: =C95/$B$35 -> 0.49932773 | E95: =IF(B95=0,0,C95/B95) -> 4972.7347 | F95: =SUMIFS('Raw Data'!$F$2:$F$1001,'Raw Data'!$J$2:$J$1001,A95) -> 13184 | G95: =IFERROR(AVERAGEIFS('Raw Data'!$K$2:$K$1001,'Raw Data'!$J$2:$J$1001,A95),0) -> 0.15172619 | H95: =IFERROR(SUMIFS('Raw Data'!$R$2:$R$1001,'Raw Data'!$J$2:$J$1001,A95)/SUMIFS('Raw Data'!$P$2:$P$1001,'Raw Data'!$J$2:$J$1001,A95),0) -> -0.062028842 | I95: =RANK(C95,$C$95:$C$96,0) -> 2
A96: Returning | B96: =COUNTIFS('Raw Data'!$J$2:$J$1001,A96) -> 496 | C96: =SUMIFS('Raw Data'!$E$2:$E$1001,'Raw Data'!$J$2:$J$1001,A96) -> 2513006.9 | D96: =C96/$B$35 -> 0.50067227 | E96: =IF(B96=0,0,C96/B96) -> 5066.5462 | F96: =SUMIFS('Raw Data'!$F$2:$F$1001,'Raw Data'!$J$2:$J$1001,A96) -> 12171 | G96: =IFERROR(AVERAGEIFS('Raw Data'!$K$2:$K$1001,'Raw Data'!$J$2:$J$1001,A96),0) -> 0.15306452 | H96: =IFERROR(SUMIFS('Raw Data'!$R$2:$R$1001,'Raw Data'!$J$2:$J$1001,A96)/SUMIFS('Raw Data'!$P$2:$P$1001,'Raw Data'!$J$2:$J$1001,A96),0) -> -0.077934697 | I96: =RANK(C96,$C$95:$C$96,0) -> 1
A97: Total | B97: =SUM(B95:B96) -> 1000 | C97: =SUM(C95:C96) -> 5019265.2 | D97: =SUM(D95:D96) -> 1 | F97: =SUM(F95:F96) -> 25355
A98: Top customer type (by sales) | B98: =INDEX(A95:A96,MATCH(MAX(C95:C96),C95:C96,0)) -> Returning
A99: Lowest customer type (by sales) | B99: =INDEX(A95:A96,MATCH(MIN(C95:C96),C95:C96,0)) -> New
A101: 9. Payment Method
A102: Payment | B102: Transactions | C102: Sales | D102: Share | E102: Avg Sale | F102: Units | G102: Avg Discount | H102: Net Margin % | I102: Rank
A103: Bank Transfer | B103: =COUNTIFS('Raw Data'!$L$2:$L$1001,A103) -> 342 | C103: =SUMIFS('Raw Data'!$E$2:$E$1001,'Raw Data'!$L$2:$L$1001,A103) -> 1717363.2 | D103: =C103/$B$35 -> 0.3421543 | E103: =IF(B103=0,0,C103/B103) -> 5021.5297 | F103: =SUMIFS('Raw Data'!$F$2:$F$1001,'Raw Data'!$L$2:$L$1001,A103) -> 8696 | G103: =IFERROR(AVERAGEIFS('Raw Data'!$K$2:$K$1001,'Raw Data'!$L$2:$L$1001,A103),0) -> 0.15350877 | H103: =IFERROR(SUMIFS('Raw Data'!$R$2:$R$1001,'Raw Data'!$L$2:$L$1001,A103)/SUMIFS('Raw Data'!$P$2:$P$1001,'Raw Data'!$L$2:$L$1001,A103),0) -> -0.072500366 | I103: =RANK(C103,$C$103:$C$105,0) -> 2
A104: Cash | B104: =COUNTIFS('Raw Data'!$L$2:$L$1001,A104) -> 313 | C104: =SUMIFS('Raw Data'!$E$2:$E$1001,'Raw Data'!$L$2:$L$1001,A104) -> 1544338.5 | D104: =C104/$B$35 -> 0.30768219 | E104: =IF(B104=0,0,C104/B104) -> 4933.9889 | F104: =SUMIFS('Raw Data'!$F$2:$F$1001,'Raw Data'!$L$2:$L$1001,A104) -> 8218 | G104: =IFERROR(AVERAGEIFS('Raw Data'!$K$2:$K$1001,'Raw Data'!$L$2:$L$1001,A104),0) -> 0.15172524 | H104: =IFERROR(SUMIFS('Raw Data'!$R$2:$R$1001,'Raw Data'!$L$2:$L$1001,A104)/SUMIFS('Raw Data'!$P$2:$P$1001,'Raw Data'!$L$2:$L$1001,A104),0) -> -0.065929509 | I104: =RANK(C104,$C$103:$C$105,0) -> 3
A105: Credit Card | B105: =COUNTIFS('Raw Data'!$L$2:$L$1001,A105) -> 345 | C105: =SUMIFS('Raw Data'!$E$2:$E$1001,'Raw Data'!$L$2:$L$1001,A105) -> 1757563.5 | D105: =C105/$B$35 -> 0.35016351 | E105: =IF(B105=0,0,C105/B105) -> 5094.387 | F105: =SUMIFS('Raw Data'!$F$2:$F$1001,'Raw Data'!$L$2:$L$1001,A105) -> 8441 | G105: =IFERROR(AVERAGEIFS('Raw Data'!$K$2:$K$1001,'Raw Data'!$L$2:$L$1001,A105),0) -> 0.15188406 | H105: =IFERROR(SUMIFS('Raw Data'!$R$2:$R$1001,'Raw Data'!$L$2:$L$1001,A105)/SUMIFS('Raw Data'!$P$2:$P$1001,'Raw Data'!$L$2:$L$1001,A105),0) -> -0.070113614 | I105: =RANK(C105,$C$103:$C$105,0) -> 1
A106: Total | B106: =SUM(B103:B105) -> 1000 | C106: =SUM(C103:C105) -> 5019265.2 | D106: =SUM(D103:D105) -> 1 | F106: =SUM(F103:F105) -> 25355
A107: Top payment (by sales) | B107: =INDEX(A103:A105,MATCH(MAX(C103:C105),C103:C105,0)) -> Credit Card
A108: Lowest payment (by sales) | B108: =INDEX(A103:A105,MATCH(MIN(C103:C105),C103:C105,0)) -> Cash
A110: 10. Discount Bands (discount vs margin)
A111: Discount Band | B111: Transactions | C111: Sales | D111: Share | E111: Avg Sale | F111: Units | G111: Avg Discount | H111: Net Margin % | I111: Rank
A112: 0-9% | B112: =COUNTIFS('Raw Data'!$U$2:$U$1001,A112) -> 313 | C112: =SUMIFS('Raw Data'!$E$2:$E$1001,'Raw Data'!$U$2:$U$1001,A112) -> 1559624.6 | D112: =C112/$B$35 -> 0.31072768 | E112: =IF(B112=0,0,C112/B112) -> 4982.8263 | F112: =SUMIFS('Raw Data'!$F$2:$F$1001,'Raw Data'!$U$2:$U$1001,A112) -> 8093 | G112: =IFERROR(AVERAGEIFS('Raw Data'!$K$2:$K$1001,'Raw Data'!$U$2:$U$1001,A112),0) -> 0.047635783 | H112: =IFERROR(SUMIFS('Raw Data'!$R$2:$R$1001,'Raw Data'!$U$2:$U$1001,A112)/SUMIFS('Raw Data'!$P$2:$P$1001,'Raw Data'!$U$2:$U$1001,A112),0) -> 0.045253605 | I112: =RANK(C112,$C$112:$C$114,0) -> 2
...

Sheet Performance
A1: Performance: GroupBy by Region-Rep, Pareto/ABC, Top Transactions
A2: No customer ID exists in this dataset, so the high-value GroupBy is built on Region-Rep combinations (matches Region_and_Sales_Rep). Tier: High-Value = 80th percentile or above, Mid = 50th to 80th, Low = below the median. | L2: Pareto / ABC ranking | S2: Top 10 Transactions (LARGE / INDEX-MATCH)
A3: Region-Rep | B3: Region | C3: Sales Rep | D3: Sales | E3: Transactions | F3: Avg Sale | G3: Net Margin % | H3: Rank | I3: Tier | J3: Share | L3: Rank | M3: Region-Rep | N3: Sales | O3: Share | P3: Cumulative | Q3: Class | S3: Rank | T3: Order_Code | U3: Date | V3: Rep | W3: Region | X3: Category | Y3: Channel | Z3: Sales_Amount
A4: East-Alice | B4: East | C4: Alice | D4: =SUMIFS('Raw Data'!$E$2:$E$1001,'Raw Data'!$N$2:$N$1001,A4) -> 260789.47 | E4: =COUNTIFS('Raw Data'!$N$2:$N$1001,A4) -> 52 | F4: =IF(E4=0,0,D4/E4) -> 5015.1821 | G4: =IFERROR(SUMIFS('Raw Data'!$R$2:$R$1001,'Raw Data'!$N$2:$N$1001,A4)/SUMIFS('Raw Data'!$P$2:$P$1001,'Raw Data'!$N$2:$N$1001,A4),0) -> -0.067180386 | H4: =RANK(D4,$D$4:$D$23,0)+COUNTIF($D$4:D4,D4)-1 -> 9 | I4: =IF(D4>=PERCENTILE($D$4:$D$23,0.8),"High-Value",IF(D4>=PERCENTILE($D$4:$D$23,0.5),"Mid","Low")) -> Mid | J4: =D4/SUM($D$4:$D$23) -> 0.051957699 | L4: 1 | M4: =INDEX($A$4:$A$23,MATCH(L4,$H$4:$H$23,0)) -> South-David | N4: =INDEX($D$4:$D$23,MATCH(L4,$H$4:$H$23,0)) -> 311416.99 | O4: =N4/SUM($D$4:$D$23) -> 0.062044338 | P4: =SUM($O$4:O4) -> 0.062044338 | Q4: =IF(P4<=0.8,"A",IF(P4<=0.95,"B","C")) -> A | S4: 1 | T4: =INDEX('Raw Data'!$AG$2:$AG$1001,MATCH($S4,'Raw Data'!$AL$2:$AL$1001,0)) -> NR-231210-0756 | U4: =INDEX('Raw Data'!$B$2:$B$1001,MATCH($S4,'Raw Data'!$AL$2:$AL$1001,0)) -> 45270 | V4: =INDEX('Raw Data'!$C$2:$C$1001,MATCH($S4,'Raw Data'!$AL$2:$AL$1001,0)) -> David | W4: =INDEX('Raw Data'!$D$2:$D$1001,MATCH($S4,'Raw Data'!$AL$2:$AL$1001,0)) -> North | X4: =INDEX('Raw Data'!$G$2:$G$1001,MATCH($S4,'Raw Data'!$AL$2:$AL$1001,0)) -> Food | Y4: =INDEX('Raw Data'!$M$2:$M$1001,MATCH($S4,'Raw Data'!$AL$2:$AL$1001,0)) -> Retail | Z4: =INDEX('Raw Data'!$E$2:$E$1001,MATCH($S4,'Raw Data'!$AL$2:$AL$1001,0)) -> 9989.04
A5: East-Bob | B5: East | C5: Bob | D5: =SUMIFS('Raw Data'!$E$2:$E$1001,'Raw Data'!$N$2:$N$1001,A5) -> 309876.11 | E5: =COUNTIFS('Raw Data'!$N$2:$N$1001,A5) -> 60 | F5: =IF(E5=0,0,D5/E5) -> 5164.6018 | G5: =IFERROR(SUMIFS('Raw Data'!$R$2:$R$1001,'Raw Data'!$N$2:$N$1001,A5)/SUMIFS('Raw Data'!$P$2:$P$1001,'Raw Data'!$N$2:$N$1001,A5),0) -> -0.10167661 | H5: =RANK(D5,$D$4:$D$23,0)+COUNTIF($D$4:D5,D5)-1 -> 2 | I5: =IF(D5>=PERCENTILE($D$4:$D$23,0.8),"High-Value",IF(D5>=PERCENTILE($D$4:$D$23,0.5),"Mid","Low")) -> High-Value | J5: =D5/SUM($D$4:$D$23) -> 0.061737345 | L5: 2 | M5: =INDEX($A$4:$A$23,MATCH(L5,$H$4:$H$23,0)) -> East-Bob | N5: =INDEX($D$4:$D$23,MATCH(L5,$H$4:$H$23,0)) -> 309876.11 | O5: =N5/SUM($D$4:$D$23) -> 0.061737345 | P5: =SUM($O$4:O5) -> 0.12378168 | Q5: =IF(P5<=0.8,"A",IF(P5<=0.95,"B","C")) -> A | S5: 2 | T5: =INDEX('Raw Data'!$AG$2:$AG$1001,MATCH($S5,'Raw Data'!$AL$2:$AL$1001,0)) -> NR-230821-0761 | U5: =INDEX('Raw Data'!$B$2:$B$1001,MATCH($S5,'Raw Data'!$AL$2:$AL$1001,0)) -> 45159 | V5: =INDEX('Raw Data'!$C$2:$C$1001,MATCH($S5,'Raw Data'!$AL$2:$AL$1001,0)) -> David | W5: =INDEX('Raw Data'!$D$2:$D$1001,MATCH($S5,'Raw Data'!$AL$2:$AL$1001,0)) -> North | X5: =INDEX('Raw Data'!$G$2:$G$1001,MATCH($S5,'Raw Data'!$AL$2:$AL$1001,0)) -> Furniture | Y5: =INDEX('Raw Data'!$M$2:$M$1001,MATCH($S5,'Raw Data'!$AL$2:$AL$1001,0)) -> Retail | Z5: =INDEX('Raw Data'!$E$2:$E$1001,MATCH($S5,'Raw Data'!$AL$2:$AL$1001,0)) -> 9976.52
A6: East-Charlie | B6: East | C6: Charlie | D6: =SUMIFS('Raw Data'!$E$2:$E$1001,'Raw Data'!$N$2:$N$1001,A6) -> 165172.94 | E6: =COUNTIFS('Raw Data'!$N$2:$N$1001,A6) -> 37 | F6: =IF(E6=0,0,D6/E6) -> 4464.1335 | G6: =IFERROR(SUMIFS('Raw Data'!$R$2:$R$1001,'Raw Data'!$N$2:$N$1001,A6)/SUMIFS('Raw Data'!$P$2:$P$1001,'Raw Data'!$N$2:$N$1001,A6),0) -> -0.082355996 | H6: =RANK(D6,$D$4:$D$23,0)+COUNTIF($D$4:D6,D6)-1 -> 19 | I6: =IF(D6>=PERCENTILE($D$4:$D$23,0.8),"High-Value",IF(D6>=PERCENTILE($D$4:$D$23,0.5),"Mid","Low")) -> Low | J6: =D6/SUM($D$4:$D$23) -> 0.032907793 | L6: 3 | M6: =INDEX($A$4:$A$23,MATCH(L6,$H$4:$H$23,0)) -> North-Eve | N6: =INDEX($D$4:$D$23,MATCH(L6,$H$4:$H$23,0)) -> 304172.2 | O6: =N6/SUM($D$4:$D$23) -> 0.060600942 | P6: =SUM($O$4:O6) -> 0.18438263 | Q6: =IF(P6<=0.8,"A",IF(P6<=0.95,"B","C")) -> A | S6: 3 | T6: =INDEX('Raw Data'!$AG$2:$AG$1001,MATCH($S6,'Raw Data'!$AL$2:$AL$1001,0)) -> NO-230824-0856 | U6: =INDEX('Raw Data'!$B$2:$B$1001,MATCH($S6,'Raw Data'!$AL$2:$AL$1001,0)) -> 45162 | V6: =INDEX('Raw Data'!$C$2:$C$1001,MATCH($S6,'Raw Data'!$AL$2:$AL$1001,0)) -> Alice | W6: =INDEX('Raw Data'!$D$2:$D$1001,MATCH($S6,'Raw Data'!$AL$2:$AL$1001,0)) -> North | X6: =INDEX('Raw Data'!$G$2:$G$1001,MATCH($S6,'Raw Data'!$AL$2:$AL$1001,0)) -> Clothing | Y6: =INDEX('Raw Data'!$M$2:$M$1001,MATCH($S6,'Raw Data'!$AL$2:$AL$1001,0)) -> Online | Z6: =INDEX('Raw Data'!$E$2:$E$1001,MATCH($S6,'Raw Data'!$AL$2:$AL$1001,0)) -> 9972.66
A7: East-David | B7: East | C7: David | D7: =SUMIFS('Raw Data'!$E$2:$E$1001,'Raw Data'!$N$2:$N$1001,A7) -> 284613.51 | E7: =COUNTIFS('Raw Data'!$N$2:$N$1001,A7) -> 59 | F7: =IF(E7=0,0,D7/E7) -> 4823.9578 | G7: =IFERROR(SUMIFS('Raw Data'!$R$2:$R$1001,'Raw Data'!$N$2:$N$1001,A7)/SUMIFS('Raw Data'!$P$2:$P$1001,'Raw Data'!$N$2:$N$1001,A7),0) -> -0.080190931 | H7: =RANK(D7,$D$4:$D$23,0)+COUNTIF($D$4:D7,D7)-1 -> 6 | I7: =IF(D7>=PERCENTILE($D$4:$D$23,0.8),"High-Value",IF(D7>=PERCENTILE($D$4:$D$23,0.5),"Mid","Low")) -> Mid | J7: =D7/SUM($D$4:$D$23) -> 0.056704218 | L7: 4 | M7: =INDEX($A$4:$A$23,MATCH(L7,$H$4:$H$23,0)) -> North-Charlie | N7: =INDEX($D$4:$D$23,MATCH(L7,$H$4:$H$23,0)) -> 299789.01 | O7: =N7/SUM($D$4:$D$23) -> 0.059727669 | P7: =SUM($O$4:O7) -> 0.24411029 | Q7: =IF(P7<=0.8,"A",IF(P7<=0.95,"B","C")) -> A | S7: 4 | T7: =INDEX('Raw Data'!$AG$2:$AG$1001,MATCH($S7,'Raw Data'!$AL$2:$AL$1001,0)) -> NR-230815-0655 | U7: =INDEX('Raw Data'!$B$2:$B$1001,MATCH($S7,'Raw Data'!$AL$2:$AL$1001,0)) -> 45153 | V7: =INDEX('Raw Data'!$C$2:$C$1001,MATCH($S7,'Raw Data'!$AL$2:$AL$1001,0)) -> Charlie | W7: =INDEX('Raw Data'!$D$2:$D$1001,MATCH($S7,'Raw Data'!$AL$2:$AL$1001,0)) -> North | X7: =INDEX('Raw Data'!$G$2:$G$1001,MATCH($S7,'Raw Data'!$AL$2:$AL$1001,0)) -> Clothing | Y7: =INDEX('Raw Data'!$M$2:$M$1001,MATCH($S7,'Raw Data'!$AL$2:$AL$1001,0)) -> Retail | Z7: =INDEX('Raw Data'!$E$2:$E$1001,MATCH($S7,'Raw Data'!$AL$2:$AL$1001,0)) -> 9972.11
A8: East-Eve | B8: East | C8: Eve | D8: =SUMIFS('Raw Data'!$E$2:$E$1001,'Raw Data'!$N$2:$N$1001,A8) -> 239340.9 | E8: =COUNTIFS('Raw Data'!$N$2:$N$1001,A8) -> 55 | F8: =IF(E8=0,0,D8/E8) -> 4351.6527 | G8: =IFERROR(SUMIFS('Raw Data'!$R$2:$R$1001,'Raw Data'!$N$2:$N$1001,A8)/SUMIFS('Raw Data'!$P$2:$P$1001,'Raw Data'!$N$2:$N$1001,A8),0) -> -0.07234197 | H8: =RANK(D8,$D$4:$D$23,0)+COUNTIF($D$4:D8,D8)-1 -> 14 | I8: =IF(D8>=PERCENTILE($D$4:$D$23,0.8),"High-Value",IF(D8>=PERCENTILE($D$4:$D$23,0.5),"Mid","Low")) -> Low | J8: =D8/SUM($D$4:$D$23) -> 0.04768445 | L8: 5 | M8: =INDEX($A$4:$A$23,MATCH(L8,$H$4:$H$23,0)) -> West-Bob | N8: =INDEX($D$4:$D$23,MATCH(L8,$H$4:$H$23,0)) -> 286449.28 | O8: =N8/SUM($D$4:$D$23) -> 0.057069963 | P8: =SUM($O$4:O8) -> 0.30118026 | Q8: =IF(P8<=0.8,"A",IF(P8<=0.95,"B","C")) -> A | S8: 5 | T8: =INDEX('Raw Data'!$AG$2:$AG$1001,MATCH($S8,'Raw Data'!$AL$2:$AL$1001,0)) -> SO-230423-0749 | U8: =INDEX('Raw Data'!$B$2:$B$1001,MATCH($S8,'Raw Data'!$AL$2:$AL$1001,0)) -> 45039 | V8: =INDEX('Raw Data'!$C$2:$C$1001,MATCH($S8,'Raw Data'!$AL$2:$AL$1001,0)) -> David | W8: =INDEX('Raw Data'!$D$2:$D$1001,MATCH($S8,'Raw Data'!$AL$2:$AL$1001,0)) -> South | X8: =INDEX('Raw Data'!$G$2:$G$1001,MATCH($S8,'Raw Data'!$AL$2:$AL$1001,0)) -> Furniture | Y8: =INDEX('Raw Data'!$M$2:$M$1001,MATCH($S8,'Raw Data'!$AL$2:$AL$1001,0)) -> Online | Z8: =INDEX('Raw Data'!$E$2:$E$1001,MATCH($S8,'Raw Data'!$AL$2:$AL$1001,0)) -> 9961.96
A9: North-Alice | B9: North | C9: Alice | D9: =SUMIFS('Raw Data'!$E$2:$E$1001,'Raw Data'!$N$2:$N$1001,A9) -> 249647.22 | E9: =COUNTIFS('Raw Data'!$N$2:$N$1001,A9) -> 48 | F9: =IF(E9=0,0,D9/E9) -> 5200.9838 | G9: =IFERROR(SUMIFS('Raw Data'!$R$2:$R$1001,'Raw Data'!$N$2:$N$1001,A9)/SUMIFS('Raw Data'!$P$2:$P$1001,'Raw Data'!$N$2:$N$1001,A9),0) -> -0.034112274 | H9: =RANK(D9,$D$4:$D$23,0)+COUNTIF($D$4:D9,D9)-1 -> 11 | I9: =IF(D9>=PERCENTILE($D$4:$D$23,0.8),"High-Value",IF(D9>=PERCENTILE($D$4:$D$23,0.5),"Mid","Low")) -> Low | J9: =D9/SUM($D$4:$D$23) -> 0.049737802 | L9: 6 | M9: =INDEX($A$4:$A$23,MATCH(L9,$H$4:$H$23,0)) -> East-David | N9: =INDEX($D$4:$D$23,MATCH(L9,$H$4:$H$23,0)) -> 284613.51 | O9: =N9/SUM($D$4:$D$23) -> 0.056704218 | P9: =SUM($O$4:O9) -> 0.35788447 | Q9: =IF(P9<=0.8,"A",IF(P9<=0.95,"B","C")) -> A | S9: 6 | T9: =INDEX('Raw Data'!$AG$2:$AG$1001,MATCH($S9,'Raw Data'!$AL$2:$AL$1001,0)) -> NO-230814-0797 | U9: =INDEX('Raw Data'!$B$2:$B$1001,MATCH($S9,'Raw Data'!$AL$2:$AL$1001,0)) -> 45152 | V9: =INDEX('Raw Data'!$C$2:$C$1001,MATCH($S9,'Raw Data'!$AL$2:$AL$1001,0)) -> Bob | W9: =INDEX('Raw Data'!$D$2:$D$1001,MATCH($S9,'Raw Data'!$AL$2:$AL$1001,0)) -> North | X9: =INDEX('Raw Data'!$G$2:$G$1001,MATCH($S9,'Raw Data'!$AL$2:$AL$1001,0)) -> Clothing | Y9: =INDEX('Raw Data'!$M$2:$M$1001,MATCH($S9,'Raw Data'!$AL$2:$AL$1001,0)) -> Online | Z9: =INDEX('Raw Data'!$E$2:$E$1001,MATCH($S9,'Raw Data'!$AL$2:$AL$1001,0)) -> 9956.75
A10: North-Bob | B10: North | C10: Bob | D10: =SUMIFS('Raw Data'!$E$2:$E$1001,'Raw Data'!$N$2:$N$1001,A10) -> 233464.81 | E10: =COUNTIFS('Raw Data'!$N$2:$N$1001,A10) -> 44 | F10: =IF(E10=0,0,D10/E10) -> 5306.0184 | G10: =IFERROR(SUMIFS('Raw Data'!$R$2:$R$1001,'Raw Data'!$N$2:$N$1001,A10)/SUMIFS('Raw Data'!$P$2:$P$1001,'Raw Data'!$N$2:$N$1001,A10),0) -> -0.074635448 | H10: =RANK(D10,$D$4:$D$23,0)+COUNTIF($D$4:D10,D10)-1 -> 15 | I10: =IF(D10>=PERCENTILE($D$4:$D$23,0.8),"High-Value",IF(D10>=PERCENTILE($D$4:$D$23,0.5),"Mid","Low")) -> Low | J10: =D10/SUM($D$4:$D$23) -> 0.046513742 | L10: 7 | M10: =INDEX($A$4:$A$23,MATCH(L10,$H$4:$H$23,0)) -> North-David | N10: =INDEX($D$4:$D$23,MATCH(L10,$H$4:$H$23,0)) -> 282539.27 | O10: =N10/SUM($D$4:$D$23) -> 0.056290962 | P10: =SUM($O$4:O10) -> 0.41417544 | Q10: =IF(P10<=0.8,"A",IF(P10<=0.95,"B","C")) -> A | S10: 7 | T10: =INDEX('Raw Data'!$AG$2:$AG$1001,MATCH($S10,'Raw Data'!$AL$2:$AL$1001,0)) -> EO-230414-0143 | U10: =INDEX('Raw Data'!$B$2:$B$1001,MATCH($S10,'Raw Data'!$AL$2:$AL$1001,0)) -> 45030 | V10: =INDEX('Raw Data'!$C$2:$C$1001,MATCH($S10,'Raw Data'!$AL$2:$AL$1001,0)) -> Alice | W10: =INDEX('Raw Data'!$D$2:$D$1001,MATCH($S10,'Raw Data'!$AL$2:$AL$1001,0)) -> East | X10: =INDEX('Raw Data'!$G$2:$G$1001,MATCH($S10,'Raw Data'!$AL$2:$AL$1001,0)) -> Food | Y10: =INDEX('Raw Data'!$M$2:$M$1001,MATCH($S10,'Raw Data'!$AL$2:$AL$1001,0)) -> Online | Z10: =INDEX('Raw Data'!$E$2:$E$1001,MATCH($S10,'Raw Data'!$AL$2:$AL$1001,0)) -> 9948.71
A11: North-Charlie | B11: North | C11: Charlie | D11: =SUMIFS('Raw Data'!$E$2:$E$1001,'Raw Data'!$N$2:$N$1001,A11) -> 299789.01 | E11: =COUNTIFS('Raw Data'!$N$2:$N$1001,A11) -> 55 | F11: =IF(E11=0,0,D11/E11) -> 5450.7093 | G11: =IFERROR(SUMIFS('Raw Data'!$R$2:$R$1001,'Raw Data'!$N$2:$N$1001,A11)/SUMIFS('Raw Data'!$P$2:$P$1001,'Raw Data'!$N$2:$N$1001,A11),0) -> -0.051989203 | H11: =RANK(D11,$D$4:$D$23,0)+COUNTIF($D$4:D11,D11)-1 -> 4 | I11: =IF(D11>=PERCENTILE($D$4:$D$23,0.8),"High-Value",IF(D11>=PERCENTILE($D$4:$D$23,0.5),"Mid","Low")) -> High-Value | J11: =D11/SUM($D$4:$D$23) -> 0.059727669 | L11: 8 | M11: =INDEX($A$4:$A$23,MATCH(L11,$H$4:$H$23,0)) -> West-David | N11: =INDEX($D$4:$D$23,MATCH(L11,$H$4:$H$23,0)) -> 263167.59 | O11: =N11/SUM($D$4:$D$23) -> 0.052431497 | P11: =SUM($O$4:O11) -> 0.46660693 | Q11: =IF(P11<=0.8,"A",IF(P11<=0.95,"B","C")) -> A | S11: 8 | T11: =INDEX('Raw Data'!$AG$2:$AG$1001,MATCH($S11,'Raw Data'!$AL$2:$AL$1001,0)) -> WR-231019-0190 | U11: =INDEX('Raw Data'!$B$2:$B$1001,MATCH($S11,'Raw Data'!$AL$2:$AL$1001,0)) -> 45218 | V11: =INDEX('Raw Data'!$C$2:$C$1001,MATCH($S11,'Raw Data'!$AL$2:$AL$1001,0)) -> Eve | W11: =INDEX('Raw Data'!$D$2:$D$1001,MATCH($S11,'Raw Data'!$AL$2:$AL$1001,0)) -> West | X11: =INDEX('Raw Data'!$G$2:$G$1001,MATCH($S11,'Raw Data'!$AL$2:$AL$1001,0)) -> Food | Y11: =INDEX('Raw Data'!$M$2:$M$1001,MATCH($S11,'Raw Data'!$AL$2:$AL$1001,0)) -> Retail | Z11: =INDEX('Raw Data'!$E$2:$E$1001,MATCH($S11,'Raw Data'!$AL$2:$AL$1001,0)) -> 9933.22
A12: North-David | B12: North | C12: David | D12: =SUMIFS('Raw Data'!$E$2:$E$1001,'Raw Data'!$N$2:$N$1001,A12) -> 282539.27 | E12: =COUNTIFS('Raw Data'!$N$2:$N$1001,A12) -> 56 | F12: =IF(E12=0,0,D12/E12) -> 5045.3441 | G12: =IFERROR(SUMIFS('Raw Data'!$R$2:$R$1001,'Raw Data'!$N$2:$N$1001,A12)/SUMIFS('Raw Data'!$P$2:$P$1001,'Raw Data'!$N$2:$N$1001,A12),0) -> -0.095243245 | H12: =RANK(D12,$D$4:$D$23,0)+COUNTIF($D$4:D12,D12)-1 -> 7 | I12: =IF(D12>=PERCENTILE($D$4:$D$23,0.8),"High-Value",IF(D12>=PERCENTILE($D$4:$D$23,0.5),"Mid","Low")) -> Mid | J12: =D12/SUM($D$4:$D$23) -> 0.056290962 | L12: 9 | M12: =INDEX($A$4:$A$23,MATCH(L12,$H$4:$H$23,0)) -> East-Alice | N12: =INDEX($D$4:$D$23,MATCH(L12,$H$4:$H$23,0)) -> 260789.47 | O12: =N12/SUM($D$4:$D$23) -> 0.051957699 | P12: =SUM($O$4:O12) -> 0.51856463 | Q12: =IF(P12<=0.8,"A",IF(P12<=0.95,"B","C")) -> A | S12: 9 | T12: =INDEX('Raw Data'!$AG$2:$AG$1001,MATCH($S12,'Raw Data'!$AL$2:$AL$1001,0)) -> SR-230922-0090 | U12: =INDEX('Raw Data'!$B$2:$B$1001,MATCH($S12,'Raw Data'!$AL$2:$AL$1001,0)) -> 45191 | V12: =INDEX('Raw Data'!$C$2:$C$1001,MATCH($S12,'Raw Data'!$AL$2:$AL$1001,0)) -> David | W12: =INDEX('Raw Data'!$D$2:$D$1001,MATCH($S12,'Raw Data'!$AL$2:$AL$1001,0)) -> South | X12: =INDEX('Raw Data'!$G$2:$G$1001,MATCH($S12,'Raw Data'!$AL$2:$AL$1001,0)) -> Electronics | Y12: =INDEX('Raw Data'!$M$2:$M$1001,MATCH($S12,'Raw Data'!$AL$2:$AL$1001,0)) -> Retail | Z12: =INDEX('Raw Data'!$E$2:$E$1001,MATCH($S12,'Raw Data'!$AL$2:$AL$1001,0)) -> 9914.15
A13: North-Eve | B13: North | C13: Eve | D13: =SUMIFS('Raw Data'!$E$2:$E$1001,'Raw Data'!$N$2:$N$1001,A13) -> 304172.2 | E13: =COUNTIFS('Raw Data'!$N$2:$N$1001,A13) -> 64 | F13: =IF(E13=0,0,D13/E13) -> 4752.6906 | G13: =IFERROR(SUMIFS('Raw Data'!$R$2:$R$1001,'Raw Data'!$N$2:$N$1001,A13)/SUMIFS('Raw Data'!$P$2:$P$1001,'Raw Data'!$N$2:$N$1001,A13),0) -> -0.044670885 | H13: =RANK(D13,$D$4:$D$23,0)+COUNTIF($D$4:D13,D13)-1 -> 3 | I13: =IF(D13>=PERCENTILE($D$4:$D$23,0.8),"High-Value",IF(D13>=PERCENTILE($D$4:$D$23,0.5),"Mid","Low")) -> High-Value | J13: =D13/SUM($D$4:$D$23) -> 0.060600942 | L13: 10 | M13: =INDEX($A$4:$A$23,MATCH(L13,$H$4:$H$23,0)) -> South-Bob | N13: =INDEX($D$4:$D$23,MATCH(L13,$H$4:$H$23,0)) -> 251200.43 | O13: =N13/SUM($D$4:$D$23) -> 0.050047252 | P13: =SUM($O$4:O13) -> 0.56861188 | Q13: =IF(P13<=0.8,"A",IF(P13<=0.95,"B","C")) -> A | S13: 10 | T13: =INDEX('Raw Data'!$AG$2:$AG$1001,MATCH($S13,'Raw Data'!$AL$2:$AL$1001,0)) -> NO-231012-0785 | U13: =INDEX('Raw Data'!$B$2:$B$1001,MATCH($S13,'Raw Data'!$AL$2:$AL$1001,0)) -> 45211 | V13: =INDEX('Raw Data'!$C$2:$C$1001,MATCH($S13,'Raw Data'!$AL$2:$AL$1001,0)) -> Charlie | W13: =INDEX('Raw Data'!$D$2:$D$1001,MATCH($S13,'Raw Data'!$AL$2:$AL$1001,0)) -> North | X13: =INDEX('Raw Data'!$G$2:$G$1001,MATCH($S13,'Raw Data'!$AL$2:$AL$1001,0)) -> Furniture | Y13: =INDEX('Raw Data'!$M$2:$M$1001,MATCH($S13,'Raw Data'!$AL$2:$AL$1001,0)) -> Online | Z13: =INDEX('Raw Data'!$E$2:$E$1001,MATCH($S13,'Raw Data'!$AL$2:$AL$1001,0)) -> 9907.72
A14: South-Alice | B14: South | C14: Alice | D14: =SUMIFS('Raw Data'!$E$2:$E$1001,'Raw Data'!$N$2:$N$1001,A14) -> 239414.54 | E14: =COUNTIFS('Raw Data'!$N$2:$N$1001,A14) -> 45 | F14: =IF(E14=0,0,D14/E14) -> 5320.3231 | G14: =IFERROR(SUMIFS('Raw Data'!$R$2:$R$1001,'Raw Data'!$N$2:$N$1001,A14)/SUMIFS('Raw Data'!$P$2:$P$1001,'Raw Data'!$N$2:$N$1001,A14),0) -> -0.07856639 | H14: =RANK(D14,$D$4:$D$23,0)+COUNTIF($D$4:D14,D14)-1 -> 13 | I14: =IF(D14>=PERCENTILE($D$4:$D$23,0.8),"High-Value",IF(D14>=PERCENTILE($D$4:$D$23,0.5),"Mid","Low")) -> Low | J14: =D14/SUM($D$4:$D$23) -> 0.047699121 | L14: 11 | M14: =INDEX($A$4:$A$23,MATCH(L14,$H$4:$H$23,0)) -> North-Alice | N14: =INDEX($D$4:$D$23,MATCH(L14,$H$4:$H$23,0)) -> 249647.22 | O14: =N14/SUM($D$4:$D$23) -> 0.049737802 | P14: =SUM($O$4:O14) -> 0.61834969 | Q14: =IF(P14<=0.8,"A",IF(P14<=0.95,"B","C")) -> A
A15: South-Bob | B15: South | C15: Bob | D15: =SUMIFS('Raw Data'!$E$2:$E$1001,'Raw Data'!$N$2:$N$1001,A15) -> 251200.43 | E15: =COUNTIFS('Raw Data'!$N$2:$N$1001,A15) -> 50 | F15: =IF(E15=0,0,D15/E15) -> 5024.0086 | G15: =IFERROR(SUMIFS('Raw Data'!$R$2:$R$1001,'Raw Data'!$N$2:$N$1001,A15)/SUMIFS('Raw Data'!$P$2:$P$1001,'Raw Data'!$N$2:$N$1001,A15),0) -> -0.036569273 | H15: =RANK(D15,$D$4:$D$23,0)+COUNTIF($D$4:D15,D15)-1 -> 10 | I15: =IF(D15>=PERCENTILE($D$4:$D$23,0.8),"High-Value",IF(D15>=PERCENTILE($D$4:$D$23,0.5),"Mid","Low")) -> Mid | J15: =D15/SUM($D$4:$D$23) -> 0.050047252 | L15: 12 | M15: =INDEX($A$4:$A$23,MATCH(L15,$H$4:$H$23,0)) -> West-Charlie | N15: =INDEX($D$4:$D$23,MATCH(L15,$H$4:$H$23,0)) -> 239708.85 | O15: =N15/SUM($D$4:$D$23) -> 0.047757757 | P15: =SUM($O$4:O15) -> 0.66610744 | Q15: =IF(P15<=0.8,"A",IF(P15<=0.95,"B","C")) -> A
A16: South-Charlie | B16: South | C16: Charlie | D16: =SUMIFS('Raw Data'!$E$2:$E$1001,'Raw Data'!$N$2:$N$1001,A16) -> 156140.68 | E16: =COUNTIFS('Raw Data'!$N$2:$N$1001,A16) -> 32 | F16: =IF(E16=0,0,D16/E16) -> 4879.3962 | G16: =IFERROR(SUMIFS('Raw Data'!$R$2:$R$1001,'Raw Data'!$N$2:$N$1001,A16)/SUMIFS('Raw Data'!$P$2:$P$1001,'Raw Data'!$N$2:$N$1001,A16),0) -> -0.05076461 | H16: =RANK(D16,$D$4:$D$23,0)+COUNTIF($D$4:D16,D16)-1 -> 20 | I16: =IF(D16>=PERCENTILE($D$4:$D$23,0.8),"High-Value",IF(D16>=PERCENTILE($D$4:$D$23,0.5),"Mid","Low")) -> Low | J16: =D16/SUM($D$4:$D$23) -> 0.031108274 | L16: 13 | M16: =INDEX($A$4:$A$23,MATCH(L16,$H$4:$H$23,0)) -> South-Alice | N16: =INDEX($D$4:$D$23,MATCH(L16,$H$4:$H$23,0)) -> 239414.54 | O16: =N16/SUM($D$4:$D$23) -> 0.047699121 | P16: =SUM($O$4:O16) -> 0.71380656 | Q16: =IF(P16<=0.8,"A",IF(P16<=0.95,"B","C")) -> A
A17: South-David | B17: South | C17: David | D17: =SUMIFS('Raw Data'!$E$2:$E$1001,'Raw Data'!$N$2:$N$1001,A17) -> 311416.99 | E17: =COUNTIFS('Raw Data'!$N$2:$N$1001,A17) -> 56 | F17: =IF(E17=0,0,D17/E17) -> 5561.0177 | G17: =IFERROR(SUMIFS('Raw Data'!$R$2:$R$1001,'Raw Data'!$N$2:$N$1001,A17)/SUMIFS('Raw Data'!$P$2:$P$1001,'Raw Data'!$N$2:$N$1001,A17),0) -> -0.070407378 | H17: =RANK(D17,$D$4:$D$23,0)+COUNTIF($D$4:D17,D17)-1 -> 1 | I17: =IF(D17>=PERCENTILE($D$4:$D$23,0.8),"High-Value",IF(D17>=PERCENTILE($D$4:$D$23,0.5),"Mid","Low")) -> High-Value | J17: =D17/SUM($D$4:$D$23) -> 0.062044338 | L17: 14 | M17: =INDEX($A$4:$A$23,MATCH(L17,$H$4:$H$23,0)) -> East-Eve | N17: =INDEX($D$4:$D$23,MATCH(L17,$H$4:$H$23,0)) -> 239340.9 | O17: =N17/SUM($D$4:$D$23) -> 0.04768445 | P17: =SUM($O$4:O17) -> 0.76149101 | Q17: =IF(P17<=0.8,"A",IF(P17<=0.95,"B","C")) -> A
A18: South-Eve | B18: South | C18: Eve | D18: =SUMIFS('Raw Data'!$E$2:$E$1001,'Raw Data'!$N$2:$N$1001,A18) -> 196078.22 | E18: =COUNTIFS('Raw Data'!$N$2:$N$1001,A18) -> 43 | F18: =IF(E18=0,0,D18/E18) -> 4559.9586 | G18: =IFERROR(SUMIFS('Raw Data'!$R$2:$R$1001,'Raw Data'!$N$2:$N$1001,A18)/SUMIFS('Raw Data'!$P$2:$P$1001,'Raw Data'!$N$2:$N$1001,A18),0) -> -0.067276551 | H18: =RANK(D18,$D$4:$D$23,0)+COUNTIF($D$4:D18,D18)-1 -> 18 | I18: =IF(D18>=PERCENTILE($D$4:$D$23,0.8),"High-Value",IF(D18>=PERCENTILE($D$4:$D$23,0.5),"Mid","Low")) -> Low | J18: =D18/SUM($D$4:$D$23) -> 0.039065124 | L18: 15 | M18: =INDEX($A$4:$A$23,MATCH(L18,$H$4:$H$23,0)) -> North-Bob | N18: =INDEX($D$4:$D$23,MATCH(L18,$H$4:$H$23,0)) -> 233464.81 | O18: =N18/SUM($D$4:$D$23) -> 0.046513742 | P18: =SUM($O$4:O18) -> 0.80800476 | Q18: =IF(P18<=0.8,"A",IF(P18<=0.95,"B","C")) -> B
A19: West-Alice | B19: West | C19: Alice | D19: =SUMIFS('Raw Data'!$E$2:$E$1001,'Raw Data'!$N$2:$N$1001,A19) -> 215690.54 | E19: =COUNTIFS('Raw Data'!$N$2:$N$1001,A19) -> 47 | F19: =IF(E19=0,0,D19/E19) -> 4589.1604 | G19: =IFERROR(SUMIFS('Raw Data'!$R$2:$R$1001,'Raw Data'!$N$2:$N$1001,A19)/SUMIFS('Raw Data'!$P$2:$P$1001,'Raw Data'!$N$2:$N$1001,A19),0) -> -0.031362681 | H19: =RANK(D19,$D$4:$D$23,0)+COUNTIF($D$4:D19,D19)-1 -> 17 | I19: =IF(D19>=PERCENTILE($D$4:$D$23,0.8),"High-Value",IF(D19>=PERCENTILE($D$4:$D$23,0.5),"Mid","Low")) -> Low | J19: =D19/SUM($D$4:$D$23) -> 0.042972533 | L19: 16 | M19: =INDEX($A$4:$A$23,MATCH(L19,$H$4:$H$23,0)) -> West-Eve | N19: =INDEX($D$4:$D$23,MATCH(L19,$H$4:$H$23,0)) -> 230592.67 | O19: =N19/SUM($D$4:$D$23) -> 0.045941519 | P19: =SUM($O$4:O19) -> 0.85394628 | Q19: =IF(P19<=0.8,"A",IF(P19<=0.95,"B","C")) -> B
A20: West-Bob | B20: West | C20: Bob | D20: =SUMIFS('Raw Data'!$E$2:$E$1001,'Raw Data'!$N$2:$N$1001,A20) -> 286449.28 | E20: =COUNTIFS('Raw Data'!$N$2:$N$1001,A20) -> 54 | F20: =IF(E20=0,0,D20/E20) -> 5304.6163 | G20: =IFERROR(SUMIFS('Raw Data'!$R$2:$R$1001,'Raw Data'!$N$2:$N$1001,A20)/SUMIFS('Raw Data'!$P$2:$P$1001,'Raw Data'!$N$2:$N$1001,A20),0) -> -0.046356405 | H20: =RANK(D20,$D$4:$D$23,0)+COUNTIF($D$4:D20,D20)-1 -> 5 | I20: =IF(D20>=PERCENTILE($D$4:$D$23,0.8),"High-Value",IF(D20>=PERCENTILE($D$4:$D$23,0.5),"Mid","Low")) -> Mid | J20: =D20/SUM($D$4:$D$23) -> 0.057069963 | L20: 17 | M20: =INDEX($A$4:$A$23,MATCH(L20,$H$4:$H$23,0)) -> West-Alice | N20: =INDEX($D$4:$D$23,MATCH(L20,$H$4:$H$23,0)) -> 215690.54 | O20: =N20/SUM($D$4:$D$23) -> 0.042972533 | P20: =SUM($O$4:O20) -> 0.89691881 | Q20: =IF(P20<=0.8,"A",IF(P20<=0.95,"B","C")) -> B
A21: West-Charlie | B21: West | C21: Charlie | D21: =SUMIFS('Raw Data'!$E$2:$E$1001,'Raw Data'!$N$2:$N$1001,A21) -> 239708.85 | E21: =COUNTIFS('Raw Data'!$N$2:$N$1001,A21) -> 45 | F21: =IF(E21=0,0,D21/E21) -> 5326.8633 | G21: =IFERROR(SUMIFS('Raw Data'!$R$2:$R$1001,'Raw Data'!$N$2:$N$1001,A21)/SUMIFS('Raw Data'!$P$2:$P$1001,'Raw Data'!$N$2:$N$1001,A21),0) -> -0.077525449 | H21: =RANK(D21,$D$4:$D$23,0)+COUNTIF($D$4:D21,D21)-1 -> 12 | I21: =IF(D21>=PERCENTILE($D$4:$D$23,0.8),"High-Value",IF(D21>=PERCENTILE($D$4:$D$23,0.5),"Mid","Low")) -> Low | J21: =D21/SUM($D$4:$D$23) -> 0.047757757 | L21: 18 | M21: =INDEX($A$4:$A$23,MATCH(L21,$H$4:$H$23,0)) -> South-Eve | N21: =INDEX($D$4:$D$23,MATCH(L21,$H$4:$H$23,0)) -> 196078.22 | O21: =N21/SUM($D$4:$D$23) -> 0.039065124 | P21: =SUM($O$4:O21) -> 0.93598393 | Q21: =IF(P21<=0.8,"A",IF(P21<=0.95,"B","C")) -> B
A22: West-David | B22: West | C22: David | D22: =SUMIFS('Raw Data'!$E$2:$E$1001,'Raw Data'!$N$2:$N$1001,A22) -> 263167.59 | E22: =COUNTIFS('Raw Data'!$N$2:$N$1001,A22) -> 51 | F22: =IF(E22=0,0,D22/E22) -> 5160.1488 | G22: =IFERROR(SUMIFS('Raw Data'!$R$2:$R$1001,'Raw Data'!$N$2:$N$1001,A22)/SUMIFS('Raw Data'!$P$2:$P$1001,'Raw Data'!$N$2:$N$1001,A22),0) -> -0.10824644 | H22: =RANK(D22,$D$4:$D$23,0)+COUNTIF($D$4:D22,D22)-1 -> 8 | I22: =IF(D22>=PERCENTILE($D$4:$D$23,0.8),"High-Value",IF(D22>=PERCENTILE($D$4:$D$23,0.5),"Mid","Low")) -> Mid | J22: =D22/SUM($D$4:$D$23) -> 0.052431497 | L22: 19 | M22: =INDEX($A$4:$A$23,MATCH(L22,$H$4:$H$23,0)) -> East-Charlie | N22: =INDEX($D$4:$D$23,MATCH(L22,$H$4:$H$23,0)) -> 165172.94 | O22: =N22/SUM($D$4:$D$23) -> 0.032907793 | P22: =SUM($O$4:O22) -> 0.96889173 | Q22: =IF(P22<=0.8,"A",IF(P22<=0.95,"B","C")) -> C
A23: West-Eve | B23: West | C23: Eve | D23: =SUMIFS('Raw Data'!$E$2:$E$1001,'Raw Data'!$N$2:$N$1001,A23) -> 230592.67 | E23: =COUNTIFS('Raw Data'!$N$2:$N$1001,A23) -> 47 | F23: =IF(E23=0,0,D23/E23) -> 4906.227 | G23: =IFERROR(SUMIFS('Raw Data'!$R$2:$R$1001,'Raw Data'!$N$2:$N$1001,A23)/SUMIFS('Raw Data'!$P$2:$P$1001,'Raw Data'!$N$2:$N$1001,A23),0) -> -0.091434793 | H23: =RANK(D23,$D$4:$D$23,0)+COUNTIF($D$4:D23,D23)-1 -> 16 | I23: =IF(D23>=PERCENTILE($D$4:$D$23,0.8),"High-Value",IF(D23>=PERCENTILE($D$4:$D$23,0.5),"Mid","Low")) -> Low | J23: =D23/SUM($D$4:$D$23) -> 0.045941519 | L23: 20 | M23: =INDEX($A$4:$A$23,MATCH(L23,$H$4:$H$23,0)) -> South-Charlie | N23: =INDEX($D$4:$D$23,MATCH(L23,$H$4:$H$23,0)) -> 156140.68 | O23: =N23/SUM($D$4:$D$23) -> 0.031108274 | P23: =SUM($O$4:O23) -> 1 | Q23: =IF(P23<=0.8,"A",IF(P23<=0.95,"B","C")) -> C
L25: ABC: A = first 80% of sales, B = next 15%, C = last 5%.

Sheet Product IDs
A1: Product IDs: frequency, repeats, and the two-list comparison
A2: Finding: a Product_ID is not tied to one category, so category-level analysis is used elsewhere. List A = IDs sold as Electronics, List B = IDs sold as Furniture; Matches = IDs sold in both.
A3: Product_ID | B3: Transactions | C3: Sales | D3: Categories_Sold | E3: Electronics_Orders | F3: Furniture_Orders | G3: Elec_Seq | H3: Furn_Seq | J3: # | K3: List A: sold as Electronics | L3: List B: sold as Furniture | M3: Matches (in both) | O3: Summary
A4: 1001 | B4: =COUNTIF('Raw Data'!$A$2:$A$1001,A4) -> 16 | C4: =SUMIFS('Raw Data'!$E$2:$E$1001,'Raw Data'!$A$2:$A$1001,A4) -> 81017.34 | D4: =(COUNTIFS('Raw Data'!$A$2:$A$1001,A4,'Raw Data'!$G$2:$G$1001,"Clothing")>0)+(COUNTIFS('Raw Data'!$A$2:$A$1001,A4,'Raw Data'!$G$2:$G$1001,"Electronics")>0)+(COUNTIFS('Raw Data'!$A$2:$A$1001,A4,'Raw Data'!$G$2:$G$1001,"Food")>0)+(COUNTIFS('Raw Data'!$A$2:$A$1001,A4,'Raw Data'!$G$2:$G$1001,"Furniture")>0) -> 4 | E4: =COUNTIFS('Raw Data'!$A$2:$A$1001,A4,'Raw Data'!$G$2:$G$1001,"Electronics") -> 5 | F4: =COUNTIFS('Raw Data'!$A$2:$A$1001,A4,'Raw Data'!$G$2:$G$1001,"Furniture") -> 3 | G4: =IF(E4>0,MAX(G$3:G3)+1,"") -> 1 | H4: =IF(F4>0,MAX(H$3:H3)+1,"") -> 1 | J4: 1 | K4: =IFERROR(INDEX($A$4:$A$103,MATCH(J4,$G$4:$G$103,0)),"") -> 1001 | L4: =IFERROR(INDEX($A$4:$A$103,MATCH(J4,$H$4:$H$103,0)),"") -> 1001 | M4: =IF(K4="","",IF(COUNTIF($L$4:$L$103,K4)>0,K4,"")) -> 1001 | O4: Most frequently sold Product_ID (MODE) | P4: =MODE('Raw Data'!$A$2:$A$1001) -> 1090
A5: 1002 | B5: =COUNTIF('Raw Data'!$A$2:$A$1001,A5) -> 13 | C5: =SUMIFS('Raw Data'!$E$2:$E$1001,'Raw Data'!$A$2:$A$1001,A5) -> 71841.31 | D5: =(COUNTIFS('Raw Data'!$A$2:$A$1001,A5,'Raw Data'!$G$2:$G$1001,"Clothing")>0)+(COUNTIFS('Raw Data'!$A$2:$A$1001,A5,'Raw Data'!$G$2:$G$1001,"Electronics")>0)+(COUNTIFS('Raw Data'!$A$2:$A$1001,A5,'Raw Data'!$G$2:$G$1001,"Food")>0)+(COUNTIFS('Raw Data'!$A$2:$A$1001,A5,'Raw Data'!$G$2:$G$1001,"Furniture")>0) -> 4 | E5: =COUNTIFS('Raw Data'!$A$2:$A$1001,A5,'Raw Data'!$G$2:$G$1001,"Electronics") -> 1 | F5: =COUNTIFS('Raw Data'!$A$2:$A$1001,A5,'Raw Data'!$G$2:$G$1001,"Furniture") -> 5 | G5: =IF(E5>0,MAX(G$3:G4)+1,"") -> 2 | H5: =IF(F5>0,MAX(H$3:H4)+1,"") -> 2 | J5: 2 | K5: =IFERROR(INDEX($A$4:$A$103,MATCH(J5,$G$4:$G$103,0)),"") -> 1002 | L5: =IFERROR(INDEX($A$4:$A$103,MATCH(J5,$H$4:$H$103,0)),"") -> 1002 | M5: =IF(K5="","",IF(COUNTIF($L$4:$L$103,K5)>0,K5,"")) -> 1002 | O5: Its transaction count | P5: =MAX(B4:B103) -> 20
A6: 1003 | B6: =COUNTIF('Raw Data'!$A$2:$A$1001,A6) -> 12 | C6: =SUMIFS('Raw Data'!$E$2:$E$1001,'Raw Data'!$A$2:$A$1001,A6) -> 60463 | D6: =(COUNTIFS('Raw Data'!$A$2:$A$1001,A6,'Raw Data'!$G$2:$G$1001,"Clothing")>0)+(COUNTIFS('Raw Data'!$A$2:$A$1001,A6,'Raw Data'!$G$2:$G$1001,"Electronics")>0)+(COUNTIFS('Raw Data'!$A$2:$A$1001,A6,'Raw Data'!$G$2:$G$1001,"Food")>0)+(COUNTIFS('Raw Data'!$A$2:$A$1001,A6,'Raw Data'!$G$2:$G$1001,"Furniture")>0) -> 4 | E6: =COUNTIFS('Raw Data'!$A$2:$A$1001,A6,'Raw Data'!$G$2:$G$1001,"Electronics") -> 3 | F6: =COUNTIFS('Raw Data'!$A$2:$A$1001,A6,'Raw Data'!$G$2:$G$1001,"Furniture") -> 4 | G6: =IF(E6>0,MAX(G$3:G5)+1,"") -> 3 | H6: =IF(F6>0,MAX(H$3:H5)+1,"") -> 3 | J6: 3 | K6: =IFERROR(INDEX($A$4:$A$103,MATCH(J6,$G$4:$G$103,0)),"") -> 1003 | L6: =IFERROR(INDEX($A$4:$A$103,MATCH(J6,$H$4:$H$103,0)),"") -> 1003 | M6: =IF(K6="","",IF(COUNTIF($L$4:$L$103,K6)>0,K6,"")) -> 1003 | O6: IDs in List A | P6: =COUNT(K4:K103) -> 88
A7: 1004 | B7: =COUNTIF('Raw Data'!$A$2:$A$1001,A7) -> 11 | C7: =SUMIFS('Raw Data'!$E$2:$E$1001,'Raw Data'!$A$2:$A$1001,A7) -> 70744.61 | D7: =(COUNTIFS('Raw Data'!$A$2:$A$1001,A7,'Raw Data'!$G$2:$G$1001,"Clothing")>0)+(COUNTIFS('Raw Data'!$A$2:$A$1001,A7,'Raw Data'!$G$2:$G$1001,"Electronics")>0)+(COUNTIFS('Raw Data'!$A$2:$A$1001,A7,'Raw Data'!$G$2:$G$1001,"Food")>0)+(COUNTIFS('Raw Data'!$A$2:$A$1001,A7,'Raw Data'!$G$2:$G$1001,"Furniture")>0) -> 4 | E7: =COUNTIFS('Raw Data'!$A$2:$A$1001,A7,'Raw Data'!$G$2:$G$1001,"Electronics") -> 2 | F7: =COUNTIFS('Raw Data'!$A$2:$A$1001,A7,'Raw Data'!$G$2:$G$1001,"Furniture") -> 2 | G7: =IF(E7>0,MAX(G$3:G6)+1,"") -> 4 | H7: =IF(F7>0,MAX(H$3:H6)+1,"") -> 4 | J7: 4 | K7: =IFERROR(INDEX($A$4:$A$103,MATCH(J7,$G$4:$G$103,0)),"") -> 1004 | L7: =IFERROR(INDEX($A$4:$A$103,MATCH(J7,$H$4:$H$103,0)),"") -> 1004 | M7: =IF(K7="","",IF(COUNTIF($L$4:$L$103,K7)>0,K7,"")) -> 1004 | O7: IDs in List B | P7: =COUNT(L4:L103) -> 91
A8: 1005 | B8: =COUNTIF('Raw Data'!$A$2:$A$1001,A8) -> 11 | C8: =SUMIFS('Raw Data'!$E$2:$E$1001,'Raw Data'!$A$2:$A$1001,A8) -> 48113.7 | D8: =(COUNTIFS('Raw Data'!$A$2:$A$1001,A8,'Raw Data'!$G$2:$G$1001,"Clothing")>0)+(COUNTIFS('Raw Data'!$A$2:$A$1001,A8,'Raw Data'!$G$2:$G$1001,"Electronics")>0)+(COUNTIFS('Raw Data'!$A$2:$A$1001,A8,'Raw Data'!$G$2:$G$1001,"Food")>0)+(COUNTIFS('Raw Data'!$A$2:$A$1001,A8,'Raw Data'!$G$2:$G$1001,"Furniture")>0) -> 4 | E8: =COUNTIFS('Raw Data'!$A$2:$A$1001,A8,'Raw Data'!$G$2:$G$1001,"Electronics") -> 2 | F8: =COUNTIFS('Raw Data'!$A$2:$A$1001,A8,'Raw Data'!$G$2:$G$1001,"Furniture") -> 3 | G8: =IF(E8>0,MAX(G$3:G7)+1,"") -> 5 | H8: =IF(F8>0,MAX(H$3:H7)+1,"") -> 5 | J8: 5 | K8: =IFERROR(INDEX($A$4:$A$103,MATCH(J8,$G$4:$G$103,0)),"") -> 1005 | L8: =IFERROR(INDEX($A$4:$A$103,MATCH(J8,$H$4:$H$103,0)),"") -> 1005 | M8: =IF(K8="","",IF(COUNTIF($L$4:$L$103,K8)>0,K8,"")) -> 1005 | O8: IDs in both lists (matches) | P8: =COUNT(M4:M103) -> 80
A9: 1006 | B9: =COUNTIF('Raw Data'!$A$2:$A$1001,A9) -> 8 | C9: =SUMIFS('Raw Data'!$E$2:$E$1001,'Raw Data'!$A$2:$A$1001,A9) -> 37357.09 | D9: =(COUNTIFS('Raw Data'!$A$2:$A$1001,A9,'Raw Data'!$G$2:$G$1001,"Clothing")>0)+(COUNTIFS('Raw Data'!$A$2:$A$1001,A9,'Raw Data'!$G$2:$G$1001,"Electronics")>0)+(COUNTIFS('Raw Data'!$A$2:$A$1001,A9,'Raw Data'!$G$2:$G$1001,"Food")>0)+(COUNTIFS('Raw Data'!$A$2:$A$1001,A9,'Raw Data'!$G$2:$G$1001,"Furniture")>0) -> 4 | E9: =COUNTIFS('Raw Data'!$A$2:$A$1001,A9,'Raw Data'!$G$2:$G$1001,"Electronics") -> 2 | F9: =COUNTIFS('Raw Data'!$A$2:$A$1001,A9,'Raw Data'!$G$2:$G$1001,"Furniture") -> 1 | G9: =IF(E9>0,MAX(G$3:G8)+1,"") -> 6 | H9: =IF(F9>0,MAX(H$3:H8)+1,"") -> 6 | J9: 6 | K9: =IFERROR(INDEX($A$4:$A$103,MATCH(J9,$G$4:$G$103,0)),"") -> 1006 | L9: =IFERROR(INDEX($A$4:$A$103,MATCH(J9,$H$4:$H$103,0)),"") -> 1006 | M9: =IF(K9="","",IF(COUNTIF($L$4:$L$103,K9)>0,K9,"")) -> 1006 | O9: IDs sold in exactly 1 category | P9: =COUNTIF(D4:D103,1) -> 0
A10: 1007 | B10: =COUNTIF('Raw Data'!$A$2:$A$1001,A10) -> 8 | C10: =SUMIFS('Raw Data'!$E$2:$E$1001,'Raw Data'!$A$2:$A$1001,A10) -> 24419.76 | D10: =(COUNTIFS('Raw Data'!$A$2:$A$1001,A10,'Raw Data'!$G$2:$G$1001,"Clothing")>0)+(COUNTIFS('Raw Data'!$A$2:$A$1001,A10,'Raw Data'!$G$2:$G$1001,"Electronics")>0)+(COUNTIFS('Raw Data'!$A$2:$A$1001,A10,'Raw Data'!$G$2:$G$1001,"Food")>0)+(COUNTIFS('Raw Data'!$A$2:$A$1001,A10,'Raw Data'!$G$2:$G$1001,"Furniture")>0) -> 3 | E10: =COUNTIFS('Raw Data'!$A$2:$A$1001,A10,'Raw Data'!$G$2:$G$1001,"Electronics") -> 0 | F10: =COUNTIFS('Raw Data'!$A$2:$A$1001,A10,'Raw Data'!$G$2:$G$1001,"Furniture") -> 4 | G10: =IF(E10>0,MAX(G$3:G9)+1,"") | H10: =IF(F10>0,MAX(H$3:H9)+1,"") -> 7 | J10: 7 | K10: =IFERROR(INDEX($A$4:$A$103,MATCH(J10,$G$4:$G$103,0)),"") -> 1008 | L10: =IFERROR(INDEX($A$4:$A$103,MATCH(J10,$H$4:$H$103,0)),"") -> 1007 | M10: =IF(K10="","",IF(COUNTIF($L$4:$L$103,K10)>0,K10,"")) -> 1008 | O10: IDs sold in exactly 2 categories | P10: =COUNTIF(D4:D103,2) -> 6
A11: 1008 | B11: =COUNTIF('Raw Data'!$A$2:$A$1001,A11) -> 13 | C11: =SUMIFS('Raw Data'!$E$2:$E$1001,'Raw Data'!$A$2:$A$1001,A11) -> 66573.72 | D11: =(COUNTIFS('Raw Data'!$A$2:$A$1001,A11,'Raw Data'!$G$2:$G$1001,"Clothing")>0)+(COUNTIFS('Raw Data'!$A$2:$A$1001,A11,'Raw Data'!$G$2:$G$1001,"Electronics")>0)+(COUNTIFS('Raw Data'!$A$2:$A$1001,A11,'Raw Data'!$G$2:$G$1001,"Food")>0)+(COUNTIFS('Raw Data'!$A$2:$A$1001,A11,'Raw Data'!$G$2:$G$1001,"Furniture")>0) -> 4 | E11: =COUNTIFS('Raw Data'!$A$2:$A$1001,A11,'Raw Data'!$G$2:$G$1001,"Electronics") -> 4 | F11: =COUNTIFS('Raw Data'!$A$2:$A$1001,A11,'Raw Data'!$G$2:$G$1001,"Furniture") -> 2 | G11: =IF(E11>0,MAX(G$3:G10)+1,"") -> 7 | H11: =IF(F11>0,MAX(H$3:H10)+1,"") -> 8 | J11: 8 | K11: =IFERROR(INDEX($A$4:$A$103,MATCH(J11,$G$4:$G$103,0)),"") -> 1011 | L11: =IFERROR(INDEX($A$4:$A$103,MATCH(J11,$H$4:$H$103,0)),"") -> 1008 | M11: =IF(K11="","",IF(COUNTIF($L$4:$L$103,K11)>0,K11,"")) -> 1011 | O11: IDs sold in exactly 3 categories | P11: =COUNTIF(D4:D103,3) -> 23
A12: 1009 | B12: =COUNTIF('Raw Data'!$A$2:$A$1001,A12) -> 10 | C12: =SUMIFS('Raw Data'!$E$2:$E$1001,'Raw Data'!$A$2:$A$1001,A12) -> 43834.35 | D12: =(COUNTIFS('Raw Data'!$A$2:$A$1001,A12,'Raw Data'!$G$2:$G$1001,"Clothing")>0)+(COUNTIFS('Raw Data'!$A$2:$A$1001,A12,'Raw Data'!$G$2:$G$1001,"Electronics")>0)+(COUNTIFS('Raw Data'!$A$2:$A$1001,A12,'Raw Data'!$G$2:$G$1001,"Food")>0)+(COUNTIFS('Raw Data'!$A$2:$A$1001,A12,'Raw Data'!$G$2:$G$1001,"Furniture")>0) -> 3 | E12: =COUNTIFS('Raw Data'!$A$2:$A$1001,A12,'Raw Data'!$G$2:$G$1001,"Electronics") -> 0 | F12: =COUNTIFS('Raw Data'!$A$2:$A$1001,A12,'Raw Data'!$G$2:$G$1001,"Furniture") -> 2 | G12: =IF(E12>0,MAX(G$3:G11)+1,"") | H12: =IF(F12>0,MAX(H$3:H11)+1,"") -> 9 | J12: 9 | K12: =IFERROR(INDEX($A$4:$A$103,MATCH(J12,$G$4:$G$103,0)),"") -> 1012 | L12: =IFERROR(INDEX($A$4:$A$103,MATCH(J12,$H$4:$H$103,0)),"") -> 1009 | M12: =IF(K12="","",IF(COUNTIF($L$4:$L$103,K12)>0,K12,"")) -> 1012 | O12: IDs sold in all 4 categories | P12: =COUNTIF(D4:D103,4) -> 71
A13: 1010 | B13: =COUNTIF('Raw Data'!$A$2:$A$1001,A13) -> 6 | C13: =SUMIFS('Raw Data'!$E$2:$E$1001,'Raw Data'!$A$2:$A$1001,A13) -> 30228.93 | D13: =(COUNTIFS('Raw Data'!$A$2:$A$1001,A13,'Raw Data'!$G$2:$G$1001,"Clothing")>0)+(COUNTIFS('Raw Data'!$A$2:$A$1001,A13,'Raw Data'!$G$2:$G$1001,"Electronics")>0)+(COUNTIFS('Raw Data'!$A$2:$A$1001,A13,'Raw Data'!$G$2:$G$1001,"Food")>0)+(COUNTIFS('Raw Data'!$A$2:$A$1001,A13,'Raw Data'!$G$2:$G$1001,"Furniture")>0) -> 3 | E13: =COUNTIFS('Raw Data'!$A$2:$A$1001,A13,'Raw Data'!$G$2:$G$1001,"Electronics") -> 0 | F13: =COUNTIFS('Raw Data'!$A$2:$A$1001,A13,'Raw Data'!$G$2:$G$1001,"Furniture") -> 2 | G13: =IF(E13>0,MAX(G$3:G12)+1,"") | H13: =IF(F13>0,MAX(H$3:H12)+1,"") -> 10 | J13: 10 | K13: =IFERROR(INDEX($A$4:$A$103,MATCH(J13,$G$4:$G$103,0)),"") -> 1013 | L13: =IFERROR(INDEX($A$4:$A$103,MATCH(J13,$H$4:$H$103,0)),"") -> 1010 | M13: =IF(K13="","",IF(COUNTIF($L$4:$L$103,K13)>0,K13,"")) -> 1013 | O13: IDs sold more than once (repeating) | P13: =COUNTIF(B4:B103,">1") -> 100
A14: 1011 | B14: =COUNTIF('Raw Data'!$A$2:$A$1001,A14) -> 4 | C14: =SUMIFS('Raw Data'!$E$2:$E$1001,'Raw Data'!$A$2:$A$1001,A14) -> 19099.43 | D14: =(COUNTIFS('Raw Data'!$A$2:$A$1001,A14,'Raw Data'!$G$2:$G$1001,"Clothing")>0)+(COUNTIFS('Raw Data'!$A$2:$A$1001,A14,'Raw Data'!$G$2:$G$1001,"Electronics")>0)+(COUNTIFS('Raw Data'!$A$2:$A$1001,A14,'Raw Data'!$G$2:$G$1001,"Food")>0)+(COUNTIFS('Raw Data'!$A$2:$A$1001,A14,'Raw Data'!$G$2:$G$1001,"Furniture")>0) -> 2 | E14: =COUNTIFS('Raw Data'!$A$2:$A$1001,A14,'Raw Data'!$G$2:$G$1001,"Electronics") -> 2 | F14: =COUNTIFS('Raw Data'!$A$2:$A$1001,A14,'Raw Data'!$G$2:$G$1001,"Furniture") -> 2 | G14: =IF(E14>0,MAX(G$3:G13)+1,"") -> 8 | H14: =IF(F14>0,MAX(H$3:H13)+1,"") -> 11 | J14: 11 | K14: =IFERROR(INDEX($A$4:$A$103,MATCH(J14,$G$4:$G$103,0)),"") -> 1014 | L14: =IFERROR(INDEX($A$4:$A$103,MATCH(J14,$H$4:$H$103,0)),"") -> 1011 | M14: =IF(K14="","",IF(COUNTIF($L$4:$L$103,K14)>0,K14,"")) -> 1014
A15: 1012 | B15: =COUNTIF('Raw Data'!$A$2:$A$1001,A15) -> 13 | C15: =SUMIFS('Raw Data'!$E$2:$E$1001,'Raw Data'!$A$2:$A$1001,A15) -> 61964.99 | D15: =(COUNTIFS('Raw Data'!$A$2:$A$1001,A15,'Raw Data'!$G$2:$G$1001,"Clothing")>0)+(COUNTIFS('Raw Data'!$A$2:$A$1001,A15,'Raw Data'!$G$2:$G$1001,"Electronics")>0)+(COUNTIFS('Raw Data'!$A$2:$A$1001,A15,'Raw Data'!$G$2:$G$1001,"Food")>0)+(COUNTIFS('Raw Data'!$A$2:$A$1001,A15,'Raw Data'!$G$2:$G$1001,"Furniture")>0) -> 4 | E15: =COUNTIFS('Raw Data'!$A$2:$A$1001,A15,'Raw Data'!$G$2:$G$1001,"Electronics") -> 4 | F15: =COUNTIFS('Raw Data'!$A$2:$A$1001,A15,'Raw Data'!$G$2:$G$1001,"Furniture") -> 3 | G15: =IF(E15>0,MAX(G$3:G14)+1,"") -> 9 | H15: =IF(F15>0,MAX(H$3:H14)+1,"") -> 12 | J15: 12 | K15: =IFERROR(INDEX($A$4:$A$103,MATCH(J15,$G$4:$G$103,0)),"") -> 1015 | L15: =IFERROR(INDEX($A$4:$A$103,MATCH(J15,$H$4:$H$103,0)),"") -> 1012 | M15: =IF(K15="","",IF(COUNTIF($L$4:$L$103,K15)>0,K15,"")) -> 1015
A16: 1013 | B16: =COUNTIF('Raw Data'!$A$2:$A$1001,A16) -> 10 | C16: =SUMIFS('Raw Data'!$E$2:$E$1001,'Raw Data'!$A$2:$A$1001,A16) -> 58767.51 | D16: =(COUNTIFS('Raw Data'!$A$2:$A$1001,A16,'Raw Data'!$G$2:$G$1001,"Clothing")>0)+(COUNTIFS('Raw Data'!$A$2:$A$1001,A16,'Raw Data'!$G$2:$G$1001,"Electronics")>0)+(COUNTIFS('Raw Data'!$A$2:$A$1001,A16,'Raw Data'!$G$2:$G$1001,"Food")>0)+(COUNTIFS('Raw Data'!$A$2:$A$1001,A16,'Raw Data'!$G$2:$G$1001,"Furniture")>0) -> 4 | E16: =COUNTIFS('Raw Data'!$A$2:$A$1001,A16,'Raw Data'!$G$2:$G$1001,"Electronics") -> 3 | F16: =COUNTIFS('Raw Data'!$A$2:$A$1001,A16,'Raw Data'!$G$2:$G$1001,"Furniture") -> 3 | G16: =IF(E16>0,MAX(G$3:G15)+1,"") -> 10 | H16: =IF(F16>0,MAX(H$3:H15)+1,"") -> 13 | J16: 13 | K16: =IFERROR(INDEX($A$4:$A$103,MATCH(J16,$G$4:$G$103,0)),"") -> 1016 | L16: =IFERROR(INDEX($A$4:$A$103,MATCH(J16,$H$4:$H$103,0)),"") -> 1013 | M16: =IF(K16="","",IF(COUNTIF($L$4:$L$103,K16)>0,K16,"")) -> 1016
A17: 1014 | B17: =COUNTIF('Raw Data'!$A$2:$A$1001,A17) -> 10 | C17: =SUMIFS('Raw Data'!$E$2:$E$1001,'Raw Data'!$A$2:$A$1001,A17) -> 59633.15 | D17: =(COUNTIFS('Raw Data'!$A$2:$A$1001,A17,'Raw Data'!$G$2:$G$1001,"Clothing")>0)+(COUNTIFS('Raw Data'!$A$2:$A$1001,A17,'Raw Data'!$G$2:$G$1001,"Electronics")>0)+(COUNTIFS('Raw Data'!$A$2:$A$1001,A17,'Raw Data'!$G$2:$G$1001,"Food")>0)+(COUNTIFS('Raw Data'!$A$2:$A$1001,A17,'Raw Data'!$G$2:$G$1001,"Furniture")>0) -> 4 | E17: =COUNTIFS('Raw Data'!$A$2:$A$1001,A17,'Raw Data'!$G$2:$G$1001,"Electronics") -> 2 | F17: =COUNTIFS('Raw Data'!$A$2:$A$1001,A17,'Raw Data'!$G$2:$G$1001,"Furniture") -> 4 | G17: =IF(E17>0,MAX(G$3:G16)+1,"") -> 11 | H17: =IF(F17>0,MAX(H$3:H16)+1,"") -> 14 | J17: 14 | K17: =IFERROR(INDEX($A$4:$A$103,MATCH(J17,$G$4:$G$103,0)),"") -> 1017 | L17: =IFERROR(INDEX($A$4:$A$103,MATCH(J17,$H$4:$H$103,0)),"") -> 1014 | M17: =IF(K17="","",IF(COUNTIF($L$4:$L$103,K17)>0,K17,"")) -> 1017
A18: 1015 | B18: =COUNTIF('Raw Data'!$A$2:$A$1001,A18) -> 10 | C18: =SUMIFS('Raw Data'!$E$2:$E$1001,'Raw Data'!$A$2:$A$1001,A18) -> 42424.3 | D18: =(COUNTIFS('Raw Data'!$A$2:$A$1001,A18,'Raw Data'!$G$2:$G$1001,"Clothing")>0)+(COUNTIFS('Raw Data'!$A$2:$A$1001,A18,'Raw Data'!$G$2:$G$1001,"Electronics")>0)+(COUNTIFS('Raw Data'!$A$2:$A$1001,A18,'Raw Data'!$G$2:$G$1001,"Food")>0)+(COUNTIFS('Raw Data'!$A$2:$A$1001,A18,'Raw Data'!$G$2:$G$1001,"Furniture")>0) -> 4 | E18: =COUNTIFS('Raw Data'!$A$2:$A$1001,A18,'Raw Data'!$G$2:$G$1001,"Electronics") -> 3 | F18: =COUNTIFS('Raw Data'!$A$2:$A$1001,A18,'Raw Data'!$G$2:$G$1001,"Furniture") -> 2 | G18: =IF(E18>0,MAX(G$3:G17)+1,"") -> 12 | H18: =IF(F18>0,MAX(H$3:H17)+1,"") -> 15 | J18: 15 | K18: =IFERROR(INDEX($A$4:$A$103,MATCH(J18,$G$4:$G$103,0)),"") -> 1018 | L18: =IFERROR(INDEX($A$4:$A$103,MATCH(J18,$H$4:$H$103,0)),"") -> 1015 | M18: =IF(K18="","",IF(COUNTIF($L$4:$L$103,K18)>0,K18,"")) -> 1018
A19: 1016 | B19: =COUNTIF('Raw Data'!$A$2:$A$1001,A19) -> 13 | C19: =SUMIFS('Raw Data'!$E$2:$E$1001,'Raw Data'!$A$2:$A$1001,A19) -> 63956.44 | D19: =(COUNTIFS('Raw Data'!$A$2:$A$1001,A19,'Raw Data'!$G$2:$G$1001,"Clothing")>0)+(COUNTIFS('Raw Data'!$A$2:$A$1001,A19,'Raw Data'!$G$2:$G$1001,"Electronics")>0)+(COUNTIFS('Raw Data'!$A$2:$A$1001,A19,'Raw Data'!$G$2:$G$1001,"Food")>0)+(COUNTIFS('Raw Data'!$A$2:$A$1001,A19,'Raw Data'!$G$2:$G$1001,"Furniture")>0) -> 4 | E19: =COUNTIFS('Raw Data'!$A$2:$A$1001,A19,'Raw Data'!$G$2:$G$1001,"Electronics") -> 5 | F19: =COUNTIFS('Raw Data'!$A$2:$A$1001,A19,'Raw Data'!$G$2:$G$1001,"Furniture") -> 3 | G19: =IF(E19>0,MAX(G$3:G18)+1,"") -> 13 | H19: =IF(F19>0,MAX(H$3:H18)+1,"") -> 16 | J19: 16 | K19: =IFERROR(INDEX($A$4:$A$103,MATCH(J19,$G$4:$G$103,0)),"") -> 1019 | L19: =IFERROR(INDEX($A$4:$A$103,MATCH(J19,$H$4:$H$103,0)),"") -> 1016 | M19: =IF(K19="","",IF(COUNTIF($L$4:$L$103,K19)>0,K19,"")) -> 1019
A20: 1017 | B20: =COUNTIF('Raw Data'!$A$2:$A$1001,A20) -> 15 | C20: =SUMIFS('Raw Data'!$E$2:$E$1001,'Raw Data'!$A$2:$A$1001,A20) -> 55854.55 | D20: =(COUNTIFS('Raw Data'!$A$2:$A$1001,A20,'Raw Data'!$G$2:$G$1001,"Clothing")>0)+(COUNTIFS('Raw Data'!$A$2:$A$1001,A20,'Raw Data'!$G$2:$G$1001,"Electronics")>0)+(COUNTIFS('Raw Data'!$A$2:$A$1001,A20,'Raw Data'!$G$2:$G$1001,"Food")>0)+(COUNTIFS('Raw Data'!$A$2:$A$1001,A20,'Raw Data'!$G$2:$G$1001,"Furniture")>0) -> 4 | E20: =COUNTIFS('Raw Data'!$A$2:$A$1001,A20,'Raw Data'!$G$2:$G$1001,"Electronics") -> 4 | F20: =COUNTIFS('Raw Data'!$A$2:$A$1001,A20,'Raw Data'!$G$2:$G$1001,"Furniture") -> 6 | G20: =IF(E20>0,MAX(G$3:G19)+1,"") -> 14 | H20: =IF(F20>0,MAX(H$3:H19)+1,"") -> 17 | J20: 17 | K20: =IFERROR(INDEX($A$4:$A$103,MATCH(J20,$G$4:$G$103,0)),"") -> 1020 | L20: =IFERROR(INDEX($A$4:$A$103,MATCH(J20,$H$4:$H$103,0)),"") -> 1017 | M20: =IF(K20="","",IF(COUNTIF($L$4:$L$103,K20)>0,K20,"")) -> 1020
A21: 1018 | B21: =COUNTIF('Raw Data'!$A$2:$A$1001,A21) -> 9 | C21: =SUMIFS('Raw Data'!$E$2:$E$1001,'Raw Data'!$A$2:$A$1001,A21) -> 43906.17 | D21: =(COUNTIFS('Raw Data'!$A$2:$A$1001,A21,'Raw Data'!$G$2:$G$1001,"Clothing")>0)+(COUNTIFS('Raw Data'!$A$2:$A$1001,A21,'Raw Data'!$G$2:$G$1001,"Electronics")>0)+(COUNTIFS('Raw Data'!$A$2:$A$1001,A21,'Raw Data'!$G$2:$G$1001,"Food")>0)+(COUNTIFS('Raw Data'!$A$2:$A$1001,A21,'Raw Data'!$G$2:$G$1001,"Furniture")>0) -> 4 | E21: =COUNTIFS('Raw Data'!$A$2:$A$1001,A21,'Raw Data'!$G$2:$G$1001,"Electronics") -> 3 | F21: =COUNTIFS('Raw Data'!$A$2:$A$1001,A21,'Raw Data'!$G$2:$G$1001,"Furniture") -> 2 | G21: =IF(E21>0,MAX(G$3:G20)+1,"") -> 15 | H21: =IF(F21>0,MAX(H$3:H20)+1,"") -> 18 | J21: 18 | K21: =IFERROR(INDEX($A$4:$A$103,MATCH(J21,$G$4:$G$103,0)),"") -> 1021 | L21: =IFERROR(INDEX($A$4:$A$103,MATCH(J21,$H$4:$H$103,0)),"") -> 1018 | M21: =IF(K21="","",IF(COUNTIF($L$4:$L$103,K21)>0,K21,"")) -> 1021
A22: 1019 | B22: =COUNTIF('Raw Data'!$A$2:$A$1001,A22) -> 14 | C22: =SUMIFS('Raw Data'!$E$2:$E$1001,'Raw Data'!$A$2:$A$1001,A22) -> 69845.79 | D22: =(COUNTIFS('Raw Data'!$A$2:$A$1001,A22,'Raw Data'!$G$2:$G$1001,"Clothing")>0)+(COUNTIFS('Raw Data'!$A$2:$A$1001,A22,'Raw Data'!$G$2:$G$1001,"Electronics")>0)+(COUNTIFS('Raw Data'!$A$2:$A$1001,A22,'Raw Data'!$G$2:$G$1001,"Food")>0)+(COUNTIFS('Raw Data'!$A$2:$A$1001,A22,'Raw Data'!$G$2:$G$1001,"Furniture")>0) -> 4 | E22: =COUNTIFS('Raw Data'!$A$2:$A$1001,A22,'Raw Data'!$G$2:$G$1001,"Electronics") -> 2 | F22: =COUNTIFS('Raw Data'!$A$2:$A$1001,A22,'Raw Data'!$G$2:$G$1001,"Furniture") -> 2 | G22: =IF(E22>0,MAX(G$3:G21)+1,"") -> 16 | H22: =IF(F22>0,MAX(H$3:H21)+1,"") -> 19 | J22: 19 | K22: =IFERROR(INDEX($A$4:$A$103,MATCH(J22,$G$4:$G$103,0)),"") -> 1022 | L22: =IFERROR(INDEX($A$4:$A$103,MATCH(J22,$H$4:$H$103,0)),"") -> 1019 | M22: =IF(K22="","",IF(COUNTIF($L$4:$L$103,K22)>0,K22,"")) -> 1022
A23: 1020 | B23: =COUNTIF('Raw Data'!$A$2:$A$1001,A23) -> 7 | C23: =SUMIFS('Raw Data'!$E$2:$E$1001,'Raw Data'!$A$2:$A$1001,A23) -> 49603.16 | D23: =(COUNTIFS('Raw Data'!$A$2:$A$1001,A23,'Raw Data'!$G$2:$G$1001,"Clothing")>0)+(COUNTIFS('Raw Data'!$A$2:$A$1001,A23,'Raw Data'!$G$2:$G$1001,"Electronics")>0)+(COUNTIFS('Raw Data'!$A$2:$A$1001,A23,'Raw Data'!$G$2:$G$1001,"Food")>0)+(COUNTIFS('Raw Data'!$A$2:$A$1001,A23,'Raw Data'!$G$2:$G$1001,"Furniture")>0) -> 4 | E23: =COUNTIFS('Raw Data'!$A$2:$A$1001,A23,'Raw Data'!$G$2:$G$1001,"Electronics") -> 2 | F23: =COUNTIFS('Raw Data'!$A$2:$A$1001,A23,'Raw Data'!$G$2:$G$1001,"Furniture") -> 1 | G23: =IF(E23>0,MAX(G$3:G22)+1,"") -> 17 | H23: =IF(F23>0,MAX(H$3:H22)+1,"") -> 20 | J23: 20 | K23: =IFERROR(INDEX($A$4:$A$103,MATCH(J23,$G$4:$G$103,0)),"") -> 1023 | L23: =IFERROR(INDEX($A$4:$A$103,MATCH(J23,$H$4:$H$103,0)),"") -> 1020 | M23: =IF(K23="","",IF(COUNTIF($L$4:$L$103,K23)>0,K23,"")) -> 1023
A24: 1021 | B24: =COUNTIF('Raw Data'!$A$2:$A$1001,A24) -> 10 | C24: =SUMIFS('Raw Data'!$E$2:$E$1001,'Raw Data'!$A$2:$A$1001,A24) -> 46998.02 | D24: =(COUNTIFS('Raw Data'!$A$2:$A$1001,A24,'Raw Data'!$G$2:$G$1001,"Clothing")>0)+(COUNTIFS('Raw Data'!$A$2:$A$1001,A24,'Raw Data'!$G$2:$G$1001,"Electronics")>0)+(COUNTIFS('Raw Data'!$A$2:$A$1001,A24,'Raw Data'!$G$2:$G$1001,"Food")>0)+(COUNTIFS('Raw Data'!$A$2:$A$1001,A24,'Raw Data'!$G$2:$G$1001,"Furniture")>0) -> 4 | E24: =COUNTIFS('Raw Data'!$A$2:$A$1001,A24,'Raw Data'!$G$2:$G$1001,"Electronics") -> 3 | F24: =COUNTIFS('Raw Data'!$A$2:$A$1001,A24,'Raw Data'!$G$2:$G$1001,"Furniture") -> 3 | G24: =IF(E24>0,MAX(G$3:G23)+1,"") -> 18 | H24: =IF(F24>0,MAX(H$3:H23)+1,"") -> 21 | J24: 21 | K24: =IFERROR(INDEX($A$4:$A$103,MATCH(J24,$G$4:$G$103,0)),"") -> 1024 | L24: =IFERROR(INDEX($A$4:$A$103,MATCH(J24,$H$4:$H$103,0)),"") -> 1021 | M24: =IF(K24="","",IF(COUNTIF($L$4:$L$103,K24)>0,K24,"")) -> 1024
A25: 1022 | B25: =COUNTIF('Raw Data'!$A$2:$A$1001,A25) -> 6 | C25: =SUMIFS('Raw Data'!$E$2:$E$1001,'Raw Data'!$A$2:$A$1001,A25) -> 42592.23 | D25: =(COUNTIFS('Raw Data'!$A$2:$A$1001,A25,'Raw Data'!$G$2:$G$1001,"Clothing")>0)+(COUNTIFS('Raw Data'!$A$2:$A$1001,A25,'Raw Data'!$G$2:$G$1001,"Electronics")>0)+(COUNTIFS('Raw Data'!$A$2:$A$1001,A25,'Raw Data'!$G$2:$G$1001,"Food")>0)+(COUNTIFS('Raw Data'!$A$2:$A$1001,A25,'Raw Data'!$G$2:$G$1001,"Furniture")>0) -> 3 | E25: =COUNTIFS('Raw Data'!$A$2:$A$1001,A25,'Raw Data'!$G$2:$G$1001,"Electronics") -> 1 | F25: =COUNTIFS('Raw Data'!$A$2:$A$1001,A25,'Raw Data'!$G$2:$G$1001,"Furniture") -> 3 | G25: =IF(E25>0,MAX(G$3:G24)+1,"") -> 19 | H25: =IF(F25>0,MAX(H$3:H24)+1,"") -> 22 | J25: 22 | K25: =IFERROR(INDEX($A$4:$A$103,MATCH(J25,$G$4:$G$103,0)),"") -> 1025 | L25: =IFERROR(INDEX($A$4:$A$103,MATCH(J25,$H$4:$H$103,0)),"") -> 1022 | M25: =IF(K25="","",IF(COUNTIF($L$4:$L$103,K25)>0,K25,"")) -> 1025
... A103: 1100 | B103: =COUNTIF('Raw Data'!$A$2:$A$1001,A103) -> 9 | C103: =SUMIFS('Raw Data'!$E$2:$E$1001,'Raw Data'!$A$2:$A$1001,A103) -> 27882.49 | D103: =(COUNTIFS('Raw Data'!$A$2:$A$1001,A103,'Raw Data'!$G$2:$G$1001,"Clothing")>0)+(COUNTIFS('Raw Data'!$A$2:$A$1001,A103,'Raw Data'!$G$2:$G$1001,"Electronics")>0)+(COUNTIFS('Raw Data'!$A$2:$A$1001,A103,'Raw Data'!$G$2:$G$1001,"Food")>0)+(COUNTIFS('Raw Data'!$A$2:$A$1001,A103,'Raw Data'!$G$2:$G$1001,"Furniture")>0) -> 3 | E103: =COUNTIFS('Raw Data'!$A$2:$A$1001,A103,'Raw Data'!$G$2:$G$1001,"Electronics") -> 3 | F103: =COUNTIFS('Raw Data'!$A$2:$A$1001,A103,'Raw Data'!$G$2:$G$1001,"Furniture") -> 3 | G103: =IF(E103>0,MAX(G$3:G102)+1,"") -> 88 | H103: =IF(F103>0,MAX(H$3:H102)+1,"") -> 91 | J103: 100 | K103: =IFERROR(INDEX($A$4:$A$103,MATCH(J103,$G$4:$G$103,0)),"") | L103: =IFERROR(INDEX($A$4:$A$103,MATCH(J103,$H$4:$H$103,0)),"") | M103: =IF(K103="","",IF(COUNTIF($L$4:$L$103,K103)>0,K103,""))

Sheet Filter
A1: FILTER demo: multi-value return
A2: Change the yellow inputs. The table returns every matching sale (up to 30). Works in all Excel versions through a helper column (Raw Data > Filter_Seq).
A4: Region | B4: All
A5: Sales channel | B5: All
A6: Min Sales_Amount ($) | B6: 9000
A7: Matching rows | B7: =COUNT('Raw Data'!$AH$2:$AH$1001) -> 90
A9: Excel 365 one-cell equivalent (paste into any empty cell):
A10: FILTER formula: =FILTER(tblSales,(tblSales[Region]=B4)*(tblSales[Sales_Amount]>=B6),"No matching records") (set B4 to a region name)
A11: # | B11: Order_Code | C11: Date | D11: Sales Rep | E11: Region | F11: Category | G11: Channel | H11: Qty | I11: Sales_Amount
A12: 1 | B12: =IFERROR(INDEX('Raw Data'!$AG$2:$AG$1001,MATCH($A12,'Raw Data'!$AH$2:$AH$1001,0)),"") -> WR-230713-0048 | C12: =IFERROR(INDEX('Raw Data'!$B$2:$B$1001,MATCH($A12,'Raw Data'!$AH$2:$AH$1001,0)),"") -> 45120 | D12: =IFERROR(INDEX('Raw Data'!$C$2:$C$1001,MATCH($A12,'Raw Data'!$AH$2:$AH$1001,0)),"") -> Bob | E12: =IFERROR(INDEX('Raw Data'!$D$2:$D$1001,MATCH($A12,'Raw Data'!$AH$2:$AH$1001,0)),"") -> West | F12: =IFERROR(INDEX('Raw Data'!$G$2:$G$1001,MATCH($A12,'Raw Data'!$AH$2:$AH$1001,0)),"") -> Furniture | G12: =IFERROR(INDEX('Raw Data'!$M$2:$M$1001,MATCH($A12,'Raw Data'!$AH$2:$AH$1001,0)),"") -> Retail | H12: =IFERROR(INDEX('Raw Data'!$F$2:$F$1001,MATCH($A12,'Raw Data'!$AH$2:$AH$1001,0)),"") -> 43 | I12: =IFERROR(INDEX('Raw Data'!$E$2:$E$1001,MATCH($A12,'Raw Data'!$AH$2:$AH$1001,0)),"") -> 9638.64
A13: 2 | B13: =IFERROR(INDEX('Raw Data'!$AG$2:$AG$1001,MATCH($A13,'Raw Data'!$AH$2:$AH$1001,0)),"") -> WO-231122-0055 | C13: =IFERROR(INDEX('Raw Data'!$B$2:$B$1001,MATCH($A13,'Raw Data'!$AH$2:$AH$1001,0)),"") -> 45252 | D13: =IFERROR(INDEX('Raw Data'!$C$2:$C$1001,MATCH($A13,'Raw Data'!$AH$2:$AH$1001,0)),"") -> David | E13: =IFERROR(INDEX('Raw Data'!$D$2:$D$1001,MATCH($A13,'Raw Data'!$AH$2:$AH$1001,0)),"") -> West | F13: =IFERROR(INDEX('Raw Data'!$G$2:$G$1001,MATCH($A13,'Raw Data'!$AH$2:$AH$1001,0)),"") -> Food | G13: =IFERROR(INDEX('Raw Data'!$M$2:$M$1001,MATCH($A13,'Raw Data'!$AH$2:$AH$1001,0)),"") -> Online | H13: =IFERROR(INDEX('Raw Data'!$F$2:$F$1001,MATCH($A13,'Raw Data'!$AH$2:$AH$1001,0)),"") -> 17 | I13: =IFERROR(INDEX('Raw Data'!$E$2:$E$1001,MATCH($A13,'Raw Data'!$AH$2:$AH$1001,0)),"") -> 9762.54
A14: 3 | B14: =IFERROR(INDEX('Raw Data'!$AG$2:$AG$1001,MATCH($A14,'Raw Data'!$AH$2:$AH$1001,0)),"") -> ER-230519-0071 | C14: =IFERROR(INDEX('Raw Data'!$B$2:$B$1001,MATCH($A14,'Raw Data'!$AH$2:$AH$1001,0)),"") -> 45065 | D14: =IFERROR(INDEX('Raw Data'!$C$2:$C$1001,MATCH($A14,'Raw Data'!$AH$2:$AH$1001,0)),"") -> Charlie | E14: =IFERROR(INDEX('Raw Data'!$D$2:$D$1001,MATCH($A14,'Raw Data'!$AH$2:$AH$1001,0)),"") -> East | F14: =IFERROR(INDEX('Raw Data'!$G$2:$G$1001,MATCH($A14,'Raw Data'!$AH$2:$AH$1001,0)),"") -> Clothing | G14: =IFERROR(INDEX('Raw Data'!$M$2:$M$1001,MATCH($A14,'Raw Data'!$AH$2:$AH$1001,0)),"") -> Retail | H14: =IFERROR(INDEX('Raw Data'!$F$2:$F$1001,MATCH($A14,'Raw Data'!$AH$2:$AH$1001,0)),"") -> 35 | I14: =IFERROR(INDEX('Raw Data'!$E$2:$E$1001,MATCH($A14,'Raw Data'!$AH$2:$AH$1001,0)),"") -> 9744.52
A15: 4 | B15: =IFERROR(INDEX('Raw Data'!$AG$2:$AG$1001,MATCH($A15,'Raw Data'!$AH$2:$AH$1001,0)),"") -> SO-230411-0087 | C15: =IFERROR(INDEX('Raw Data'!$B$2:$B$1001,MATCH($A15,'Raw Data'!$AH$2:$AH$1001,0)),"") -> 45027 | D15: =IFERROR(INDEX('Raw Data'!$C$2:$C$1001,MATCH($A15,'Raw Data'!$AH$2:$AH$1001,0)),"") -> Alice | E15: =IFERROR(INDEX('Raw Data'!$D$2:$D$1001,MATCH($A15,'Raw Data'!$AH$2:$AH$1001,0)),"") -> South | F15: =IFERROR(INDEX('Raw Data'!$G$2:$G$1001,MATCH($A15,'Raw Data'!$AH$2:$AH$1001,0)),"") -> Food | G15: =IFERROR(INDEX('Raw Data'!$M$2:$M$1001,MATCH($A15,'Raw Data'!$AH$2:$AH$1001,0)),"") -> Online | H15: =IFERROR(INDEX('Raw Data'!$F$2:$F$1001,MATCH($A15,'Raw Data'!$AH$2:$AH$1001,0)),"") -> 38 | I15: =IFERROR(INDEX('Raw Data'!$E$2:$E$1001,MATCH($A15,'Raw Data'!$AH$2:$AH$1001,0)),"") -> 9582.12
A16: 5 | B16: =IFERROR(INDEX('Raw Data'!$AG$2:$AG$1001,MATCH($A16,'Raw Data'!$AH$2:$AH$1001,0)),"") -> ER-231125-0088 | C16: =IFERROR(INDEX('Raw Data'!$B$2:$B$1001,MATCH($A16,'Raw Data'!$AH$2:$AH$1001,0)),"") -> 45255 | D16: =IFERROR(INDEX('Raw Data'!$C$2:$C$1001,MATCH($A16,'Raw Data'!$AH$2:$AH$1001,0)),"") -> Alice | E16: =IFERROR(INDEX('Raw Data'!$D$2:$D$1001,MATCH($A16,'Raw Data'!$AH$2:$AH$1001,0)),"") -> East | F16: =IFERROR(INDEX('Raw Data'!$G$2:$G$1001,MATCH($A16,'Raw Data'!$AH$2:$AH$1001,0)),"") -> Electronics | G16: =IFERROR(INDEX('Raw Data'!$M$2:$M$1001,MATCH($A16,'Raw Data'!$AH$2:$AH$1001,0)),"") -> Retail | H16: =IFERROR(INDEX('Raw Data'!$F$2:$F$1001,MATCH($A16,'Raw Data'!$AH$2:$AH$1001,0)),"") -> 37 | I16: =IFERROR(INDEX('Raw Data'!$E$2:$E$1001,MATCH($A16,'Raw Data'!$AH$2:$AH$1001,0)),"") -> 9432.97
A17: 6 | B17: =IFERROR(INDEX('Raw Data'!$AG$2:$AG$1001,MATCH($A17,'Raw Data'!$AH$2:$AH$1001,0)),"") -> SR-230922-0090 | C17: =IFERROR(INDEX('Raw Data'!$B$2:$B$1001,MATCH($A17,'Raw Data'!$AH$2:$AH$1001,0)),"") -> 45191 | D17: =IFERROR(INDEX('Raw Data'!$C$2:$C$1001,MATCH($A17,'Raw Data'!$AH$2:$AH$1001,0)),"") -> David | E17: =IFERROR(INDEX('Raw Data'!$D$2:$D$1001,MATCH($A17,'Raw Data'!$AH$2:$AH$1001,0)),"") -> South | F17: =IFERROR(INDEX('Raw Data'!$G$2:$G$1001,MATCH($A17,'Raw Data'!$AH$2:$AH$1001,0)),"") -> Electronics | G17: =IFERROR(INDEX('Raw Data'!$M$2:$M$1001,MATCH($A17,'Raw Data'!$AH$2:$AH$1001,0)),"") -> Retail | H17: =IFERROR(INDEX('Raw Data'!$F$2:$F$1001,MATCH($A17,'Raw Data'!$AH$2:$AH$1001,0)),"") -> 22 | I17: =IFERROR(INDEX('Raw Data'!$E$2:$E$1001,MATCH($A17,'Raw Data'!$AH$2:$AH$1001,0)),"") -> 9914.15
A18: 7 | B18: =IFERROR(INDEX('Raw Data'!$AG$2:$AG$1001,MATCH($A18,'Raw Data'!$AH$2:$AH$1001,0)),"") -> ER-230404-0092 | C18: =IFERROR(INDEX('Raw Data'!$B$2:$B$1001,MATCH($A18,'Raw Data'!$AH$2:$AH$1001,0)),"") -> 45020 | D18: =IFERROR(INDEX('Raw Data'!$C$2:$C$1001,MATCH($A18,'Raw Data'!$AH$2:$AH$1001,0)),"") -> David | E18: =IFERROR(INDEX('Raw Data'!$D$2:$D$1001,MATCH($A18,'Raw Data'!$AH$2:$AH$1001,0)),"") -> East | F18: =IFERROR(INDEX('Raw Data'!$G$2:$G$1001,MATCH($A18,'Raw Data'!$AH$2:$AH$1001,0)),"") -> Furniture | G18: =IFERROR(INDEX('Raw Data'!$M$2:$M$1001,MATCH($A18,'Raw Data'!$AH$2:$AH$1001,0)),"") -> Retail | H18: =IFERROR(INDEX('Raw Data'!$F$2:$F$1001,MATCH($A18,'Raw Data'!$AH$2:$AH$1001,0)),"") -> 49 | I18: =IFERROR(INDEX('Raw Data'!$E$2:$E$1001,MATCH($A18,'Raw Data'!$AH$2:$AH$1001,0)),"") -> 9631.41
A19: 8 | B19: =IFERROR(INDEX('Raw Data'!$AG$2:$AG$1001,MATCH($A19,'Raw Data'!$AH$2:$AH$1001,0)),"") -> ER-231124-0108 | C19: =IFERROR(INDEX('Raw Data'!$B$2:$B$1001,MATCH($A19,'Raw Data'!$AH$2:$AH$1001,0)),"") -> 45254 | D19: =IFERROR(INDEX('Raw Data'!$C$2:$C$1001,MATCH($A19,'Raw Data'!$AH$2:$AH$1001,0)),"") -> Bob | E19: =IFERROR(INDEX('Raw Data'!$D$2:$D$1001,MATCH($A19,'Raw Data'!$AH$2:$AH$1001,0)),"") -> East | F19: =IFERROR(INDEX('Raw Data'!$G$2:$G$1001,MATCH($A19,'Raw Data'!$AH$2:$AH$1001,0)),"") -> Food | G19: =IFERROR(INDEX('Raw Data'!$M$2:$M$1001,MATCH($A19,'Raw Data'!$AH$2:$AH$1001,0)),"") -> Retail | H19: =IFERROR(INDEX('Raw Data'!$F$2:$F$1001,MATCH($A19,'Raw Data'!$AH$2:$AH$1001,0)),"") -> 18 | I19: =IFERROR(INDEX('Raw Data'!$E$2:$E$1001,MATCH($A19,'Raw Data'!$AH$2:$AH$1001,0)),"") -> 9183.11
A20: 9 | B20: =IFERROR(INDEX('Raw Data'!$AG$2:$AG$1001,MATCH($A20,'Raw Data'!$AH$2:$AH$1001,0)),"") -> ER-231205-0119 | C20: =IFERROR(INDEX('Raw Data'!$B$2:$B$1001,MATCH($A20,'Raw Data'!$AH$2:$AH$1001,0)),"") -> 45265 | D20: =IFERROR(INDEX('Raw Data'!$C$2:$C$1001,MATCH($A20,'Raw Data'!$AH$2:$AH$1001,0)),"") -> Charlie | E20: =IFERROR(INDEX('Raw Data'!$D$2:$D$1001,MATCH($A20,'Raw Data'!$AH$2:$AH$1001,0)),"") -> East | F20: =IFERROR(INDEX('Raw Data'!$G$2:$G$1001,MATCH($A20,'Raw Data'!$AH$2:$AH$1001,0)),"") -> Electronics | G20: =IFERROR(INDEX('Raw Data'!$M$2:$M$1001,MATCH($A20,'Raw Data'!$AH$2:$AH$1001,0)),"") -> Retail | H20: =IFERROR(INDEX('Raw Data'!$F$2:$F$1001,MATCH($A20,'Raw Data'!$AH$2:$AH$1001,0)),"") -> 27 | I20: =IFERROR(INDEX('Raw Data'!$E$2:$E$1001,MATCH($A20,'Raw Data'!$AH$2:$AH$1001,0)),"") -> 9583.55
A21: 10 | B21: =IFERROR(INDEX('Raw Data'!$AG$2:$AG$1001,MATCH($A21,'Raw Data'!$AH$2:$AH$1001,0)),"") -> NO-230123-0136 | C21: =IFERROR(INDEX('Raw Data'!$B$2:$B$1001,MATCH($A21,'Raw Data'!$AH$2:$AH$1001,0)),"") -> 44949 | D21: =IFERROR(INDEX('Raw Data'!$C$2:$C$1001,MATCH($A21,'Raw Data'!$AH$2:$AH$1001,0)),"") -> Bob | E21: =IFERROR(INDEX('Raw Data'!$D$2:$D$1001,MATCH($A21,'Raw Data'!$AH$2:$AH$1001,0)),"") -> North | F21: =IFERROR(INDEX('Raw Data'!$G$2:$G$1001,MATCH($A21,'Raw Data'!$AH$2:$AH$1001,0)),"") -> Clothing | G21: =IFERROR(INDEX('Raw Data'!$M$2:$M$1001,MATCH($A21,'Raw Data'!$AH$2:$AH$1001,0)),"") -> Online | H21: =IFERROR(INDEX('Raw Data'!$F$2:$F$1001,MATCH($A21,'Raw Data'!$AH$2:$AH$1001,0)),"") -> 40 | I21: =IFERROR(INDEX('Raw Data'!$E$2:$E$1001,MATCH($A21,'Raw Data'!$AH$2:$AH$1001,0)),"") -> 9813.81
A22: 11 | B22: =IFERROR(INDEX('Raw Data'!$AG$2:$AG$1001,MATCH($A22,'Raw Data'!$AH$2:$AH$1001,0)),"") -> NR-230525-0140 | C22: =IFERROR(INDEX('Raw Data'!$B$2:$B$1001,MATCH($A22,'Raw Data'!$AH$2:$AH$1001,0)),"") -> 45071 | D22: =IFERROR(INDEX('Raw Data'!$C$2:$C$1001,MATCH($A22,'Raw Data'!$AH$2:$AH$1001,0)),"") -> Alice | E22: =IFERROR(INDEX('Raw Data'!$D$2:$D$1001,MATCH($A22,'Raw Data'!$AH$2:$AH$1001,0)),"") -> North | F22: =IFERROR(INDEX('Raw Data'!$G$2:$G$1001,MATCH($A22,'Raw Data'!$AH$2:$AH$1001,0)),"") -> Clothing | G22: =IFERROR(INDEX('Raw Data'!$M$2:$M$1001,MATCH($A22,'Raw Data'!$AH$2:$AH$1001,0)),"") -> Retail | H22: =IFERROR(INDEX('Raw Data'!$F$2:$F$1001,MATCH($A22,'Raw Data'!$AH$2:$AH$1001,0)),"") -> 24 | I22: =IFERROR(INDEX('Raw Data'!$E$2:$E$1001,MATCH($A22,'Raw Data'!$AH$2:$AH$1001,0)),"") -> 9610.21
A23: 12 | B23: =IFERROR(INDEX('Raw Data'!$AG$2:$AG$1001,MATCH($A23,'Raw Data'!$AH$2:$AH$1001,0)),"") -> ER-231105-0142 | C23: =IFERROR(INDEX('Raw Data'!$B$2:$B$1001,MATCH($A23,'Raw Data'!$AH$2:$AH$1001,0)),"") -> 45235 | D23: =IFERROR(INDEX('Raw Data'!$C$2:$C$1001,MATCH($A23,'Raw Data'!$AH$2:$AH$1001,0)),"") -> Alice | E23: =IFERROR(INDEX('Raw Data'!$D$2:$D$1001,MATCH($A23,'Raw Data'!$AH$2:$AH$1001,0)),"") -> East | F23: =IFERROR(INDEX('Raw Data'!$G$2:$G$1001,MATCH($A23,'Raw Data'!$AH$2:$AH$1001,0)),"") -> Furniture | G23: =IFERROR(INDEX('Raw Data'!$M$2:$M$1001,MATCH($A23,'Raw Data'!$AH$2:$AH$1001,0)),"") -> Retail | H23: =IFERROR(INDEX('Raw Data'!$F$2:$F$1001,MATCH($A23,'Raw Data'!$AH$2:$AH$1001,0)),"") -> 3 | I23: =IFERROR(INDEX('Raw Data'!$E$2:$E$1001,MATCH($A23,'Raw Data'!$AH$2:$AH$1001,0)),"") -> 9519.16
... A41: 30 | B41: =IFERROR(INDEX('Raw Data'!$AG$2:$AG$1001,MATCH($A41,'Raw Data'!$AH$2:$AH$1001,0)),"") -> NO-231210-0267 | C41: =IFERROR(INDEX('Raw Data'!$B$2:$B$1001,MATCH($A41,'Raw Data'!$AH$2:$AH$1001,0)),"") -> 45270 | D41: =IFERROR(INDEX('Raw Data'!$C$2:$C$1001,MATCH($A41,'Raw Data'!$AH$2:$AH$1001,0)),"") -> Bob | E41: =IFERROR(INDEX('Raw Data'!$D$2:$D$1001,MATCH($A41,'Raw Data'!$AH$2:$AH$1001,0)),"") -> North | F41: =IFERROR(INDEX('Raw Data'!$G$2:$G$1001,MATCH($A41,'Raw Data'!$AH$2:$AH$1001,0)),"") -> Electronics | G41: =IFERROR(INDEX('Raw Data'!$M$2:$M$1001,MATCH($A41,'Raw Data'!$AH$2:$AH$1001,0)),"") -> Online | H41: =IFERROR(INDEX('Raw Data'!$F$2:$F$1001,MATCH($A41,'Raw Data'!$AH$2:$AH$1001,0)),"") -> 45 | I41: =IFERROR(INDEX('Raw Data'!$E$2:$E$1001,MATCH($A41,'Raw Data'!$AH$2:$AH$1001,0)),"") -> 9671.77

Sheet Pivots
A1: Pivot Tables
A2: Nine live PivotTables built on the Raw Data table. The four slicers on the Dashboard (Region, Product Category, Sales Channel, Sales Rep) filter these pivots as well; the report filters (▼) above each table also work. Right-click > Refresh after editing data.
A3: Slicers are already connected. To add a Timeline: click a pivot > PivotTable Analyze > Insert Timeline (Sale_Date) > Report Connections > tick all pivots.
A4: Sales by Region | E4: Sales by Month | I4: Sales by Category | M4: Sales by Rep | Q4: Transactions by Payment | U4: Quarter x Category | AB4: Region x Sales Rep | AJ4: Avg Sale by Discount Band | AN4: Channel x Customer Type
A6: Filter | E6: Filter | I6: Filter | M6: Filter | Q6: Filter | U6: Filter | AB6: Filter | AJ6: Filter | AN6: Filter
A7: Product_Category | B7: - all - | E7: Region | F7: - all - | I7: Region | J7: - all - | M7: Region | N7: - all - | Q7: Region | R7: - all - | U7: Region | V7: - all - | AB7: Product_Category | AC7: - all - | AJ7: Region | AK7: - all - | AN7: Region | AO7: - all -
A8: Sales_Channel | B8: - all - | E8: Product_Category | F8: - all - | I8: Sales_Channel | J8: - all - | M8: Product_Category | N8: - all - | Q8: Product_Category | R8: - all - | AJ8: Product_Category | AK8: - all -
U9: Sales ($) | V9: Product_Category | AB9: Sales ($) | AC9: Sales_Rep | AN9: Sales ($) | AO9: Customer_Type
A10: Region | B10: Sales ($) | E10: Year_Month | F10: Sales ($) | I10: Product_Category | J10: Sales ($) | M10: Sales_Rep | N10: Sales ($) | Q10: Payment_Method | R10: Transactions | U10: Year_Quarter | V10: Clothing | W10: Electronics | X10: Food | Y10: Furniture | Z10: Grand Total | AB10: Region | AC10: Alice | AD10: Bob | AE10: Charlie | AF10: David | AG10: Eve | AH10: Grand Total | AJ10: Discount_Band | AK10: Avg Sale ($) | AN10: Sales_Channel | AO10: New | AP10: Returning | AQ10: Grand Total
A11: East | B11: 1259792.9 | E11: 2023-01 | F11: 476092.36 | I11: Clothing | J11: 1313474.4 | M11: Alice | N11: 965541.77 | Q11: Bank Transfer | R11: 342 | U11: 2023-Q1 | V11: 350256.74 | W11: 284310.07 | X11: 265563.35 | Y11: 347520.33 | Z11: 1247650.5 | AB11: East | AC11: 260789.47 | AD11: 309876.11 | AE11: 165172.94 | AF11: 284613.51 | AG11: 239340.9 | AH11: 1259792.9 | AJ11: 0-9% | AK11: 4982.8263 | AN11: Online | AO11: 1282624 | AP11: 1176209.9 | AQ11: 2458833.9
A12: North | B12: 1369612.5 | E12: 2023-02 | F12: 368919.36 | I12: Electronics | J12: 1243499.6 | M12: Bob | N12: 1080990.6 | Q12: Cash | R12: 313 | U12: 2023-Q2 | V12: 287512.72 | W12: 322811.44 | X12: 281996.18 | Y12: 354209.37 | Z12: 1246529.7 | AB12: North | AC12: 249647.22 | AD12: 233464.81 | AE12: 299789.01 | AF12: 282539.27 | AG12: 304172.2 | AH12: 1369612.5 | AJ12: 10-19% | AK12: 4798.0266 | AN12: Retail | AO12: 1223634.3 | AP12: 1336797 | AQ12: 2560431.3
A13: South | B13: 1154250.9 | E13: 2023-03 | F13: 402638.77 | I13: Food | J13: 1201773.5 | M13: Charlie | N13: 860811.48 | Q13: Credit Card | R13: 345 | U13: 2023-Q3 | V13: 324530.56 | W13: 309438.08 | X13: 290914.51 | Y13: 260368.61 | Z13: 1185251.8 | AB13: South | AC13: 239414.54 | AD13: 251200.43 | AE13: 156140.68 | AF13: 311416.99 | AG13: 196078.22 | AH13: 1154250.9 | AJ13: 20%+ | AK13: 5228.0169 | AN13: Grand Total | AO13: 2506258.3 | AP13: 2513006.9 | AQ13: 5019265.2
A14: West | B14: 1235608.9 | E14: 2023-04 | F14: 438992.61 | I14: Furniture | J14: 1260517.7 | M14: David | N14: 1141737.4 | Q14: Grand Total | R14: 1000 | U14: 2023-Q4 | V14: 348803.62 | W14: 318360.33 | X14: 354921.93 | Y14: 298419.38 | Z14: 1320505.3 | AB14: West | AC14: 215690.54 | AD14: 286449.28 | AE14: 239708.85 | AF14: 263167.59 | AG14: 230592.67 | AH14: 1235608.9 | AJ14: Grand Total | AK14: 5019.2652
A15: Grand Total | B15: 5019265.2 | E15: 2023-05 | F15: 389078.76 | I15: Grand Total | J15: 5019265.2 | M15: Eve | N15: 970183.99 | U15: 2024-Q1 | V15: 2370.72 | W15: 8579.72 | X15: 8377.57 | Z15: 19328.01 | AB15: Grand Total | AC15: 965541.77 | AD15: 1080990.6 | AE15: 860811.48 | AF15: 1141737.4 | AG15: 970183.99 | AH15: 5019265.2
E16: 2023-06 | F16: 418458.34 | M16: Grand Total | N16: 5019265.2 | U16: Grand Total | V16: 1313474.4 | W16: 1243499.6 | X16: 1201773.5 | Y16: 1260517.7 | Z16: 5019265.2
E17: 2023-07 | F17: 374242.88
E18: 2023-08 | F18: 443171.28
E19: 2023-09 | F19: 367837.6
E20: 2023-10 | F20: 460378.78
E21: 2023-11 | F21: 467482.9
E22: 2023-12 | F22: 392643.58
E23: 2024-01 | F23: 19328.01
E24: Grand Total | F24: 5019265.2

Sheet Regression Output
A1: Regression Analysis (Analysis ToolPak layout, live formulas)
A2: Each block reproduces Data > Data Analysis > Regression: Regression Statistics, ANOVA, Coefficients. Cells are formulas (LINEST, FDIST, TDIST) so they update with the data.
A4: REGRESSION A: Monthly Sales Trend (Y = monthly sales, X = month index, 12 full months)
A5: Regression Statistics
A6: Multiple R | B6: =SQRT(B7) -> 0.043197528
A7: R Square | B7: =INDEX(LINEST(Analysis!$E$167:$E$178,Analysis!$C$167:$C$178,TRUE(),TRUE()),3,1) -> 0.0018660264
A8: Adjusted R Square | B8: =1-(1-B7)*(B10-1)/(B10-1-1) -> -0.097947371
A9: Standard Error | B9: =INDEX(LINEST(Analysis!$E$167:$E$178,Analysis!$C$167:$C$178,TRUE(),TRUE()),3,2) -> 41467.217
A10: Observations | B10: =COUNT(Analysis!$E$167:$E$178) -> 12
A12: ANOVA
B13: df | C13: SS | D13: MS | E13: F | F13: Significance F
A14: Regression | B14: 1 | C14: =INDEX(LINEST(Analysis!$E$167:$E$178,Analysis!$C$167:$C$178,TRUE(),TRUE()),5,1) -> 32146872 | D14: =C14/B14 -> 32146872 | E14: =D14/D15 -> 0.01869515 | F14: =FDIST(E14,B14,B15) -> 0.89395763
A15: Residual | B15: =B10-1-1 -> 10 | C15: =INDEX(LINEST(Analysis!$E$167:$E$178,Analysis!$C$167:$C$178,TRUE(),TRUE()),5,2) -> 1.7195301e+10 | D15: =C15/B15 -> 1.7195301e+09
A16: Total | B16: =B10-1 -> 11 | C16: =C14+C15 -> 1.7227447e+10
A18: Coefficients
B19: Coefficients | C19: Standard Error | D19: t Stat | E19: P-value | F19: Lower 95% | G19: Upper 95%
A20: Intercept | B20: =INDEX(LINEST(Analysis!$E$167:$E$178,Analysis!$C$167:$C$178,TRUE(),TRUE()),1,2) -> 413579.56 | C20: =INDEX(LINEST(Analysis!$E$167:$E$178,Analysis!$C$167:$C$178,TRUE(),TRUE()),2,2) -> 25521.308 | D20: =B20/C20 -> 16.205265 | E20: =TDIST(ABS(D20),$B$15,2) -> 1.6600943e-08 | F20: =B20-TINV(0.05,$B$15)*C20 -> 356714.55 | G20: =B20+TINV(0.05,$B$15)*C20 -> 470444.58
A21: Month index | B21: =INDEX(LINEST(Analysis!$E$167:$E$178,Analysis!$C$167:$C$178,TRUE(),TRUE()),1,1) -> 474.13427 | C21: =INDEX(LINEST(Analysis!$E$167:$E$178,Analysis!$C$167:$C$178,TRUE(),TRUE()),2,1) -> 3467.6629 | D21: =B21/C21 -> 0.13673021 | E21: =TDIST(ABS(D21),$B$15,2) -> 0.89395763 | F21: =B21-TINV(0.05,$B$15)*C21 -> -7252.3001 | G21: =B21+TINV(0.05,$B$15)*C21 -> 8200.5686
A23: RESIDUAL OUTPUT (Regression A)
A24: Observation | B24: Month | C24: Predicted Sales | D24: Residuals
A25: 1 | B25: =Analysis!B167 -> Jan-23 | C25: =$B$20+$B$21*Analysis!C167 -> 414053.7 | D25: =Analysis!E167-C25 -> 62038.663
A26: 2 | B26: =Analysis!B168 -> Feb-23 | C26: =$B$20+$B$21*Analysis!C168 -> 414527.83 | D26: =Analysis!E168-C26 -> -45608.471
A27: 3 | B27: =Analysis!B169 -> Mar-23 | C27: =$B$20+$B$21*Analysis!C169 -> 415001.97 | D27: =Analysis!E169-C27 -> -12363.195
A28: 4 | B28: =Analysis!B170 -> Apr-23 | C28: =$B$20+$B$21*Analysis!C170 -> 415476.1 | D28: =Analysis!E170-C28 -> 23516.511
A29: 5 | B29: =Analysis!B171 -> May-23 | C29: =$B$20+$B$21*Analysis!C171 -> 415950.23 | D29: =Analysis!E171-C29 -> -26871.474
A30: 6 | B30: =Analysis!B172 -> Jun-23 | C30: =$B$20+$B$21*Analysis!C172 -> 416424.37 | D30: =Analysis!E172-C30 -> 2033.9721
A31: 7 | B31: =Analysis!B173 -> Jul-23 | C31: =$B$20+$B$21*Analysis!C173 -> 416898.5 | D31: =Analysis!E173-C31 -> -42655.622
A32: 8 | B32: =Analysis!B174 -> Aug-23 | C32: =$B$20+$B$21*Analysis!C174 -> 417372.64 | D32: =Analysis!E174-C32 -> 25798.644
A33: 9 | B33: =Analysis!B175 -> Sep-23 | C33: =$B$20+$B$21*Analysis!C175 -> 417846.77 | D33: =Analysis!E175-C33 -> -50009.171
A34: 10 | B34: =Analysis!B176 -> Oct-23 | C34: =$B$20+$B$21*Analysis!C176 -> 418320.9 | D34: =Analysis!E176-C34 -> 42057.875
A35: 11 | B35: =Analysis!B177 -> Nov-23 | C35: =$B$20+$B$21*Analysis!C177 -> 418795.04 | D35: =Analysis!E177-C35 -> 48687.861
A36: 12 | B36: =Analysis!B178 -> Dec-23 | C36: =$B$20+$B$21*Analysis!C178 -> 419269.17 | D36: =Analysis!E178-C36 -> -26625.593
A39: REGRESSION B: What drives Sales_Amount? (Y = Sales_Amount, X = Quantity, Discount, Unit_Price; n = 1000)
A40: Regression Statistics
A41: Multiple R | B41: =SQRT(B42) -> 0.04964634
A42: R Square | B42: =INDEX(LINEST('Raw Data'!$E$2:$E$1001,'Raw Data'!$AI$2:$AK$1001,TRUE(),TRUE()),3,1) -> 0.0024647591
A43: Adjusted R Square | B43: =1-(1-B42)*(B45-1)/(B45-3-1) -> -0.00053986515
A44: Standard Error | B44: =INDEX(LINEST('Raw Data'!$E$2:$E$1001,'Raw Data'!$AI$2:$AK$1001,TRUE(),TRUE()),3,2) -> 2847.5585
A45: Observations | B45: =COUNT('Raw Data'!$E$2:$E$1001) -> 1000
A47: ANOVA
B48: df | C48: SS | D48: MS | E48: F | F48: Significance F
A49: Regression | B49: 3 | C49: =INDEX(LINEST('Raw Data'!$E$2:$E$1001,'Raw Data'!$AI$2:$AK$1001,TRUE(),TRUE()),5,1) -> 19954960 | D49: =C49/B49 -> 6651653.4 | E49: =D49/D50 -> 0.82032191 | F49: =FDIST(E49,B49,B50) -> 0.48271637
A50: Residual | B50: =B45-3-1 -> 996 | C50: =INDEX(LINEST('Raw Data'!$E$2:$E$1001,'Raw Data'!$AI$2:$AK$1001,TRUE(),TRUE()),5,2) -> 8.0761548e+09 | D50: =C50/B50 -> 8108589.2
A51: Total | B51: =B45-1 -> 999 | C51: =C49+C50 -> 8.0961098e+09
A53: Coefficients
B54: Coefficients | C54: Standard Error | D54: t Stat | E54: P-value | F54: Lower 95% | G54: Upper 95%
A55: Intercept | B55: =INDEX(LINEST('Raw Data'!$E$2:$E$1001,'Raw Data'!$AI$2:$AK$1001,TRUE(),TRUE()),1,4) -> 5039.8622 | C55: =INDEX(LINEST('Raw Data'!$E$2:$E$1001,'Raw Data'!$AI$2:$AK$1001,TRUE(),TRUE()),2,4) -> 295.24507 | D55: =B55/C55 -> 17.070098 | E55: =TDIST(ABS(D55),$B$50,2) -> 1.6658924e-57 | F55: =B55-TINV(0.05,$B$50)*C55 -> 4460.4884 | G55: =B55+TINV(0.05,$B$50)*C55 -> 5619.236
A56: Quantity_Sold | B56: =INDEX(LINEST('Raw Data'!$E$2:$E$1001,'Raw Data'!$AI$2:$AK$1001,TRUE(),TRUE()),1,3) -> -8.4960554 | C56: =INDEX(LINEST('Raw Data'!$E$2:$E$1001,'Raw Data'!$AI$2:$AK$1001,TRUE(),TRUE()),2,3) -> 6.3735491 | D56: =B56/C56 -> -1.333018 | E56: =TDIST(ABS(D56),$B$50,2) -> 0.18283074 | F56: =B56-TINV(0.05,$B$50)*C56 -> -21.003181 | G56: =B56+TINV(0.05,$B$50)*C56 -> 4.0110699
A57: Discount | B57: =INDEX(LINEST('Raw Data'!$E$2:$E$1001,'Raw Data'!$AI$2:$AK$1001,TRUE(),TRUE()),1,2) -> 753.22231 | C57: =INDEX(LINEST('Raw Data'!$E$2:$E$1001,'Raw Data'!$AI$2:$AK$1001,TRUE(),TRUE()),2,2) -> 1033.3512 | D57: =B57/C57 -> 0.72891224 | E57: =TDIST(ABS(D57),$B$50,2) -> 0.4662267 | F57: =B57-TINV(0.05,$B$50)*C57 -> -1274.5729 | G57: =B57+TINV(0.05,$B$50)*C57 -> 2781.0175
A58: Unit_Price | B58: =INDEX(LINEST('Raw Data'!$E$2:$E$1001,'Raw Data'!$AI$2:$AK$1001,TRUE(),TRUE()),1,1) -> 0.029334329 | C58: =INDEX(LINEST('Raw Data'!$E$2:$E$1001,'Raw Data'!$AI$2:$AK$1001,TRUE(),TRUE()),2,1) -> 0.063585645 | D58: =B58/C58 -> 0.46133572 | E58: =TDIST(ABS(D58),$B$50,2) -> 0.64465849 | F58: =B58-TINV(0.05,$B$50)*C58 -> -0.095442874 | G58: =B58+TINV(0.05,$B$50)*C58 -> 0.15411153
A61: REGRESSION C: How much margin does each discount point cost? (Y = Net Margin %, X = Discount, n = 1000)
A62: Regression Statistics
A63: Multiple R | B63: =SQRT(B64) -> 0.47213998
A64: R Square | B64: =INDEX(LINEST('Raw Data'!$S$2:$S$1001,'Raw Data'!$K$2:$K$1001,TRUE(),TRUE()),3,1) -> 0.22291616
A65: Adjusted R Square | B65: =1-(1-B64)*(B67-1)/(B67-1-1) -> 0.22213752
A66: Standard Error | B66: =INDEX(LINEST('Raw Data'!$S$2:$S$1001,'Raw Data'!$K$2:$K$1001,TRUE(),TRUE()),3,2) -> 0.18616711
A67: Observations | B67: =COUNT('Raw Data'!$S$2:$S$1001) -> 1000
A69: ANOVA
B70: df | C70: SS | D70: MS | E70: F | F70: Significance F
A71: Regression | B71: 1 | C71: =INDEX(LINEST('Raw Data'!$S$2:$S$1001,'Raw Data'!$K$2:$K$1001,TRUE(),TRUE()),5,1) -> 9.9222488 | D71: =C71/B71 -> 9.9222488 | E71: =D71/D72 -> 286.28871 | F71: =FDIST(E71,B71,B72) -> 1.1753443e-56
A72: Residual | B72: =B67-1-1 -> 998 | C72: =INDEX(LINEST('Raw Data'!$S$2:$S$1001,'Raw Data'!$K$2:$K$1001,TRUE(),TRUE()),5,2) -> 34.588875 | D72: =C72/B72 -> 0.034658191
A73: Total | B73: =B67-1 -> 999 | C73: =C71+C72 -> 44.511124
A75: Coefficients
B76: Coefficients | C76: Standard Error | D76: t Stat | E76: P-value | F76: Lower 95% | G76: Upper 95%
A77: Intercept | B77: =INDEX(LINEST('Raw Data'!$S$2:$S$1001,'Raw Data'!$K$2:$K$1001,TRUE(),TRUE()),1,2) -> 0.15255822 | C77: =INDEX(LINEST('Raw Data'!$S$2:$S$1001,'Raw Data'!$K$2:$K$1001,TRUE(),TRUE()),2,2) -> 0.011858061 | D77: =B77/C77 -> 12.86536 | E77: =TDIST(ABS(D77),$B$72,2) -> 3.7034284e-35 | F77: =B77-TINV(0.05,$B$72)*C77 -> 0.12928863 | G77: =B77+TINV(0.05,$B$72)*C77 -> 0.17582781
A78: Discount | B78: =INDEX(LINEST('Raw Data'!$S$2:$S$1001,'Raw Data'!$K$2:$K$1001,TRUE(),TRUE()),1,1) -> -1.1428973 | C78: =INDEX(LINEST('Raw Data'!$S$2:$S$1001,'Raw Data'!$K$2:$K$1001,TRUE(),TRUE()),2,1) -> 0.06754685 | D78: =B78/C78 -> -16.920068 | E78: =TDIST(ABS(D78),$B$72,2) -> 1.1753443e-56 | F78: =B78-TINV(0.05,$B$72)*C78 -> -1.2754474 | G78: =B78+TINV(0.05,$B$72)*C78 -> -1.0103472
A81: CORRELATION MATRIX (CORREL)
B82: Sales_Amount | C82: Quantity | D82: Discount | E82: Unit_Price | F82: Unit_Cost | G82: Net Margin %
A83: Sales_Amount | B83: =CORREL('Raw Data'!$E$2:$E$1001,'Raw Data'!$E$2:$E$1001) -> 1 | C83: =CORREL('Raw Data'!$E$2:$E$1001,'Raw Data'!$F$2:$F$1001) -> -0.041598705 | D83: =CORREL('Raw Data'!$E$2:$E$1001,'Raw Data'!$K$2:$K$1001) -> 0.023152703 | E83: =CORREL('Raw Data'!$E$2:$E$1001,'Raw Data'!$I$2:$I$1001) -> 0.011812024 | F83: =CORREL('Raw Data'!$E$2:$E$1001,'Raw Data'!$H$2:$H$1001) -> 0.0097695122 | G83: =CORREL('Raw Data'!$E$2:$E$1001,'Raw Data'!$S$2:$S$1001) -> -0.011217282
A84: Quantity | B84: =CORREL('Raw Data'!$F$2:$F$1001,'Raw Data'!$E$2:$E$1001) -> -0.041598705 | C84: =CORREL('Raw Data'!$F$2:$F$1001,'Raw Data'!$F$2:$F$1001) -> 1 | D84: =CORREL('Raw Data'!$F$2:$F$1001,'Raw Data'!$K$2:$K$1001) -> -0.0078062601 | E84: =CORREL('Raw Data'!$F$2:$F$1001,'Raw Data'!$I$2:$I$1001) -> 0.057295929 | F84: =CORREL('Raw Data'!$F$2:$F$1001,'Raw Data'!$H$2:$H$1001) -> 0.053887557 | G84: =CORREL('Raw Data'!$F$2:$F$1001,'Raw Data'!$S$2:$S$1001) -> -0.0095327777
A85: Discount | B85: =CORREL('Raw Data'!$K$2:$K$1001,'Raw Data'!$E$2:$E$1001) -> 0.023152703 | C85: =CORREL('Raw Data'!$K$2:$K$1001,'Raw Data'!$F$2:$F$1001) -> -0.0078062601 | D85: =CORREL('Raw Data'!$K$2:$K$1001,'Raw Data'!$K$2:$K$1001) -> 1 | E85: =CORREL('Raw Data'!$K$2:$K$1001,'Raw Data'!$I$2:$I$1001) -> -0.017026838 | F85: =CORREL('Raw Data'!$K$2:$K$1001,'Raw Data'!$H$2:$H$1001) -> -0.017741095 | G85: =CORREL('Raw Data'!$K$2:$K$1001,'Raw Data'!$S$2:$S$1001) -> -0.47213998
A86: Unit_Price | B86: =CORREL('Raw Data'!$I$2:$I$1001,'Raw Data'!$E$2:$E$1001) -> 0.011812024 | C86: =CORREL('Raw Data'!$I$2:$I$1001,'Raw Data'!$F$2:$F$1001) -> 0.057295929 | D86: =CORREL('Raw Data'!$I$2:$I$1001,'Raw Data'!$K$2:$K$1001) -> -0.017026838 | E86: =CORREL('Raw Data'!$I$2:$I$1001,'Raw Data'!$I$2:$I$1001) -> 1 | F86: =CORREL('Raw Data'!$I$2:$I$1001,'Raw Data'!$H$2:$H$1001) -> 0.99505556 | G86: =CORREL('Raw Data'!$I$2:$I$1001,'Raw Data'!$S$2:$S$1001) -> -0.53906843
A87: Unit_Cost | B87: =CORREL('Raw Data'!$H$2:$H$1001,'Raw Data'!$E$2:$E$1001) -> 0.0097695122 | C87: =CORREL('Raw Data'!$H$2:$H$1001,'Raw Data'!$F$2:$F$1001) -> 0.053887557 | D87: =CORREL('Raw Data'!$H$2:$H$1001,'Raw Data'!$K$2:$K$1001) -> -0.017741095 | E87: =CORREL('Raw Data'!$H$2:$H$1001,'Raw Data'!$I$2:$I$1001) -> 0.99505556 | F87: =CORREL('Raw Data'!$H$2:$H$1001,'Raw Data'!$H$2:$H$1001) -> 1 | G87: =CORREL('Raw Data'!$H$2:$H$1001,'Raw Data'!$S$2:$S$1001) -> -0.57807519
A88: Net Margin % | B88: =CORREL('Raw Data'!$S$2:$S$1001,'Raw Data'!$E$2:$E$1001) -> -0.011217282 | C88: =CORREL('Raw Data'!$S$2:$S$1001,'Raw Data'!$F$2:$F$1001) -> -0.0095327777 | D88: =CORREL('Raw Data'!$S$2:$S$1001,'Raw Data'!$K$2:$K$1001) -> -0.47213998 | E88: =CORREL('Raw Data'!$S$2:$S$1001,'Raw Data'!$I$2:$I$1001) -> -0.53906843 | F88: =CORREL('Raw Data'!$S$2:$S$1001,'Raw Data'!$H$2:$H$1001) -> -0.57807519 | G88: =CORREL('Raw Data'!$S$2:$S$1001,'Raw Data'!$S$2:$S$1001) -> 1
A90: ="A) Trend: sales move "&TEXT('Regression Output'!$B$21,"$#,##0")&" per month (R² "&TEXT('Regression Output'!$B$7,"0.000")&", Significance F "&TEXT('Regression Output'!$F$14,"0.000")&"): "&IF('Regression Output'!$F$14<0.05,"statistically significant.","NOT significant, so monthly sales are flat apart from random swings.") -> A) Trend: sales move $474 per month (R² 0.002, Significance F 0.894): NOT significant, so monthly sales are flat apart from random swings.
A91: ="B) Drivers: Quantity, Discount and Unit_Price together explain only "&TEXT('Regression Output'!$B$42,"0.0%")&" of Sales_Amount (Significance F "&TEXT('Regression Output'!$F$49,"0.000")&"): "&IF('Regression Output'!$F$49<0.05,"at least one driver is significant.","none of these fields predicts the size of a sale.") -> B) Drivers: Quantity, Discount and Unit_Price together explain only 0.2% of Sales_Amount (Significance F 0.483): none of these fields predicts the size of a sale.
A92: ="C) Discount vs margin: every +1 percentage point of discount changes net margin by "&TEXT('Regression Output'!$B$78/100,"0.00%")&" (R² "&TEXT('Regression Output'!$B$64,"0.000")&", p-value "&TEXT('Regression Output'!$E$78,"0.0000")&"): "&IF('Regression Output'!$E$78<0.05,"statistically significant.","not significant.") -> C) Discount vs margin: every +1 percentage point of discount changes net margin by -1.14% (R² 0.223, p-value 0.0000): statistically significant.

Sheet Scenario Summary
A1: Scenario Summary
A2: Scenarios are saved in Scenario Manager (Data > What-If Analysis > Scenario Manager) on the Analysis sheet; this sheet compares them. Sales_Amount is treated as net of discount; margins use the list-price basis.
B4: Current Values | C4: Base case | D4: Discount discipline | E4: Growth push | F4: Price rise
A5: Changing Cells:
A6: Price change % | B6: =Analysis!B211 -> 0 | C6: =Analysis!C211 -> 0 | D6: =Analysis!D211 -> 0 | E6: =Analysis!E211 -> 0 | F6: =Analysis!F211 -> 0.05
A7: Volume change % | B7: =Analysis!B212 -> 0 | C7: =Analysis!C212 -> 0 | D7: =Analysis!D212 -> -0.03 | E7: =Analysis!E212 -> 0.1 | F7: =Analysis!F212 -> -0.04
A8: Discount change (pp) | B8: =Analysis!B213 -> 0 | C8: =Analysis!C213 -> 0 | D8: =Analysis!D213 -> -0.05 | E8: =Analysis!E213 -> 0.03 | F8: =Analysis!F213 -> 0
A9: Result Cells:
A10: Projected sales | B10: =Analysis!B219 -> 5019265.2 | C10: =Analysis!C219 -> 5019265.2 | D10: =Analysis!D219 -> 5155533 | E10: =Analysis!E219 -> 5326018.4 | F10: =Analysis!F219 -> 5059419.4
A11: Change vs baseline sales | B11: =B10/Analysis!B214-1 -> 0 | C11: =C10/Analysis!C214-1 -> 0 | D11: =D10/Analysis!D214-1 -> 0.02714895 | E11: =E10/Analysis!E214-1 -> 0.061115148 | F11: =F10/Analysis!F214-1 -> 0.008
A12: Projected net margin ($) | B12: =Analysis!B221 -> -4155920.1 | C12: =Analysis!C221 -> -4155920.1 | D12: =Analysis!D221 -> -620240.38 | E12: =Analysis!E221 -> -6892400.2 | F12: =Analysis!F221 -> -1124747
A13: Projected net margin % | B13: =Analysis!B222 -> -0.069629528 | C13: =Analysis!C222 -> -0.069629528 | D13: =Analysis!D222 -> -0.010117026 | E13: =Analysis!E222 -> -0.10882639 | F13: =Analysis!F222 -> -0.018694789
A15: Goal Seek result: discount level needed for the target net margin
A16: Target net margin % | B16: =Analysis!B224 -> 0.05
A17: Current weighted discount | B17: =Analysis!B217 -> 0.15134048
A18: Weighted discount that reaches target (closed form) | B18: =Analysis!B225 -> 0.044472338
A19: Discount change needed (percentage points) | B19: =Analysis!B226 -> -0.10686814
A20: Net margin % at that discount (check) | B20: =1-Analysis!B216/(Analysis!B215*(1+Analysis!B211)*(1-B18)) -> 0.05
A21: Difference to target (0 = solved) | B21: =ROUND(B20-B16,6) -> 0

Sheet Formula Lab
A1: Formula Lab: basic to advanced
A2: Each row shows a formula (as text), what it answers, and its live result computed from the Raw Data.
A3: Level | B3: Topic | C3: What it answers | D3: Formula | E3: Result
A4: Basic | B4: SUM | C4: Total sales | D4: =SUM('Raw Data'!$E$2:$E$1001) | E4: =SUM('Raw Data'!$E$2:$E$1001) -> 5019265.2
A5: Basic | B5: AVERAGE | C5: Average sale | D5: =AVERAGE('Raw Data'!$E$2:$E$1001) | E5: =AVERAGE('Raw Data'!$E$2:$E$1001) -> 5019.2652
A6: Basic | B6: MEDIAN | C6: Median sale | D6: =MEDIAN('Raw Data'!$E$2:$E$1001) | E6: =MEDIAN('Raw Data'!$E$2:$E$1001) -> 5019.3
A7: Basic | B7: MIN / MAX | C7: Smallest and largest sale | D7: =TEXT(MIN('Raw Data'!$E$2:$E$1001),"$#,##0")&" to "&TEXT(MAX('Raw Data'!$E$2:$E$1001),"$#,##0") | E7: =TEXT(MIN('Raw Data'!$E$2:$E$1001),"$#,##0")&" to "&TEXT(MAX('Raw Data'!$E$2:$E$1001),"$#,##0") -> $100 to $9,989
A8: Basic | B8: COUNT | C8: Numeric sales rows | D8: =COUNT('Raw Data'!$E$2:$E$1001) | E8: =COUNT('Raw Data'!$E$2:$E$1001) -> 1000
A9: Basic | B9: COUNTA | C9: Filled rep cells | D9: =COUNTA('Raw Data'!$C$2:$C$1001) | E9: =COUNTA('Raw Data'!$C$2:$C$1001) -> 1000
A10: Basic | B10: COUNTBLANK | C10: Blank cells in Sales_Amount | D10: =COUNTBLANK('Raw Data'!$E$2:$E$1001) | E10: =COUNTBLANK('Raw Data'!$E$2:$E$1001) -> 0
A11: Basic | B11: ROUND | C11: Average sale to the nearest 100 | D11: =ROUND(AVERAGE('Raw Data'!$E$2:$E$1001),-2) | E11: =ROUND(AVERAGE('Raw Data'!$E$2:$E$1001),-2) -> 5000
A12: Basic | B12: MODE.SNGL | C12: Most frequent Product_ID | D12: =MODE.SNGL('Raw Data'!$A$2:$A$1001) | E12: =_xlfn.MODE.SNGL('Raw Data'!$A$2:$A$1001) -> 1090
A13: Basic | B13: Arithmetic | C13: Average units per sale | D13: =SUM('Raw Data'!$F$2:$F$1001)/COUNT('Raw Data'!$F$2:$F$1001) | E13: =SUM('Raw Data'!$F$2:$F$1001)/COUNT('Raw Data'!$F$2:$F$1001) -> 25.355
A14: Intermediate | B14: SUMIF | C14: Sales in the North region | D14: =SUMIF('Raw Data'!$D$2:$D$1001,"North",'Raw Data'!$E$2:$E$1001) | E14: =SUMIF('Raw Data'!$D$2:$D$1001,"North",'Raw Data'!$E$2:$E$1001) -> 1369612.5
A15: Intermediate | B15: COUNTIF | C15: Online transactions | D15: =COUNTIF('Raw Data'!$M$2:$M$1001,"Online") | E15: =COUNTIF('Raw Data'!$M$2:$M$1001,"Online") -> 488
A16: Intermediate | B16: AVERAGEIF | C16: Average sale to returning customers | D16: =AVERAGEIF('Raw Data'!$J$2:$J$1001,"Returning",'Raw Data'!$E$2:$E$1001) | E16: =AVERAGEIF('Raw Data'!$J$2:$J$1001,"Returning",'Raw Data'!$E$2:$E$1001) -> 5066.5462
A17: Intermediate | B17: SUMIFS | C17: West sales of Electronics | D17: =SUMIFS('Raw Data'!$E$2:$E$1001,'Raw Data'!$D$2:$D$1001,"West",'Raw Data'!$G$2:$G$1001,"Electronics") | E17: =SUMIFS('Raw Data'!$E$2:$E$1001,'Raw Data'!$D$2:$D$1001,"West",'Raw Data'!$G$2:$G$1001,"Electronics") -> 304067.97
A18: Intermediate | B18: COUNTIFS + dates | C18: Sales made in June 2023 | D18: =COUNTIFS('Raw Data'!$B$2:$B$1001,">="&DATE(2023,6,1),'Raw Data'!$B$2:$B$1001,"<"&DATE(2023,7,1)) | E18: =COUNTIFS('Raw Data'!$B$2:$B$1001,">="&DATE(2023,6,1),'Raw Data'!$B$2:$B$1001,"<"&DATE(2023,7,1)) -> 92
A19: Intermediate | B19: AVERAGEIFS | C19: Average discount, Retail channel, Alice | D19: =AVERAGEIFS('Raw Data'!$K$2:$K$1001,'Raw Data'!$M$2:$M$1001,"Retail",'Raw Data'!$C$2:$C$1001,"Alice") | E19: =AVERAGEIFS('Raw Data'!$K$2:$K$1001,'Raw Data'!$M$2:$M$1001,"Retail",'Raw Data'!$C$2:$C$1001,"Alice") -> 0.1446875
A20: Intermediate | B20: MAXIFS | C20: Largest Food sale | D20: =MAXIFS('Raw Data'!$E$2:$E$1001,'Raw Data'!$G$2:$G$1001,"Food") | E20: =_xlfn.MAXIFS('Raw Data'!$E$2:$E$1001,'Raw Data'!$G$2:$G$1001,"Food") -> 9989.04
A21: Intermediate | B21: MINIFS | C21: Smallest Furniture sale | D21: =MINIFS('Raw Data'!$E$2:$E$1001,'Raw Data'!$G$2:$G$1001,"Furniture") | E21: =_xlfn.MINIFS('Raw Data'!$E$2:$E$1001,'Raw Data'!$G$2:$G$1001,"Furniture") -> 113.4
A22: Intermediate | B22: IF | C22: Is total sales above $5M? | D22: =IF(SUM('Raw Data'!$E$2:$E$1001)>5000000,"Above $5M","Below $5M") | E22: =IF(SUM('Raw Data'!$E$2:$E$1001)>5000000,"Above $5M","Below $5M") -> Above $5M
A23: Intermediate | B23: IFS (nested logic) | C23: Discount level label | D23: =IFS(AVERAGE('Raw Data'!$K$2:$K$1001)<0.1,"Low",AVERAGE('Raw Data'!$K$2:$K$1001)<0.2,"Medium",TRUE,"High") | E23: =_xlfn.IFS(AVERAGE('Raw Data'!$K$2:$K$1001)<0.1,"Low",AVERAGE('Raw Data'!$K$2:$K$1001)<0.2,"Medium",TRUE(),"High") -> Medium
A24: Intermediate | B24: IF + AND | C24: Does discount span 0% to 30%? | D24: =IF(AND(MIN('Raw Data'!$K$2:$K$1001)=0,MAX('Raw Data'!$K$2:$K$1001)>=0.3),"Full range 0-30%","Narrower") | E24: =IF(AND(MIN('Raw Data'!$K$2:$K$1001)=0,MAX('Raw Data'!$K$2:$K$1001)>=0.3),"Full range 0-30%","Narrower") -> Full range 0-30%
A25: Intermediate | B25: RANK | C25: Rank of the first sale by amount | D25: =RANK('Raw Data'!$E$2,'Raw Data'!$E$2:$E$1001,0) | E25: =RANK('Raw Data'!$E$2,'Raw Data'!$E$2:$E$1001,0) -> 496
A26: Intermediate | B26: LARGE | C26: Third-largest sale | D26: =LARGE('Raw Data'!$E$2:$E$1001,3) | E26: =LARGE('Raw Data'!$E$2:$E$1001,3) -> 9972.66
A27: Intermediate | B27: SMALL | C27: Second-smallest sale | D27: =SMALL('Raw Data'!$E$2:$E$1001,2) | E27: =SMALL('Raw Data'!$E$2:$E$1001,2) -> 106.47
A28: Intermediate | B28: PERCENTILE | C28: 90th percentile of sales | D28: =PERCENTILE('Raw Data'!$E$2:$E$1001,0.9) | E28: =PERCENTILE('Raw Data'!$E$2:$E$1001,0.9) -> 8912.473
A29: Intermediate | B29: QUARTILE | C29: Third quartile of sales | D29: =QUARTILE('Raw Data'!$E$2:$E$1001,3) | E29: =QUARTILE('Raw Data'!$E$2:$E$1001,3) -> 7507.445
A30: Intermediate | B30: STDEV.S | C30: Standard deviation of sales | D30: =STDEV.S('Raw Data'!$E$2:$E$1001) | E30: =_xlfn.STDEV.S('Raw Data'!$E$2:$E$1001) -> 2846.7901
A31: Intermediate | B31: CORREL | C31: Discount vs Sales correlation | D31: =CORREL('Raw Data'!$K$2:$K$1001,'Raw Data'!$E$2:$E$1001) | E31: =CORREL('Raw Data'!$K$2:$K$1001,'Raw Data'!$E$2:$E$1001) -> 0.023152703
A32: Intermediate | B32: SUBTOTAL | C32: Sum that ignores filtered-out rows | D32: =SUBTOTAL(109,'Raw Data'!$E$2:$E$1001) | E32: =SUBTOTAL(109,'Raw Data'!$E$2:$E$1001) -> 5019265.2
A33: Intermediate | B33: COUNTIF wildcard | C33: Combinations for Alice | D33: =COUNTIF('Raw Data'!$N$2:$N$1001,"*-Alice") | E33: =COUNTIF('Raw Data'!$N$2:$N$1001,"*-Alice") -> 192
A34: Text & date | B34: TEXT | C34: Date of the last sale, long form | D34: =TEXT(MAX('Raw Data'!$B$2:$B$1001),"dddd, dd mmmm yyyy") | E34: =TEXT(MAX('Raw Data'!$B$2:$B$1001),"dddd, dd mmmm yyyy") -> Monday, 01 January 2024
A35: Text & date | B35: LEFT + FIND | C35: Region extracted from the first label | D35: =LEFT('Raw Data'!$N$2,FIND("-",'Raw Data'!$N$2)-1) | E35: =LEFT('Raw Data'!$N$2,FIND("-",'Raw Data'!$N$2)-1) -> North
A36: Text & date | B36: MID + FIND | C36: Rep extracted from the first label | D36: =MID('Raw Data'!$N$2,FIND("-",'Raw Data'!$N$2)+1,20) | E36: =MID('Raw Data'!$N$2,FIND("-",'Raw Data'!$N$2)+1,20) -> Bob
A37: Text & date | B37: UPPER + LEFT | C37: Three-letter rep code | D37: =UPPER(LEFT('Raw Data'!$C$2,3)) | E37: =UPPER(LEFT('Raw Data'!$C$2,3)) -> BOB
A38: Text & date | B38: LEN | C38: Length of the first label | D38: =LEN('Raw Data'!$N$2) | E38: =LEN('Raw Data'!$N$2) -> 9
A39: Text & date | B39: SUBSTITUTE | C39: Label with a different separator | D39: =SUBSTITUTE('Raw Data'!$N$2,"-"," / ") | E39: =SUBSTITUTE('Raw Data'!$N$2,"-"," / ") -> North / Bob
A40: Text & date | B40: & (concatenate) | C40: Sentence from three fields | D40: ='Raw Data'!$C$2&" sold "&'Raw Data'!$G$2&" in the "&'Raw Data'!$D$2 | E40: ='Raw Data'!$C$2&" sold "&'Raw Data'!$G$2&" in the "&'Raw Data'!$D$2 -> Bob sold Furniture in the North
A41: Text & date | B41: TEXTJOIN | C41: List of all reps | D41: =TEXTJOIN(", ",TRUE,Analysis!$A$76:$A$80) | E41: =_xlfn.TEXTJOIN(", ",TRUE(),Analysis!$A$76:$A$80) -> Alice, Bob, Charlie, David, Eve
A42: Text & date | B42: EOMONTH | C42: Month-end of the last sale | D42: =EOMONTH(MAX('Raw Data'!$B$2:$B$1001),0) | E42: =EOMONTH(MAX('Raw Data'!$B$2:$B$1001),0) -> 45322
A43: Text & date | B43: EDATE | C43: Date six months after the first sale | D43: =EDATE(MIN('Raw Data'!$B$2:$B$1001),6) | E43: =EDATE(MIN('Raw Data'!$B$2:$B$1001),6) -> 45108
A44: Text & date | B44: DATEDIF | C44: Months covered by the data | D44: =DATEDIF(MIN('Raw Data'!$B$2:$B$1001),MAX('Raw Data'!$B$2:$B$1001),"M") | E44: =DATEDIF(MIN('Raw Data'!$B$2:$B$1001),MAX('Raw Data'!$B$2:$B$1001),"M") -> 12
A45: Text & date | B45: NETWORKDAYS | C45: Working days covered | D45: =NETWORKDAYS(MIN('Raw Data'!$B$2:$B$1001),MAX('Raw Data'!$B$2:$B$1001)) | E45: =NETWORKDAYS(MIN('Raw Data'!$B$2:$B$1001),MAX('Raw Data'!$B$2:$B$1001)) -> 261
A46: Text & date | B46: WEEKNUM / WEEKDAY | C46: Week number of the last sale | D46: =WEEKNUM(MAX('Raw Data'!$B$2:$B$1001),2) | E46: =WEEKNUM(MAX('Raw Data'!$B$2:$B$1001),2) -> 1
A47: Text & date | B47: TODAY | C47: Days since the last sale | D47: =TODAY()-MAX('Raw Data'!$B$2:$B$1001) | E47: =TODAY()-MAX('Raw Data'!$B$2:$B$1001) -> 1027
A48: Advanced | B48: SUMPRODUCT (weighted) | C48: Value-weighted average discount | D48: =SUMPRODUCT('Raw Data'!$F$2:$F$1001,'Raw Data'!$I$2:$I$1001,'Raw Data'!$K$2:$K$1001)/SUMPRODUCT('Raw Data'!$F$2:$F$1001,'Raw Data'!$I$2:$I$1001) | E48: =SUMPRODUCT('Raw Data'!$F$2:$F$1001,'Raw Data'!$I$2:$I$1001,'Raw Data'!$K$2:$K$1001)/SUMPRODUCT('Raw Data'!$F$2:$F$1001,'Raw Data'!$I$2:$I$1001) -> 0.15134049
A49: Advanced | B49: SUMPRODUCT (multi-condition) | C49: North Food sales without SUMIFS | D49: =SUMPRODUCT(('Raw Data'!$D$2:$D$1001="North")*('Raw Data'!$G$2:$G$1001="Food")*'Raw Data'!$E$2:$E$1001) | E49: =SUMPRODUCT(('Raw Data'!$D$2:$D$1001="North")*('Raw Data'!$G$2:$G$1001="Food")*'Raw Data'!$E$2:$E$1001) -> 258985.65
A50: Advanced | B50: SUMPRODUCT + COUNTIF | C50: Distinct selling days | D50: =SUMPRODUCT(1/COUNTIF('Raw Data'!$B$2:$B$1001,'Raw Data'!$B$2:$B$1001)) | E50: =SUMPRODUCT(1/COUNTIF('Raw Data'!$B$2:$B$1001,'Raw Data'!$B$2:$B$1001)) -> 340
A51: Advanced | B51: INDEX + MATCH + MAX | C51: Best rep by sales | D51: =INDEX(Analysis!$A$76:$A$80,MATCH(MAX(Analysis!$C$76:$C$80),Analysis!$C$76:$C$80,0)) | E51: =INDEX(Analysis!$A$76:$A$80,MATCH(MAX(Analysis!$C$76:$C$80),Analysis!$C$76:$C$80,0)) -> David
A52: Advanced | B52: INDEX + MATCH (two-way) | C52: North sales by Bob from the matrix | D52: =INDEX(Analysis!$B$154:$F$157,MATCH("North",Analysis!$A$154:$A$157,0),MATCH("Bob",Analysis!$B$153:$F$153,0)) | E52: =INDEX(Analysis!$B$154:$F$157,MATCH("North",Analysis!$A$154:$A$157,0),MATCH("Bob",Analysis!$B$153:$F$153,0)) -> 233464.81
A53: Advanced | B53: IFERROR + MATCH | C53: Lookup that fails gracefully | D53: =IFERROR(MATCH("Zoe",Analysis!$A$76:$A$80,0),"Rep not found") | E53: =IFERROR(MATCH("Zoe",Analysis!$A$76:$A$80,0),"Rep not found") -> Rep not found
A54: Advanced | B54: CHOOSE + WEEKDAY | C54: Name of the weekday of the last sale | D54: =CHOOSE(WEEKDAY(MAX('Raw Data'!$B$2:$B$1001),2),"Mon","Tue","Wed","Thu","Fri","Sat","Sun") | E54: =CHOOSE(WEEKDAY(MAX('Raw Data'!$B$2:$B$1001),2),"Mon","Tue","Wed","Thu","Fri","Sat","Sun") -> Mon
A55: Advanced | B55: LOOKUP (approximate) | C55: Size band of the average sale | D55: =LOOKUP(AVERAGE('Raw Data'!$E$2:$E$1001),{0,2500,5000,7500},{"Low","Mid","High","Top"}) | E55: =LOOKUP(AVERAGE('Raw Data'!$E$2:$E$1001),{0,2500,5000,7500},{"Low","Mid","High","Top"}) -> High
A56: Advanced | B56: LINEST (regression) | C56: Margin lost per +100% discount (slope) | D56: =INDEX(LINEST('Raw Data'!$S$2:$S$1001,'Raw Data'!$K$2:$K$1001),1,1) | E56: =INDEX(LINEST('Raw Data'!$S$2:$S$1001,'Raw Data'!$K$2:$K$1001),1,1) -> -1.1428973
A57: Advanced | B57: FORECAST | C57: Next-month sales on the trend line | D57: =FORECAST(13,Analysis!$E$167:$E$178,Analysis!$C$167:$C$178) | E57: =FORECAST(13,Analysis!$E$167:$E$178,Analysis!$C$167:$C$178) -> 419743.31
A58: Advanced | B58: z-score outliers | C58: Sales more than 2 SD from the mean | D58: =SUMPRODUCT(--(ABS('Raw Data'!$E$2:$E$1001-AVERAGE('Raw Data'!$E$2:$E$1001))/STDEV.S('Raw Data'!$E$2:$E$1001)>2)) | E58: =SUMPRODUCT(--(ABS('Raw Data'!$E$2:$E$1001-AVERAGE('Raw Data'!$E$2:$E$1001))/_xlfn.STDEV.S('Raw Data'!$E$2:$E$1001)>2)) -> 0
A59: Excel 365 | B59: UNIQUE | C59: Distinct list of reps | D59: =UNIQUE(tblSales[Sales_Rep]) | E59: Paste into Excel 365 (not evaluated here)
A60: Excel 365 | B60: FILTER | C60: All North sales above $9,000 | D60: =FILTER(tblSales,(tblSales[Region]="North")*(tblSales[Sales_Amount]>9000)) | E60: Paste into Excel 365 (not evaluated here)
A61: Excel 365 | B61: SORTBY | C61: Rep leaderboard sorted | D61: =SORTBY(Analysis!A76:C80,Analysis!C76:C80,-1) | E61: Paste into Excel 365 (not evaluated here)
A62: Excel 365 | B62: XLOOKUP | C62: Region of a sale code | D62: =XLOOKUP("NO-230203-0001",tblSales[Order_Code],tblSales[Region],"Not found") | E62: Paste into Excel 365 (not evaluated here)
A63: Excel 365 | B63: LET | C63: Named intermediate values | D63: =LET(s,SUM(tblSales[Sales_Amount]),n,COUNTA(tblSales[Sales_Amount]),s/n) | E63: Paste into Excel 365 (not evaluated here)
A64: Excel 365 | B64: GROUPBY | C64: Sales by rep in one formula | D64: =GROUPBY(tblSales[Sales_Rep],tblSales[Sales_Amount],SUM,,0,-2) | E64: Paste into Excel 365 (not evaluated here)

Sheet Visualizations
A1: Visualizations
A2: Charts linked to the Analysis tables (always the full dataset). Interactive charts and pivot charts are on the Dashboard.
A4: Sales by Region | J4: Monthly Sales Trend with 3-Month Moving Average
A21: Share of Sales by Category | J21: Sales by Sales Rep
A38: Sales by Day of Week | J38: Net Margin % by Discount Band

Sheet Calc
A1: Regions | B1: Categories | C1: Sales reps | D1: Channels
A2: All | B2: All | C2: All | D2: All
A3: East | B3: Clothing | C3: Alice | D3: Online
A4: North | B4: Electronics | C4: Bob | D4: Retail
A5: South | B5: Food | C5: Charlie
A6: West | B6: Furniture | C6: David
C7: Eve
A8: Criteria (wildcard * = All)
A9: Region | B9: =IF(Dashboard!$B$11="All","*",Dashboard!$B$11) -> *
A10: Category | B10: =IF(Dashboard!$E$11="All","*",Dashboard!$E$11) -> *
A11: Sales rep | B11: =IF(Dashboard!$H$11="All","*",Dashboard!$H$11) -> *
A12: Channel | B12: =IF(Dashboard!$K$11="All","*",Dashboard!$K$11) -> *
A13: From date | B13: =Dashboard!$N$11 -> 44927
A14: To date | B14: =Dashboard!$Q$11 -> 45322
A18: Month | B18: Month_End | C18: Sales | D18: Transactions
A19: =Analysis!B167 -> Jan-23 | B19: =Analysis!A167 -> 44957 | C19: =SUMIFS('Raw Data'!$E$2:$E$1001,'Raw Data'!$D$2:$D$1001,$B$9,'Raw Data'!$G$2:$G$1001,$B$10,'Raw Data'!$C$2:$C$1001,$B$11,'Raw Data'!$M$2:$M$1001,$B$12,'Raw Data'!$B$2:$B$1001,">="&$B$13,'Raw Data'!$B$2:$B$1001,"<="&$B$14,'Raw Data'!$X$2:$X$1001,B19) -> 476092.36 | D19: =COUNTIFS('Raw Data'!$D$2:$D$1001,$B$9,'Raw Data'!$G$2:$G$1001,$B$10,'Raw Data'!$C$2:$C$1001,$B$11,'Raw Data'!$M$2:$M$1001,$B$12,'Raw Data'!$B$2:$B$1001,">="&$B$13,'Raw Data'!$B$2:$B$1001,"<="&$B$14,'Raw Data'!$X$2:$X$1001,B19) -> 100
A20: =Analysis!B168 -> Feb-23 | B20: =Analysis!A168 -> 44985 | C20: =SUMIFS('Raw Data'!$E$2:$E$1001,'Raw Data'!$D$2:$D$1001,$B$9,'Raw Data'!$G$2:$G$1001,$B$10,'Raw Data'!$C$2:$C$1001,$B$11,'Raw Data'!$M$2:$M$1001,$B$12,'Raw Data'!$B$2:$B$1001,">="&$B$13,'Raw Data'!$B$2:$B$1001,"<="&$B$14,'Raw Data'!$X$2:$X$1001,B20) -> 368919.36 | D20: =COUNTIFS('Raw Data'!$D$2:$D$1001,$B$9,'Raw Data'!$G$2:$G$1001,$B$10,'Raw Data'!$C$2:$C$1001,$B$11,'Raw Data'!$M$2:$M$1001,$B$12,'Raw Data'!$B$2:$B$1001,">="&$B$13,'Raw Data'!$B$2:$B$1001,"<="&$B$14,'Raw Data'!$X$2:$X$1001,B20) -> 75
A21: =Analysis!B169 -> Mar-23 | B21: =Analysis!A169 -> 45016 | C21: =SUMIFS('Raw Data'!$E$2:$E$1001,'Raw Data'!$D$2:$D$1001,$B$9,'Raw Data'!$G$2:$G$1001,$B$10,'Raw Data'!$C$2:$C$1001,$B$11,'Raw Data'!$M$2:$M$1001,$B$12,'Raw Data'!$B$2:$B$1001,">="&$B$13,'Raw Data'!$B$2:$B$1001,"<="&$B$14,'Raw Data'!$X$2:$X$1001,B21) -> 402638.77 | D21: =COUNTIFS('Raw Data'!$D$2:$D$1001,$B$9,'Raw Data'!$G$2:$G$1001,$B$10,'Raw Data'!$C$2:$C$1001,$B$11,'Raw Data'!$M$2:$M$1001,$B$12,'Raw Data'!$B$2:$B$1001,">="&$B$13,'Raw Data'!$B$2:$B$1001,"<="&$B$14,'Raw Data'!$X$2:$X$1001,B21) -> 80
A22: =Analysis!B170 -> Apr-23 | B22: =Analysis!A170 -> 45046 | C22: =SUMIFS('Raw Data'!$E$2:$E$1001,'Raw Data'!$D$2:$D$1001,$B$9,'Raw Data'!$G$2:$G$1001,$B$10,'Raw Data'!$C$2:$C$1001,$B$11,'Raw Data'!$M$2:$M$1001,$B$12,'Raw Data'!$B$2:$B$1001,">="&$B$13,'Raw Data'!$B$2:$B$1001,"<="&$B$14,'Raw Data'!$X$2:$X$1001,B22) -> 438992.61 | D22: =COUNTIFS('Raw Data'!$D$2:$D$1001,$B$9,'Raw Data'!$G$2:$G$1001,$B$10,'Raw Data'!$C$2:$C$1001,$B$11,'Raw Data'!$M$2:$M$1001,$B$12,'Raw Data'!$B$2:$B$1001,">="&$B$13,'Raw Data'!$B$2:$B$1001,"<="&$B$14,'Raw Data'!$X$2:$X$1001,B22) -> 81
A23: =Analysis!B171 -> May-23 | B23: =Analysis!A171 -> 45077 | C23: =SUMIFS('Raw Data'!$E$2:$E$1001,'Raw Data'!$D$2:$D$1001,$B$9,'Raw Data'!$G$2:$G$1001,$B$10,'Raw Data'!$C$2:$C$1001,$B$11,'Raw Data'!$M$2:$M$1001,$B$12,'Raw Data'!$B$2:$B$1001,">="&$B$13,'Raw Data'!$B$2:$B$1001,"<="&$B$14,'Raw Data'!$X$2:$X$1001,B23) -> 389078.76 | D23: =COUNTIFS('Raw Data'!$D$2:$D$1001,$B$9,'Raw Data'!$G$2:$G$1001,$B$10,'Raw Data'!$C$2:$C$1001,$B$11,'Raw Data'!$M$2:$M$1001,$B$12,'Raw Data'!$B$2:$B$1001,">="&$B$13,'Raw Data'!$B$2:$B$1001,"<="&$B$14,'Raw Data'!$X$2:$X$1001,B23) -> 72
A24: =Analysis!B172 -> Jun-23 | B24: =Analysis!A172 -> 45107 | C24: =SUMIFS('Raw Data'!$E$2:$E$1001,'Raw Data'!$D$2:$D$1001,$B$9,'Raw Data'!$G$2:$G$1001,$B$10,'Raw Data'!$C$2:$C$1001,$B$11,'Raw Data'!$M$2:$M$1001,$B$12,'Raw Data'!$B$2:$B$1001,">="&$B$13,'Raw Data'!$B$2:$B$1001,"<="&$B$14,'Raw Data'!$X$2:$X$1001,B24) -> 418458.34 | D24: =COUNTIFS('Raw Data'!$D$2:$D$1001,$B$9,'Raw Data'!$G$2:$G$1001,$B$10,'Raw Data'!$C$2:$C$1001,$B$11,'Raw Data'!$M$2:$M$1001,$B$12,'Raw Data'!$B$2:$B$1001,">="&$B$13,'Raw Data'!$B$2:$B$1001,"<="&$B$14,'Raw Data'!$X$2:$X$1001,B24) -> 92
A25: =Analysis!B173 -> Jul-23 | B25: =Analysis!A173 -> 45138 | C25: =SUMIFS('Raw Data'!$E$2:$E$1001,'Raw Data'!$D$2:$D$1001,$B$9,'Raw Data'!$G$2:$G$1001,$B$10,'Raw Data'!$C$2:$C$1001,$B$11,'Raw Data'!$M$2:$M$1001,$B$12,'Raw Data'!$B$2:$B$1001,">="&$B$13,'Raw Data'!$B$2:$B$1001,"<="&$B$14,'Raw Data'!$X$2:$X$1001,B25) -> 374242.88 | D25: =COUNTIFS('Raw Data'!$D$2:$D$1001,$B$9,'Raw Data'!$G$2:$G$1001,$B$10,'Raw Data'!$C$2:$C$1001,$B$11,'Raw Data'!$M$2:$M$1001,$B$12,'Raw Data'!$B$2:$B$1001,">="&$B$13,'Raw Data'!$B$2:$B$1001,"<="&$B$14,'Raw Data'!$X$2:$X$1001,B25) -> 68
A26: =Analysis!B174 -> Aug-23 | B26: =Analysis!A174 -> 45169 | C26: =SUMIFS('Raw Data'!$E$2:$E$1001,'Raw Data'!$D$2:$D$1001,$B$9,'Raw Data'!$G$2:$G$1001,$B$10,'Raw Data'!$C$2:$C$1001,$B$11,'Raw Data'!$M$2:$M$1001,$B$12,'Raw Data'!$B$2:$B$1001,">="&$B$13,'Raw Data'!$B$2:$B$1001,"<="&$B$14,'Raw Data'!$X$2:$X$1001,B26) -> 443171.28 | D26: =COUNTIFS('Raw Data'!$D$2:$D$1001,$B$9,'Raw Data'!$G$2:$G$1001,$B$10,'Raw Data'!$C$2:$C$1001,$B$11,'Raw Data'!$M$2:$M$1001,$B$12,'Raw Data'!$B$2:$B$1001,">="&$B$13,'Raw Data'!$B$2:$B$1001,"<="&$B$14,'Raw Data'!$X$2:$X$1001,B26) -> 93
A27: =Analysis!B175 -> Sep-23 | B27: =Analysis!A175 -> 45199 | C27: =SUMIFS('Raw Data'!$E$2:$E$1001,'Raw Data'!$D$2:$D$1001,$B$9,'Raw Data'!$G$2:$G$1001,$B$10,'Raw Data'!$C$2:$C$1001,$B$11,'Raw Data'!$M$2:$M$1001,$B$12,'Raw Data'!$B$2:$B$1001,">="&$B$13,'Raw Data'!$B$2:$B$1001,"<="&$B$14,'Raw Data'!$X$2:$X$1001,B27) -> 367837.6 | D27: =COUNTIFS('Raw Data'!$D$2:$D$1001,$B$9,'Raw Data'!$G$2:$G$1001,$B$10,'Raw Data'!$C$2:$C$1001,$B$11,'Raw Data'!$M$2:$M$1001,$B$12,'Raw Data'!$B$2:$B$1001,">="&$B$13,'Raw Data'!$B$2:$B$1001,"<="&$B$14,'Raw Data'!$X$2:$X$1001,B27) -> 68
A28: =Analysis!B176 -> Oct-23 | B28: =Analysis!A176 -> 45230 | C28: =SUMIFS('Raw Data'!$E$2:$E$1001,'Raw Data'!$D$2:$D$1001,$B$9,'Raw Data'!$G$2:$G$1001,$B$10,'Raw Data'!$C$2:$C$1001,$B$11,'Raw Data'!$M$2:$M$1001,$B$12,'Raw Data'!$B$2:$B$1001,">="&$B$13,'Raw Data'!$B$2:$B$1001,"<="&$B$14,'Raw Data'!$X$2:$X$1001,B28) -> 460378.78 | D28: =COUNTIFS('Raw Data'!$D$2:$D$1001,$B$9,'Raw Data'!$G$2:$G$1001,$B$10,'Raw Data'!$C$2:$C$1001,$B$11,'Raw Data'!$M$2:$M$1001,$B$12,'Raw Data'!$B$2:$B$1001,">="&$B$13,'Raw Data'!$B$2:$B$1001,"<="&$B$14,'Raw Data'!$X$2:$X$1001,B28) -> 88
A29: =Analysis!B177 -> Nov-23 | B29: =Analysis!A177 -> 45260 | C29: =SUMIFS('Raw Data'!$E$2:$E$1001,'Raw Data'!$D$2:$D$1001,$B$9,'Raw Data'!$G$2:$G$1001,$B$10,'Raw Data'!$C$2:$C$1001,$B$11,'Raw Data'!$M$2:$M$1001,$B$12,'Raw Data'!$B$2:$B$1001,">="&$B$13,'Raw Data'!$B$2:$B$1001,"<="&$B$14,'Raw Data'!$X$2:$X$1001,B29) -> 467482.9 | D29: =COUNTIFS('Raw Data'!$D$2:$D$1001,$B$9,'Raw Data'!$G$2:$G$1001,$B$10,'Raw Data'!$C$2:$C$1001,$B$11,'Raw Data'!$M$2:$M$1001,$B$12,'Raw Data'!$B$2:$B$1001,">="&$B$13,'Raw Data'!$B$2:$B$1001,"<="&$B$14,'Raw Data'!$X$2:$X$1001,B29) -> 95
A30: =Analysis!B178 -> Dec-23 | B30: =Analysis!A178 -> 45291 | C30: =SUMIFS('Raw Data'!$E$2:$E$1001,'Raw Data'!$D$2:$D$1001,$B$9,'Raw Data'!$G$2:$G$1001,$B$10,'Raw Data'!$C$2:$C$1001,$B$11,'Raw Data'!$M$2:$M$1001,$B$12,'Raw Data'!$B$2:$B$1001,">="&$B$13,'Raw Data'!$B$2:$B$1001,"<="&$B$14,'Raw Data'!$X$2:$X$1001,B30) -> 392643.58 | D30: =COUNTIFS('Raw Data'!$D$2:$D$1001,$B$9,'Raw Data'!$G$2:$G$1001,$B$10,'Raw Data'!$C$2:$C$1001,$B$11,'Raw Data'!$M$2:$M$1001,$B$12,'Raw Data'!$B$2:$B$1001,">="&$B$13,'Raw Data'!$B$2:$B$1001,"<="&$B$14,'Raw Data'!$X$2:$X$1001,B30) -> 85
A31: =Analysis!B179 -> Jan-24 | B31: =Analysis!A179 -> 45322 | C31: =SUMIFS('Raw Data'!$E$2:$E$1001,'Raw Data'!$D$2:$D$1001,$B$9,'Raw Data'!$G$2:$G$1001,$B$10,'Raw Data'!$C$2:$C$1001,$B$11,'Raw Data'!$M$2:$M$1001,$B$12,'Raw Data'!$B$2:$B$1001,">="&$B$13,'Raw Data'!$B$2:$B$1001,"<="&$B$14,'Raw Data'!$X$2:$X$1001,B31) -> 19328.01 | D31: =COUNTIFS('Raw Data'!$D$2:$D$1001,$B$9,'Raw Data'!$G$2:$G$1001,$B$10,'Raw Data'!$C$2:$C$1001,$B$11,'Raw Data'!$M$2:$M$1001,$B$12,'Raw Data'!$B$2:$B$1001,">="&$B$13,'Raw Data'!$B$2:$B$1001,"<="&$B$14,'Raw Data'!$X$2:$X$1001,B31) -> 3
A34: Region | B34: Sales | C34: Transactions
A35: East | B35: =SUMIFS('Raw Data'!$E$2:$E$1001,'Raw Data'!$D$2:$D$1001,$B$9,'Raw Data'!$G$2:$G$1001,$B$10,'Raw Data'!$C$2:$C$1001,$B$11,'Raw Data'!$M$2:$M$1001,$B$12,'Raw Data'!$B$2:$B$1001,">="&$B$13,'Raw Data'!$B$2:$B$1001,"<="&$B$14,'Raw Data'!$D$2:$D$1001,A35) -> 1259792.9 | C35: =COUNTIFS('Raw Data'!$D$2:$D$1001,$B$9,'Raw Data'!$G$2:$G$1001,$B$10,'Raw Data'!$C$2:$C$1001,$B$11,'Raw Data'!$M$2:$M$1001,$B$12,'Raw Data'!$B$2:$B$1001,">="&$B$13,'Raw Data'!$B$2:$B$1001,"<="&$B$14,'Raw Data'!$D$2:$D$1001,A35) -> 263
A36: North | B36: =SUMIFS('Raw Data'!$E$2:$E$1001,'Raw Data'!$D$2:$D$1001,$B$9,'Raw Data'!$G$2:$G$1001,$B$10,'Raw Data'!$C$2:$C$1001,$B$11,'Raw Data'!$M$2:$M$1001,$B$12,'Raw Data'!$B$2:$B$1001,">="&$B$13,'Raw Data'!$B$2:$B$1001,"<="&$B$14,'Raw Data'!$D$2:$D$1001,A36) -> 1369612.5 | C36: =COUNTIFS('Raw Data'!$D$2:$D$1001,$B$9,'Raw Data'!$G$2:$G$1001,$B$10,'Raw Data'!$C$2:$C$1001,$B$11,'Raw Data'!$M$2:$M$1001,$B$12,'Raw Data'!$B$2:$B$1001,">="&$B$13,'Raw Data'!$B$2:$B$1001,"<="&$B$14,'Raw Data'!$D$2:$D$1001,A36) -> 267
A37: South | B37: =SUMIFS('Raw Data'!$E$2:$E$1001,'Raw Data'!$D$2:$D$1001,$B$9,'Raw Data'!$G$2:$G$1001,$B$10,'Raw Data'!$C$2:$C$1001,$B$11,'Raw Data'!$M$2:$M$1001,$B$12,'Raw Data'!$B$2:$B$1001,">="&$B$13,'Raw Data'!$B$2:$B$1001,"<="&$B$14,'Raw Data'!$D$2:$D$1001,A37) -> 1154250.9 | C37: =COUNTIFS('Raw Data'!$D$2:$D$1001,$B$9,'Raw Data'!$G$2:$G$1001,$B$10,'Raw Data'!$C$2:$C$1001,$B$11,'Raw Data'!$M$2:$M$1001,$B$12,'Raw Data'!$B$2:$B$1001,">="&$B$13,'Raw Data'!$B$2:$B$1001,"<="&$B$14,'Raw Data'!$D$2:$D$1001,A37) -> 226
A38: West | B38: =SUMIFS('Raw Data'!$E$2:$E$1001,'Raw Data'!$D$2:$D$1001,$B$9,'Raw Data'!$G$2:$G$1001,$B$10,'Raw Data'!$C$2:$C$1001,$B$11,'Raw Data'!$M$2:$M$1001,$B$12,'Raw Data'!$B$2:$B$1001,">="&$B$13,'Raw Data'!$B$2:$B$1001,"<="&$B$14,'Raw Data'!$D$2:$D$1001,A38) -> 1235608.9 | C38: =COUNTIFS('Raw Data'!$D$2:$D$1001,$B$9,'Raw Data'!$G$2:$G$1001,$B$10,'Raw Data'!$C$2:$C$1001,$B$11,'Raw Data'!$M$2:$M$1001,$B$12,'Raw Data'!$B$2:$B$1001,">="&$B$13,'Raw Data'!$B$2:$B$1001,"<="&$B$14,'Raw Data'!$D$2:$D$1001,A38) -> 244
A40: Category | B40: Sales | C40: Transactions
A41: Clothing | B41: =SUMIFS('Raw Data'!$E$2:$E$1001,'Raw Data'!$D$2:$D$1001,$B$9,'Raw Data'!$G$2:$G$1001,$B$10,'Raw Data'!$C$2:$C$1001,$B$11,'Raw Data'!$M$2:$M$1001,$B$12,'Raw Data'!$B$2:$B$1001,">="&$B$13,'Raw Data'!$B$2:$B$1001,"<="&$B$14,'Raw Data'!$G$2:$G$1001,A41) -> 1313474.4 | C41: =COUNTIFS('Raw Data'!$D$2:$D$1001,$B$9,'Raw Data'!$G$2:$G$1001,$B$10,'Raw Data'!$C$2:$C$1001,$B$11,'Raw Data'!$M$2:$M$1001,$B$12,'Raw Data'!$B$2:$B$1001,">="&$B$13,'Raw Data'!$B$2:$B$1001,"<="&$B$14,'Raw Data'!$G$2:$G$1001,A41) -> 268
A42: Electronics | B42: =SUMIFS('Raw Data'!$E$2:$E$1001,'Raw Data'!$D$2:$D$1001,$B$9,'Raw Data'!$G$2:$G$1001,$B$10,'Raw Data'!$C$2:$C$1001,$B$11,'Raw Data'!$M$2:$M$1001,$B$12,'Raw Data'!$B$2:$B$1001,">="&$B$13,'Raw Data'!$B$2:$B$1001,"<="&$B$14,'Raw Data'!$G$2:$G$1001,A42) -> 1243499.6 | C42: =COUNTIFS('Raw Data'!$D$2:$D$1001,$B$9,'Raw Data'!$G$2:$G$1001,$B$10,'Raw Data'!$C$2:$C$1001,$B$11,'Raw Data'!$M$2:$M$1001,$B$12,'Raw Data'!$B$2:$B$1001,">="&$B$13,'Raw Data'!$B$2:$B$1001,"<="&$B$14,'Raw Data'!$G$2:$G$1001,A42) -> 246
A43: Food | B43: =SUMIFS('Raw Data'!$E$2:$E$1001,'Raw Data'!$D$2:$D$1001,$B$9,'Raw Data'!$G$2:$G$1001,$B$10,'Raw Data'!$C$2:$C$1001,$B$11,'Raw Data'!$M$2:$M$1001,$B$12,'Raw Data'!$B$2:$B$1001,">="&$B$13,'Raw Data'!$B$2:$B$1001,"<="&$B$14,'Raw Data'!$G$2:$G$1001,A43) -> 1201773.5 | C43: =COUNTIFS('Raw Data'!$D$2:$D$1001,$B$9,'Raw Data'!$G$2:$G$1001,$B$10,'Raw Data'!$C$2:$C$1001,$B$11,'Raw Data'!$M$2:$M$1001,$B$12,'Raw Data'!$B$2:$B$1001,">="&$B$13,'Raw Data'!$B$2:$B$1001,"<="&$B$14,'Raw Data'!$G$2:$G$1001,A43) -> 226
A44: Furniture | B44: =SUMIFS('Raw Data'!$E$2:$E$1001,'Raw Data'!$D$2:$D$1001,$B$9,'Raw Data'!$G$2:$G$1001,$B$10,'Raw Data'!$C$2:$C$1001,$B$11,'Raw Data'!$M$2:$M$1001,$B$12,'Raw Data'!$B$2:$B$1001,">="&$B$13,'Raw Data'!$B$2:$B$1001,"<="&$B$14,'Raw Data'!$G$2:$G$1001,A44) -> 1260517.7 | C44: =COUNTIFS('Raw Data'!$D$2:$D$1001,$B$9,'Raw Data'!$G$2:$G$1001,$B$10,'Raw Data'!$C$2:$C$1001,$B$11,'Raw Data'!$M$2:$M$1001,$B$12,'Raw Data'!$B$2:$B$1001,">="&$B$13,'Raw Data'!$B$2:$B$1001,"<="&$B$14,'Raw Data'!$G$2:$G$1001,A44) -> 260
A46: Sales rep | B46: Sales | C46: Transactions
A47: Alice | B47: =SUMIFS('Raw Data'!$E$2:$E$1001,'Raw Data'!$D$2:$D$1001,$B$9,'Raw Data'!$G$2:$G$1001,$B$10,'Raw Data'!$C$2:$C$1001,$B$11,'Raw Data'!$M$2:$M$1001,$B$12,'Raw Data'!$B$2:$B$1001,">="&$B$13,'Raw Data'!$B$2:$B$1001,"<="&$B$14,'Raw Data'!$C$2:$C$1001,A47) -> 965541.77 | C47: =COUNTIFS('Raw Data'!$D$2:$D$1001,$B$9,'Raw Data'!$G$2:$G$1001,$B$10,'Raw Data'!$C$2:$C$1001,$B$11,'Raw Data'!$M$2:$M$1001,$B$12,'Raw Data'!$B$2:$B$1001,">="&$B$13,'Raw Data'!$B$2:$B$1001,"<="&$B$14,'Raw Data'!$C$2:$C$1001,A47) -> 192
A48: Bob | B48: =SUMIFS('Raw Data'!$E$2:$E$1001,'Raw Data'!$D$2:$D$1001,$B$9,'Raw Data'!$G$2:$G$1001,$B$10,'Raw Data'!$C$2:$C$1001,$B$11,'Raw Data'!$M$2:$M$1001,$B$12,'Raw Data'!$B$2:$B$1001,">="&$B$13,'Raw Data'!$B$2:$B$1001,"<="&$B$14,'Raw Data'!$C$2:$C$1001,A48) -> 1080990.6 | C48: =COUNTIFS('Raw Data'!$D$2:$D$1001,$B$9,'Raw Data'!$G$2:$G$1001,$B$10,'Raw Data'!$C$2:$C$1001,$B$11,'Raw Data'!$M$2:$M$1001,$B$12,'Raw Data'!$B$2:$B$1001,">="&$B$13,'Raw Data'!$B$2:$B$1001,"<="&$B$14,'Raw Data'!$C$2:$C$1001,A48) -> 208
A49: Charlie | B49: =SUMIFS('Raw Data'!$E$2:$E$1001,'Raw Data'!$D$2:$D$1001,$B$9,'Raw Data'!$G$2:$G$1001,$B$10,'Raw Data'!$C$2:$C$1001,$B$11,'Raw Data'!$M$2:$M$1001,$B$12,'Raw Data'!$B$2:$B$1001,">="&$B$13,'Raw Data'!$B$2:$B$1001,"<="&$B$14,'Raw Data'!$C$2:$C$1001,A49) -> 860811.48 | C49: =COUNTIFS('Raw Data'!$D$2:$D$1001,$B$9,'Raw Data'!$G$2:$G$1001,$B$10,'Raw Data'!$C$2:$C$1001,$B$11,'Raw Data'!$M$2:$M$1001,$B$12,'Raw Data'!$B$2:$B$1001,">="&$B$13,'Raw Data'!$B$2:$B$1001,"<="&$B$14,'Raw Data'!$C$2:$C$1001,A49) -> 169
A50: David | B50: =SUMIFS('Raw Data'!$E$2:$E$1001,'Raw Data'!$D$2:$D$1001,$B$9,'Raw Data'!$G$2:$G$1001,$B$10,'Raw Data'!$C$2:$C$1001,$B$11,'Raw Data'!$M$2:$M$1001,$B$12,'Raw Data'!$B$2:$B$1001,">="&$B$13,'Raw Data'!$B$2:$B$1001,"<="&$B$14,'Raw Data'!$C$2:$C$1001,A50) -> 1141737.4 | C50: =COUNTIFS('Raw Data'!$D$2:$D$1001,$B$9,'Raw Data'!$G$2:$G$1001,$B$10,'Raw Data'!$C$2:$C$1001,$B$11,'Raw Data'!$M$2:$M$1001,$B$12,'Raw Data'!$B$2:$B$1001,">="&$B$13,'Raw Data'!$B$2:$B$1001,"<="&$B$14,'Raw Data'!$C$2:$C$1001,A50) -> 222
A51: Eve | B51: =SUMIFS('Raw Data'!$E$2:$E$1001,'Raw Data'!$D$2:$D$1001,$B$9,'Raw Data'!$G$2:$G$1001,$B$10,'Raw Data'!$C$2:$C$1001,$B$11,'Raw Data'!$M$2:$M$1001,$B$12,'Raw Data'!$B$2:$B$1001,">="&$B$13,'Raw Data'!$B$2:$B$1001,"<="&$B$14,'Raw Data'!$C$2:$C$1001,A51) -> 970183.99 | C51: =COUNTIFS('Raw Data'!$D$2:$D$1001,$B$9,'Raw Data'!$G$2:$G$1001,$B$10,'Raw Data'!$C$2:$C$1001,$B$11,'Raw Data'!$M$2:$M$1001,$B$12,'Raw Data'!$B$2:$B$1001,">="&$B$13,'Raw Data'!$B$2:$B$1001,"<="&$B$14,'Raw Data'!$C$2:$C$1001,A51) -> 209
A53: Channel | B53: Sales | C53: Transactions
A54: Online | B54: =SUMIFS('Raw Data'!$E$2:$E$1001,'Raw Data'!$D$2:$D$1001,$B$9,'Raw Data'!$G$2:$G$1001,$B$10,'Raw Data'!$C$2:$C$1001,$B$11,'Raw Data'!$M$2:$M$1001,$B$12,'Raw Data'!$B$2:$B$1001,">="&$B$13,'Raw Data'!$B$2:$B$1001,"<="&$B$14,'Raw Data'!$M$2:$M$1001,A54) -> 2458833.9 | C54: =COUNTIFS('Raw Data'!$D$2:$D$1001,$B$9,'Raw Data'!$G$2:$G$1001,$B$10,'Raw Data'!$C$2:$C$1001,$B$11,'Raw Data'!$M$2:$M$1001,$B$12,'Raw Data'!$B$2:$B$1001,">="&$B$13,'Raw Data'!$B$2:$B$1001,"<="&$B$14,'Raw Data'!$M$2:$M$1001,A54) -> 488
A55: Retail | B55: =SUMIFS('Raw Data'!$E$2:$E$1001,'Raw Data'!$D$2:$D$1001,$B$9,'Raw Data'!$G$2:$G$1001,$B$10,'Raw Data'!$C$2:$C$1001,$B$11,'Raw Data'!$M$2:$M$1001,$B$12,'Raw Data'!$B$2:$B$1001,">="&$B$13,'Raw Data'!$B$2:$B$1001,"<="&$B$14,'Raw Data'!$M$2:$M$1001,A55) -> 2560431.3 | C55: =COUNTIFS('Raw Data'!$D$2:$D$1001,$B$9,'Raw Data'!$G$2:$G$1001,$B$10,'Raw Data'!$C$2:$C$1001,$B$11,'Raw Data'!$M$2:$M$1001,$B$12,'Raw Data'!$B$2:$B$1001,">="&$B$13,'Raw Data'!$B$2:$B$1001,"<="&$B$14,'Raw Data'!$M$2:$M$1001,A55) -> 512
A58: Discount band | B58: Transactions | C58: Net margin %
A59: 0-9% | B59: =COUNTIFS('Raw Data'!$D$2:$D$1001,$B$9,'Raw Data'!$G$2:$G$1001,$B$10,'Raw Data'!$C$2:$C$1001,$B$11,'Raw Data'!$M$2:$M$1001,$B$12,'Raw Data'!$B$2:$B$1001,">="&$B$13,'Raw Data'!$B$2:$B$1001,"<="&$B$14,'Raw Data'!$U$2:$U$1001,A59) -> 313 | C59: =IFERROR(SUMIFS('Raw Data'!$R$2:$R$1001,'Raw Data'!$D$2:$D$1001,$B$9,'Raw Data'!$G$2:$G$1001,$B$10,'Raw Data'!$C$2:$C$1001,$B$11,'Raw Data'!$M$2:$M$1001,$B$12,'Raw Data'!$B$2:$B$1001,">="&$B$13,'Raw Data'!$B$2:$B$1001,"<="&$B$14,'Raw Data'!$U$2:$U$1001,A59)/SUMIFS('Raw Data'!$P$2:$P$1001,'Raw Data'!$D$2:$D$1001,$B$9,'Raw Data'!$G$2:$G$1001,$B$10,'Raw Data'!$C$2:$C$1001,$B$11,'Raw Data'!$M$2:$M$1001,$B$12,'Raw Data'!$B$2:$B$1001,">="&$B$13,'Raw Data'!$B$2:$B$1001,"<="&$B$14,'Raw Data'!$U$2:$U$1001,A59),0) -> 0.045253605
A60: 10-19% | B60: =COUNTIFS('Raw Data'!$D$2:$D$1001,$B$9,'Raw Data'!$G$2:$G$1001,$B$10,'Raw Data'!$C$2:$C$1001,$B$11,'Raw Data'!$M$2:$M$1001,$B$12,'Raw Data'!$B$2:$B$1001,">="&$B$13,'Raw Data'!$B$2:$B$1001,"<="&$B$14,'Raw Data'!$U$2:$U$1001,A60) -> 307 | C60: =IFERROR(SUMIFS('Raw Data'!$R$2:$R$1001,'Raw Data'!$D$2:$D$1001,$B$9,'Raw Data'!$G$2:$G$1001,$B$10,'Raw Data'!$C$2:$C$1001,$B$11,'Raw Data'!$M$2:$M$1001,$B$12,'Raw Data'!$B$2:$B$1001,">="&$B$13,'Raw Data'!$B$2:$B$1001,"<="&$B$14,'Raw Data'!$U$2:$U$1001,A60)/SUMIFS('Raw Data'!$P$2:$P$1001,'Raw Data'!$D$2:$D$1001,$B$9,'Raw Data'!$G$2:$G$1001,$B$10,'Raw Data'!$C$2:$C$1001,$B$11,'Raw Data'!$M$2:$M$1001,$B$12,'Raw Data'!$B$2:$B$1001,">="&$B$13,'Raw Data'!$B$2:$B$1001,"<="&$B$14,'Raw Data'!$U$2:$U$1001,A60),0) -> -0.057639642
A61: 20%+ | B61: =COUNTIFS('Raw Data'!$D$2:$D$1001,$B$9,'Raw Data'!$G$2:$G$1001,$B$10,'Raw Data'!$C$2:$C$1001,$B$11,'Raw Data'!$M$2:$M$1001,$B$12,'Raw Data'!$B$2:$B$1001,">="&$B$13,'Raw Data'!$B$2:$B$1001,"<="&$B$14,'Raw Data'!$U$2:$U$1001,A61) -> 380 | C61: =IFERROR(SUMIFS('Raw Data'!$R$2:$R$1001,'Raw Data'!$D$2:$D$1001,$B$9,'Raw Data'!$G$2:$G$1001,$B$10,'Raw Data'!$C$2:$C$1001,$B$11,'Raw Data'!$M$2:$M$1001,$B$12,'Raw Data'!$B$2:$B$1001,">="&$B$13,'Raw Data'!$B$2:$B$1001,"<="&$B$14,'Raw Data'!$U$2:$U$1001,A61)/SUMIFS('Raw Data'!$P$2:$P$1001,'Raw Data'!$D$2:$D$1001,$B$9,'Raw Data'!$G$2:$G$1001,$B$10,'Raw Data'!$C$2:$C$1001,$B$11,'Raw Data'!$M$2:$M$1001,$B$12,'Raw Data'!$B$2:$B$1001,">="&$B$13,'Raw Data'!$B$2:$B$1001,"<="&$B$14,'Raw Data'!$U$2:$U$1001,A61),0) -> -0.20766012
A65: Selected-view KPIs
A66: Sales | B66: =SUMIFS('Raw Data'!$E$2:$E$1001,'Raw Data'!$D$2:$D$1001,$B$9,'Raw Data'!$G$2:$G$1001,$B$10,'Raw Data'!$C$2:$C$1001,$B$11,'Raw Data'!$M$2:$M$1001,$B$12,'Raw Data'!$B$2:$B$1001,">="&$B$13,'Raw Data'!$B$2:$B$1001,"<="&$B$14) -> 5019265.2
A67: Transactions | B67: =COUNTIFS('Raw Data'!$D$2:$D$1001,$B$9,'Raw Data'!$G$2:$G$1001,$B$10,'Raw Data'!$C$2:$C$1001,$B$11,'Raw Data'!$M$2:$M$1001,$B$12,'Raw Data'!$B$2:$B$1001,">="&$B$13,'Raw Data'!$B$2:$B$1001,"<="&$B$14) -> 1000
A68: Units | B68: =SUMIFS('Raw Data'!$F$2:$F$1001,'Raw Data'!$D$2:$D$1001,$B$9,'Raw Data'!$G$2:$G$1001,$B$10,'Raw Data'!$C$2:$C$1001,$B$11,'Raw Data'!$M$2:$M$1001,$B$12,'Raw Data'!$B$2:$B$1001,">="&$B$13,'Raw Data'!$B$2:$B$1001,"<="&$B$14) -> 25355
A69: Avg discount | B69: =IFERROR(AVERAGEIFS('Raw Data'!$K$2:$K$1001,'Raw Data'!$D$2:$D$1001,$B$9,'Raw Data'!$G$2:$G$1001,$B$10,'Raw Data'!$C$2:$C$1001,$B$11,'Raw Data'!$M$2:$M$1001,$B$12,'Raw Data'!$B$2:$B$1001,">="&$B$13,'Raw Data'!$B$2:$B$1001,"<="&$B$14),0) -> 0.15239
A70: Net margin % | B70: =IFERROR(SUMIFS('Raw Data'!$R$2:$R$1001,'Raw Data'!$D$2:$D$1001,$B$9,'Raw Data'!$G$2:$G$1001,$B$10,'Raw Data'!$C$2:$C$1001,$B$11,'Raw Data'!$M$2:$M$1001,$B$12,'Raw Data'!$B$2:$B$1001,">="&$B$13,'Raw Data'!$B$2:$B$1001,"<="&$B$14)/SUMIFS('Raw Data'!$P$2:$P$1001,'Raw Data'!$D$2:$D$1001,$B$9,'Raw Data'!$G$2:$G$1001,$B$10,'Raw Data'!$C$2:$C$1001,$B$11,'Raw Data'!$M$2:$M$1001,$B$12,'Raw Data'!$B$2:$B$1001,">="&$B$13,'Raw Data'!$B$2:$B$1001,"<="&$B$14),0) -> -0.069629528
A71: Share of total sales | B71: =IF(Analysis!$B$35=0,0,B66/Analysis!$B$35) -> 1
A72: Filter state | B72: =IF(AND(Dashboard!B11="All",Dashboard!E11="All",Dashboard!H11="All",Dashboard!K11="All",Dashboard!N11<=Analysis!B12,Dashboard!Q11>=Analysis!B13),"Full dataset (no filters)","Filtered view") -> Full dataset (no filters)
